Workbook
Name carbon: 'MER Environment Data'!$A$11:$O$62
Name carbon_col: 'MER Environment Data'!$A$11:$O$11
Name code: 'EIA SEDS Codes'!$B$11:$D$770
Name code_col: 'EIA SEDS Codes'!$B$11:$D$11
Name emissions: Calibration!$A$6:$A$55
Name emissions_col: Calibration!$A$4:$A$4
Name forstata_cd: #REF!
Name forstata_cd_col: #REF!
Name forstata_ee: #REF!
Name forstata_ee_col: #REF!
Name gdp: 'MER GDP Data'!$A$11:$H$86
Name gdp_col: 'MER GDP Data'!$A$11:$H$11
Name sedsAnalysis: 'Carbon Intensity'!$A$4:$AO$54
Name sedsAnalysis: 'Intermediate (old)'!$A$5:$AT$64
Name sedsAnalysis: 'SEDS Data Processed'!$A$5:$DC$64
Name sedsAnalysis_col: 'Carbon Intensity'!#REF!
Name sedsAnalysis_col: 'Intermediate (old)'!$A$5:$AT$5
Name sedsAnalysis_col: 'SEDS Data Processed'!$A$5:$DC$5
Name sedsPE: 'SEDS Prices and Expenditures'!$C$1:$BC$310
Name sedsPE_col: 'SEDS Prices and Expenditures'!$C$1:$BC$1
Name sedsQ: 'SEDS Quantities'!$C$1:$BM$432
Name sedsQ_col: 'SEDS Quantities'!$C$1:$BM$1

Sheet Audit
A1: Last updated: 12/3/23
A3: Data
A4: Tab | B4: Description | C4: Source | D4: Link | E4: Access Date
A5: MER GDP Data | B5: Macroeconomic data reported by EIA. Originally from EIA | C5: MER Table C1, "Population, U.S. gross domestic product, and U.S. gross output" | D5: https://www.eia.gov/totalenergy/data/monthly/ | E5: 45212
A6: MER Quantity Data | B6: Primary Energy Use data reported by EIA. | C6: MER Table 1.1, "Primary energy overview" | D6: https://www.eia.gov/totalenergy/data/monthly/ | E6: 45212
A7: MER Environment Data | B7: Carbon emissions report by EIA. | C7: MER Table 11.1, "Carbon dioxide emissions from energy consumption: by source") | D7: https://www.eia.gov/totalenergy/data/monthly/ | E7: 45212
A9: Results
A10: Tab | B10: Description
A11: Calibration | B11: Calculates: (1) growth rate of CO2/Zd (cell G6) and (2) Climate damages as a % of output in 2020 (cell K13).

Sheet Results -->

Sheet Calibration
A1: Dataset: | C1: carbon
A2: Variable: | C2: Total Energy CO2 Emissions
A4: Year | B4: Total Fossil | C4: CO2 Emissions | D4: Carbon intensity of fossil energy
B5: (Quadrillion Btu) | C5: =VLOOKUP("unit",INDIRECT(C$1),MATCH(C$2,INDIRECT(C$1&"_col"),),) -> (Million Metric Tons of Carbon Dioxide) | D5: Ratio | F5: Growth Rate Calculation | J5: SCC Calculation
A6: 1973 | B6: ='MER Quantity Data'!E37 -> 61.592952 | C6: =VLOOKUP($A6,INDIRECT(C$1),MATCH(C$2,INDIRECT(C$1&"_col"),),) -> 4720.916 | D6: =IF(ISERROR(C6/B6),"",C6/B6) -> 76.647016 | F6: Annual: | G6: {=LOGEST(D33:D54)} -> 0.97271173 | H6: 98.109085 | J6: Variable | K6: Value | L6: Unit | M6: Notes
A7: 1974 | B7: ='MER Quantity Data'!E38 -> 60.152492 | C7: =VLOOKUP($A7,INDIRECT(C$1),MATCH(C$2,INDIRECT(C$1&"_col"),),) -> 4561.017 | D7: =IF(ISERROR(C7/B7),"",C7/B7) -> 75.82424 | J7: SCC in $2020 | K7: 185 | L7: dollars/tonne of CO2 | M7: Source: Rennert et al 2022 (full citation in paper)
A8: 1975 | B8: ='MER Quantity Data'!E39 -> 59.140884 | C8: =VLOOKUP($A8,INDIRECT(C$1),MATCH(C$2,INDIRECT(C$1&"_col"),),) -> 4427.937 | D8: =IF(ISERROR(C8/B8),"",C8/B8) -> 74.870998 | J8: 2020 Deflator | K8: ='MER GDP Data'!G84 -> 1.13784 | L8: $2020/$2012
A9: 1976 | B9: ='MER Quantity Data'!E40 -> 59.499382 | C9: =VLOOKUP($A9,INDIRECT(C$1),MATCH(C$2,INDIRECT(C$1&"_col"),),) -> 4694.612 | D9: =IF(ISERROR(C9/B9),"",C9/B9) -> 78.901862 | J9: SCC in $2012 | K9: =K7/K8 -> 162.58876 | L9: dollars/tonne of CO2
A10: 1977 | B10: ='MER Quantity Data'!E41 -> 60.374687 | C10: =VLOOKUP($A10,INDIRECT(C$1),MATCH(C$2,INDIRECT(C$1&"_col"),),) -> 4835.148 | D10: =IF(ISERROR(C10/B10),"",C10/B10) -> 80.085682 | J10: Emissions in 2020 | K10: ='MER Environment Data'!O60*1000000 -> 4580512000 | L10: tonnes
A11: 1978 | B11: ='MER Quantity Data'!E42 -> 61.069714 | C11: =VLOOKUP($A11,INDIRECT(C$1),MATCH(C$2,INDIRECT(C$1&"_col"),),) -> 4884.113 | D11: =IF(ISERROR(C11/B11),"",C11/B11) -> 79.976025 | J11: Damage in 2020 | K11: =K10*K9 -> 7.4473979e+11 | L11: dollars
A12: 1979 | B12: ='MER Quantity Data'!E43 -> 63.85871 | C12: =VLOOKUP($A12,INDIRECT(C$1),MATCH(C$2,INDIRECT(C$1&"_col"),),) -> 4949.897 | D12: =IF(ISERROR(C12/B12),"",C12/B12) -> 77.513263 | J12: Y in 2020 | K12: ='MER GDP Data'!F84*1000000000 -> 18509100000000 | L12: dollars
A13: 1980 | B13: ='MER Quantity Data'!E44 -> 65.163631 | C13: =VLOOKUP($A13,INDIRECT(C$1),MATCH(C$2,INDIRECT(C$1&"_col"),),) -> 4756.328 | D13: =IF(ISERROR(C13/B13),"",C13/B13) -> 72.990531 | J13: Fraction of Y Lost | K13: =K11/K12 -> 0.040236413
A14: 1981 | B14: ='MER Quantity Data'!E45 -> 65.011741 | C14: =VLOOKUP($A14,INDIRECT(C$1),MATCH(C$2,INDIRECT(C$1&"_col"),),) -> 4636.684 | D14: =IF(ISERROR(C14/B14),"",C14/B14) -> 71.320717
A15: 1982 | B15: ='MER Quantity Data'!E46 -> 64.292891 | C15: =VLOOKUP($A15,INDIRECT(C$1),MATCH(C$2,INDIRECT(C$1&"_col"),),) -> 4404.478 | D15: =IF(ISERROR(C15/B15),"",C15/B15) -> 68.506454
A16: 1983 | B16: ='MER Quantity Data'!E47 -> 61.639884 | C16: =VLOOKUP($A16,INDIRECT(C$1),MATCH(C$2,INDIRECT(C$1&"_col"),),) -> 4383.992 | D16: =IF(ISERROR(C16/B16),"",C16/B16) -> 71.122652
A17: 1984 | B17: ='MER Quantity Data'!E48 -> 66.465843 | C17: =VLOOKUP($A17,INDIRECT(C$1),MATCH(C$2,INDIRECT(C$1&"_col"),),) -> 4612.908 | D17: =IF(ISERROR(C17/B17),"",C17/B17) -> 69.402686
A18: 1985 | B18: ='MER Quantity Data'!E49 -> 65.595457 | C18: =VLOOKUP($A18,INDIRECT(C$1),MATCH(C$2,INDIRECT(C$1&"_col"),),) -> 4605.41 | D18: =IF(ISERROR(C18/B18),"",C18/B18) -> 70.209283
A19: 1986 | B19: ='MER Quantity Data'!E50 -> 64.889589 | C19: =VLOOKUP($A19,INDIRECT(C$1),MATCH(C$2,INDIRECT(C$1&"_col"),),) -> 4615.724 | D19: =IF(ISERROR(C19/B19),"",C19/B19) -> 71.131965
A20: 1987 | B20: ='MER Quantity Data'!E51 -> 65.659019 | C20: =VLOOKUP($A20,INDIRECT(C$1),MATCH(C$2,INDIRECT(C$1&"_col"),),) -> 4775.616 | D20: =IF(ISERROR(C20/B20),"",C20/B20) -> 72.733587
A21: 1988 | B21: ='MER Quantity Data'!E52 -> 67.255507 | C21: =VLOOKUP($A21,INDIRECT(C$1),MATCH(C$2,INDIRECT(C$1&"_col"),),) -> 4998.283 | D21: =IF(ISERROR(C21/B21),"",C21/B21) -> 74.317825
A22: 1989 | B22: ='MER Quantity Data'!E53 -> 67.256001 | C22: =VLOOKUP($A22,INDIRECT(C$1),MATCH(C$2,INDIRECT(C$1&"_col"),),) -> 5084.633 | D22: =IF(ISERROR(C22/B22),"",C22/B22) -> 75.601179
A23: 1990 | B23: ='MER Quantity Data'!E54 -> 68.490245 | C23: =VLOOKUP($A23,INDIRECT(C$1),MATCH(C$2,INDIRECT(C$1&"_col"),),) -> 5037.975 | D23: =IF(ISERROR(C23/B23),"",C23/B23) -> 73.557556
A24: 1991 | B24: ='MER Quantity Data'!E55 -> 68.154712 | C24: =VLOOKUP($A24,INDIRECT(C$1),MATCH(C$2,INDIRECT(C$1&"_col"),),) -> 4990.804 | D24: =IF(ISERROR(C24/B24),"",C24/B24) -> 73.227571
A25: 1992 | B25: ='MER Quantity Data'!E56 -> 68.025635 | C25: =VLOOKUP($A25,INDIRECT(C$1),MATCH(C$2,INDIRECT(C$1&"_col"),),) -> 5088.755 | D25: =IF(ISERROR(C25/B25),"",C25/B25) -> 74.806431
... A54: 2021 | B54: ='MER Quantity Data'!E85 -> 93.829441 | C54: =VLOOKUP($A54,INDIRECT(C$1),MATCH(C$2,INDIRECT(C$1&"_col"),),) -> 4903.572 | D54: =IF(ISERROR(C54/B54),"",C54/B54) -> 52.260484
A55: 2022

Sheet Data -->

Sheet MER GDP Data
A1: U.S. Energy Information Administration
A2: September 2023 Monthly Energy Review
A4: =HYPERLINK("http://www.eia.gov/totalenergy/data/monthly/dataunits.cfm","Note: Information about data precision.") -> Note: Information about data precision.
A6: Release Date: September 26, 2023
A7: Next Update: October 26, 2023
A9: Table C1 Population, U.S. Gross Domestic Product, and U.S. Gross Output
A11: Year | B11: Total Resident Population, United States | C11: Total Resident Population, World | D11: United States Share of World Population | E11: U.S. Gross Domestic Product, Nominal | F11: U.S. Gross Domestic Product, Real | G11: U.S. Gross Domestic Product Implicit Price Deflator | H11: U.S. Gross Output, Nominal Dollars
A12: units | B12: (Million people) | C12: (Million people) | D12: (Percent) | E12: (Billion Dollars) | F12: (Billion chained (2012) dollars) | G12: (2012 = 1.00000) | H12: (Billion Dollars)
A13: 1949 | B13: 149.2 | C13: Not Available | D13: Not Available | E13: 272.5 | F13: 2108 | G13: 0.12926 | H13: 510.3
A14: 1950 | B14: 152.3 | C14: 2557.6 | D14: 6 | E14: 299.8 | F14: 2291.1 | G14: 0.13087 | H14: 577.8
A15: 1951 | B15: 154.9 | C15: 2594.9 | D15: 6 | E15: 346.9 | F15: 2475.4 | G15: 0.14014 | H15: 654.6
A16: 1952 | B16: 157.6 | C16: 2636.8 | D16: 6 | E16: 367.3 | F16: 2576.7 | G16: 0.14256 | H16: 686
A17: 1953 | B17: 160.2 | C17: 2682.1 | D17: 6 | E17: 389.2 | F17: 2697.5 | G17: 0.14429 | H17: 739.2
A18: 1954 | B18: 163 | C18: 2730.2 | D18: 6 | E18: 390.5 | F18: 2681.9 | G18: 0.14563 | H18: 739.9
A19: 1955 | B19: 165.9 | C19: 2782.1 | D19: 6 | E19: 425.5 | F19: 2873.2 | G19: 0.14809 | H19: 802.6
A20: 1956 | B20: 168.9 | C20: 2835.3 | D20: 6 | E20: 449.4 | F20: 2934.4 | G20: 0.15313 | H20: 841.8
A21: 1957 | B21: 172 | C21: 2891.4 | D21: 5.9 | E21: 474 | F21: 2996.2 | G21: 0.15821 | H21: 875.5
A22: 1958 | B22: 174.9 | C22: 2948.2 | D22: 5.9 | E22: 481.2 | F22: 2974 | G22: 0.16181 | H22: 897.5
A23: 1959 | B23: 177.8 | C23: 3000.7 | D23: 5.9 | E23: 521.7 | F23: 3180.2 | G23: 0.16403 | H23: 978.9
A24: 1960 | B24: 180.7 | C24: 3043 | D24: 5.9 | E24: 542.4 | F24: 3262.1 | G24: 0.16627 | H24: 1006
A25: 1961 | B25: 183.7 | C25: 3084.1 | D25: 6 | E25: 562.2 | F25: 3345.7 | G25: 0.16804 | H25: 1029.7
... A86: 2022 | B86: 333.3 | C86: 7905.3 | D86: 4.2 | E86: 25462.7 | F86: 20014.1 | G86: 1.27224 | H86: 45962.8

Sheet MER Quantity Data
A1: U.S. Energy Information Administration
A2: September 2023 Monthly Energy Review
A4: =HYPERLINK("http://www.eia.gov/totalenergy/data/monthly/dataunits.cfm","Note: Information about data precision.") -> Note: Information about data precision.
A6: Release Date: September 26, 2023
A7: Next Update: October 26, 2023
A9: Table 1.1 Primary Energy Overview
A11: Annual Total | B11: Total Fossil Fuels Production | C11: Nuclear Electric Power Production | D11: Total Renewable Energy Production | E11: Total Primary Energy Production | F11: Primary Energy Imports | G11: Primary Energy Exports | H11: Primary Energy Net Imports | I11: Primary Energy Stock Change and Other | J11: Total Fossil Fuels Consumption | K11: Nuclear Electric Power Consumption | L11: Total Renewable Energy Consumption | M11: Total Primary Energy Consumption
B12: (Quadrillion Btu) | C12: (Quadrillion Btu) | D12: (Quadrillion Btu) | E12: (Quadrillion Btu) | F12: (Quadrillion Btu) | G12: (Quadrillion Btu) | H12: (Quadrillion Btu) | I12: (Quadrillion Btu) | J12: (Quadrillion Btu) | K12: (Quadrillion Btu) | L12: (Quadrillion Btu) | M12: (Quadrillion Btu)
A13: 1949 | B13: 28.740479 | C13: 0 | D13: 1.872627 | E13: 30.613106 | F13: 1.448158 | G13: 1.59176 | H13: -0.143602 | I13: 0.396915 | J13: 28.988371 | K13: 0 | L13: 1.872627 | M13: 30.866419
A14: 1950 | B14: 32.553205 | C14: 0 | D14: 1.906525 | E14: 34.45973 | F14: 1.912887 | G14: 1.465322 | H14: 0.447565 | I14: -1.379921 | J14: 31.614755 | K14: 0 | L14: 1.906525 | M14: 33.527374
A15: 1951 | B15: 35.782118 | C15: 0 | D15: 1.8908 | E15: 37.672919 | F15: 1.892425 | G15: 2.621545 | H15: -0.729119 | I15: -1.057801 | J15: 33.987736 | K15: 0 | L15: 1.8908 | M15: 35.885997
A16: 1952 | B16: 34.964662 | C16: 0 | D16: 1.848694 | E16: 36.813356 | F16: 2.145984 | G16: 2.365131 | H16: -0.219147 | I16: -0.959659 | J16: 33.778116 | K16: 0 | L16: 1.848694 | M16: 35.63455
A17: 1953 | B17: 35.338361 | C17: 0 | D17: 1.792616 | E17: 37.130976 | F17: 2.313042 | G17: 1.866013 | H17: 0.447029 | I17: -0.976252 | J17: 34.802286 | K17: 0 | L17: 1.792616 | M17: 36.601753
A18: 1954 | B18: 33.752228 | C18: 0 | D18: 1.775242 | E18: 35.52747 | F18: 2.347876 | G18: 1.696301 | H18: 0.651575 | I18: -0.544362 | J18: 33.851458 | K18: 0 | L18: 1.775242 | M18: 35.634683
A19: 1955 | B19: 37.346797 | C19: 0 | D19: 1.82074 | E19: 39.167537 | F19: 2.789908 | G19: 2.285508 | H19: 0.504399 | I19: -0.4569 | J19: 37.380419 | K19: 0 | L19: 1.82074 | M19: 39.215038
A20: 1956 | B20: 39.75301 | C20: 0 | D20: 1.843178 | E20: 41.596188 | F20: 3.206741 | G20: 2.945377 | H20: 0.261364 | I20: -1.143199 | J20: 38.855656 | K20: 0 | L20: 1.843178 | M20: 40.714353
A21: 1957 | B21: 40.11844 | C21: 0.000112 | D21: 1.788598 | E21: 41.90715 | F21: 3.528983 | G21: 3.439441 | H21: 0.089541 | I21: -1.303379 | J21: 38.892315 | K21: 0.000112 | L21: 1.788598 | M21: 40.693313
A22: 1958 | B22: 37.205122 | C22: 0.001915 | D22: 1.813136 | E22: 39.020172 | F22: 3.884371 | G22: 2.049839 | H22: 1.834533 | I22: -0.347378 | J22: 38.680955 | K22: 0.001915 | L22: 1.813136 | M22: 40.507326
A23: 1959 | B23: 39.032065 | C23: 0.002187 | D23: 1.834493 | E23: 40.868746 | F23: 4.076278 | G23: 1.533808 | H23: 2.54247 | I23: -1.055097 | J23: 40.507312 | K23: 0.002187 | L23: 1.834493 | M23: 42.356119
A24: 1960 | B24: 39.854831 | C24: 0.006026 | D24: 1.829873 | E24: 41.69073 | F24: 4.187626 | G24: 1.477475 | H24: 2.710151 | I24: -0.45848 | J24: 42.091028 | K24: 0.006026 | L24: 1.829873 | M24: 43.942401
... A86: 2022 | B86: 81.592463 | C86: 8.046361 | D86: 8.304253 | E86: 97.943077 | F86: 21.506533 | G86: 27.338551 | H86: -5.832018 | I86: 2.681597 | J86: 78.517967 | K86: 8.046361 | L86: 8.087707 | M86: 94.792656

Sheet MER Environment Data
A1: U.S. Energy Information Administration
A2: September 2023 Monthly Energy Review
A4: =HYPERLINK("http://www.eia.gov/totalenergy/data/monthly/dataunits.cfm","Note: Information about data precision.") -> Note: Information about data precision.
A6: Release Date: September 26, 2023
A7: Next Update: October 26, 2023
A9: Table 11.1 Carbon Dioxide Emissions From Energy Consumption by Source
A11: Annual Total | B11: Coal, Including Coal Coke Net Imports, CO2 Emissions | C11: Natural Gas, Excluding Supplemental Gaseous Fuels, CO2 Emissions | D11: Aviation Gasoline CO2 Emissions | E11: Distillate Fuel Oil, Excluding Biodiesel, CO2 Emissions | F11: Hydrocarbon Gas Liquids CO2 Emissions | G11: Jet Fuel CO2 Emissions | H11: Kerosene CO2 Emissions | I11: Lubricants CO2 Emissions | J11: Motor Gasoline, Excluding Ethanol, CO2 Emissions | K11: Petroleum Coke CO2 Emissions | L11: Residual Fuel Oil CO2 Emissions | M11: Other Petroleum Products CO2 Emissions | N11: Petroleum, Excluding Biofuels, CO2 Emissions | O11: Total Energy CO2 Emissions
A12: unit | B12: (Million Metric Tons of Carbon Dioxide) | C12: (Million Metric Tons of Carbon Dioxide) | D12: (Million Metric Tons of Carbon Dioxide) | E12: (Million Metric Tons of Carbon Dioxide) | F12: (Million Metric Tons of Carbon Dioxide) | G12: (Million Metric Tons of Carbon Dioxide) | H12: (Million Metric Tons of Carbon Dioxide) | I12: (Million Metric Tons of Carbon Dioxide) | J12: (Million Metric Tons of Carbon Dioxide) | K12: (Million Metric Tons of Carbon Dioxide) | L12: (Million Metric Tons of Carbon Dioxide) | M12: (Million Metric Tons of Carbon Dioxide) | N12: (Million Metric Tons of Carbon Dioxide) | O12: (Million Metric Tons of Carbon Dioxide)
A13: 1973 | B13: 1220.645 | C13: 1174.859 | D13: 5.769 | E13: 485.041 | F13: 79.54 | G13: 154.162 | H13: 32.747 | I13: 13.29 | J13: 911.373 | K13: 55.137 | L13: 486.2 | M13: 102.153 | N13: 2325.412 | O13: 4720.916
A14: 1974 | B14: 1199.284 | C14: 1134.215 | D14: 5.659 | E14: 462.397 | F14: 76.569 | G14: 144.427 | H14: 26.704 | I14: 12.728 | J14: 892.676 | K14: 50.473 | L14: 454.598 | M14: 101.288 | N14: 2227.518 | O14: 4561.017
A15: 1975 | B15: 1195.032 | C15: 1042.504 | D15: 4.909 | E15: 447.176 | F15: 72.841 | G15: 145.616 | H15: 24.064 | I15: 11.268 | J15: 911.4 | K15: 52.102 | L15: 424.097 | M15: 96.927 | N15: 2190.401 | O15: 4427.937
A16: 1976 | B16: 1281.173 | C16: 1062.805 | D16: 4.663 | E16: 492.737 | F16: 75.039 | G16: 144.116 | H16: 25.695 | I16: 12.518 | J16: 955.397 | K16: 51.548 | L16: 483.828 | M16: 105.093 | N16: 2350.634 | O16: 4694.612
A17: 1977 | B17: 1315.721 | C17: 1041.058 | D17: 4.862 | E17: 525.595 | F17: 73.753 | G17: 151.264 | H17: 26.542 | I17: 13.097 | J17: 979.978 | K17: 56.553 | L17: 529.037 | M17: 117.689 | N17: 2478.369 | O17: 4835.148
A18: 1978 | B18: 1314.183 | C18: 1045.228 | D18: 4.94 | E18: 538.161 | F18: 71.192 | G18: 153.919 | H18: 26.575 | I18: 14.065 | J18: 1012.064 | K18: 54.057 | L18: 520.702 | M18: 129.028 | N18: 2524.703 | O18: 4884.113
A19: 1979 | B19: 1427.458 | C19: 1080.485 | D19: 4.861 | E19: 519.151 | F19: 81.865 | G19: 156.752 | H19: 28.454 | I19: 14.717 | J19: 960.537 | K19: 52.031 | L19: 486.868 | M19: 136.719 | N19: 2441.955 | O19: 4949.897
A20: 1980 | B20: 1453.794 | C20: 1058.054 | D20: 4.449 | E20: 450.809 | F20: 78.025 | G20: 155.811 | H20: 24.056 | I20: 13.105 | J20: 900.745 | K20: 50.116 | L20: 433.295 | M20: 134.069 | N20: 2244.48 | O20: 4756.328
A21: 1981 | B21: 1502.932 | C21: 1032.089 | D21: 3.89 | E21: 443.648 | F21: 77.922 | G21: 146.691 | H21: 19.215 | I21: 12.569 | J21: 899.511 | K21: 53.167 | L21: 359.671 | M21: 85.379 | N21: 2101.662 | O21: 4636.684
A22: 1982 | B22: 1449.085 | C22: 960.901 | D22: 3.248 | E22: 418.891 | F22: 79.278 | G22: 147.354 | H22: 19.488 | I22: 11.461 | J22: 892.918 | K22: 52.375 | L22: 295.693 | M22: 73.785 | N22: 1994.492 | O22: 4404.478
A23: 1983 | B23: 1504.796 | C23: 901.094 | D23: 3.296 | E23: 422.074 | F23: 73.586 | G23: 152.29 | H23: 19.235 | I23: 12 | J23: 904.238 | K23: 48.327 | L23: 244.771 | M23: 98.285 | N23: 1978.102 | O23: 4383.992
A24: 1984 | B24: 1616.103 | C24: 962.252 | D24: 3.034 | E24: 447.566 | F24: 79.848 | G24: 171.696 | H24: 17.505 | I24: 12.796 | J24: 916.35 | K24: 52.421 | L24: 236.546 | M24: 96.791 | N24: 2034.553 | O24: 4612.908
... A62: 2022 | B62: 934.698 | C62: 1745.629 | D62: 1.543 | E62: 619.456 | F62: 95.848 | G62: 233.162 | H62: 0.795 | I62: 9.071 | J62: 1065.004 | K62: 56.758 | L62: 56.728 | M62: 111.158 | N62: 2249.523 | O62: 4940.825

Sheet To be deleted -->

Sheet Carbon Intensity
A1: dataset: | C1: carbon
C2: Total Energy CO2 Emissions
B4: Total Fossil | C4: CO2 Emissions | D4: Carbon intensity of fossil energy
B5: (Quadrillion Btu) | C5: =VLOOKUP("unit",INDIRECT(C$1),MATCH(C$2,INDIRECT(C$1&"_col"),),) -> (Million Metric Tons of Carbon Dioxide) | D5: Ratio | F5: Growth Rate Calculation
A6: 1973 | B6: ='MER Quantity Data'!B37 -> 58.207232 | C6: =VLOOKUP($A6,INDIRECT(C$1),MATCH(C$2,INDIRECT(C$1&"_col"),),) -> 4720.916 | D6: =IF(ISERROR(C6/B6),"",C6/B6) -> 81.105317 | F6: Annual: | G6: {=LOGEST(D33:D54)} -> 0.97271264 | H6: 119.89084 | I6: =G6-1 -> -0.027287365 | L6: Variable | M6: Value | N6: Unit | O6: Notes
A7: =A6+1 -> 1974 | B7: ='MER Quantity Data'!B38 -> 56.294408 | C7: =VLOOKUP($A7,INDIRECT(C$1),MATCH(C$2,INDIRECT(C$1&"_col"),),) -> 4561.017 | D7: =IF(ISERROR(C7/B7),"",C7/B7) -> 81.020783 | F7: 10 Year: | G7: =G6^10-1 -> -0.24169212 | L7: SCC in $2020 | M7: 185 | N7: dollars/ton of CO2 | O7: Source: Rennert et al 2022 (full citation in paper)
A8: =A7+1 -> 1975 | B8: ='MER Quantity Data'!B39 -> 54.696919 | C8: =VLOOKUP($A8,INDIRECT(C$1),MATCH(C$2,INDIRECT(C$1&"_col"),),) -> 4427.937 | D8: =IF(ISERROR(C8/B8),"",C8/B8) -> 80.954048 | L8: 2020 Deflator | M8: ='MER GDP Data'!O89 -> 0 | N8: $2020/$2012
A9: =A8+1 -> 1976 | B9: ='MER Quantity Data'!B40 -> 54.683564 | C9: =VLOOKUP($A9,INDIRECT(C$1),MATCH(C$2,INDIRECT(C$1&"_col"),),) -> 4694.612 | D9: =IF(ISERROR(C9/B9),"",C9/B9) -> 85.850513 | L9: SCC in $2012 | M9: =M7/M8 -> #DIV/0! | N9: dollars/ton of CO2
A10: =A9+1 -> 1977 | B10: ='MER Quantity Data'!B41 -> 55.059451 | C10: =VLOOKUP($A10,INDIRECT(C$1),MATCH(C$2,INDIRECT(C$1&"_col"),),) -> 4835.148 | D10: =IF(ISERROR(C10/B10),"",C10/B10) -> 87.816858 | L10: Emissions in 2020 | M10: ='MER Environment Data'!W65*1000000 -> 0 | N10: tons
A11: =A10+1 -> 1978 | B11: ='MER Quantity Data'!B42 -> 55.03064 | C11: =VLOOKUP($A11,INDIRECT(C$1),MATCH(C$2,INDIRECT(C$1&"_col"),),) -> 4884.113 | D11: =IF(ISERROR(C11/B11),"",C11/B11) -> 88.752611 | L11: Damage in 2020 | M11: =M10*M9 -> #DIV/0! | N11: dollars
A12: =A11+1 -> 1979 | B12: ='MER Quantity Data'!B43 -> 57.951852 | C12: =VLOOKUP($A12,INDIRECT(C$1),MATCH(C$2,INDIRECT(C$1&"_col"),),) -> 4949.897 | D12: =IF(ISERROR(C12/B12),"",C12/B12) -> 85.413957 | L12: Y in 2020 | M12: ='MER GDP Data'!N89*1000000000 -> 0 | N12: dollars
A13: =A12+1 -> 1980 | B13: ='MER Quantity Data'!B44 -> 58.979084 | C13: =VLOOKUP($A13,INDIRECT(C$1),MATCH(C$2,INDIRECT(C$1&"_col"),),) -> 4756.328 | D13: =IF(ISERROR(C13/B13),"",C13/B13) -> 80.644318 | L13: Fraction of Y Lost | M13: =M11/M12 -> #DIV/0!
A14: =A13+1 -> 1981 | B14: ='MER Quantity Data'!B45 -> 58.488231 | C14: =VLOOKUP($A14,INDIRECT(C$1),MATCH(C$2,INDIRECT(C$1&"_col"),),) -> 4636.684 | D14: =IF(ISERROR(C14/B14),"",C14/B14) -> 79.275504
A15: =A14+1 -> 1982 | B15: ='MER Quantity Data'!B46 -> 57.415947 | C15: =VLOOKUP($A15,INDIRECT(C$1),MATCH(C$2,INDIRECT(C$1&"_col"),),) -> 4404.478 | D15: =IF(ISERROR(C15/B15),"",C15/B15) -> 76.711754
A16: =A15+1 -> 1983 | B16: ='MER Quantity Data'!B47 -> 54.368171 | C16: =VLOOKUP($A16,INDIRECT(C$1),MATCH(C$2,INDIRECT(C$1&"_col"),),) -> 4383.992 | D16: =IF(ISERROR(C16/B16),"",C16/B16) -> 80.635267
A17: =A16+1 -> 1984 | B17: ='MER Quantity Data'!B48 -> 58.809192 | C17: =VLOOKUP($A17,INDIRECT(C$1),MATCH(C$2,INDIRECT(C$1&"_col"),),) -> 4612.908 | D17: =IF(ISERROR(C17/B17),"",C17/B17) -> 78.438554
A18: =A17+1 -> 1985 | B18: ='MER Quantity Data'!B49 -> 57.501721 | C18: =VLOOKUP($A18,INDIRECT(C$1),MATCH(C$2,INDIRECT(C$1&"_col"),),) -> 4605.41 | D18: =IF(ISERROR(C18/B18),"",C18/B18) -> 80.09169
A19: =A18+1 -> 1986 | B19: ='MER Quantity Data'!B50 -> 56.539007 | C19: =VLOOKUP($A19,INDIRECT(C$1),MATCH(C$2,INDIRECT(C$1&"_col"),),) -> 4615.724 | D19: =IF(ISERROR(C19/B19),"",C19/B19) -> 81.637868
A20: =A19+1 -> 1987 | B20: ='MER Quantity Data'!B51 -> 57.130643 | C20: =VLOOKUP($A20,INDIRECT(C$1),MATCH(C$2,INDIRECT(C$1&"_col"),),) -> 4775.616 | D20: =IF(ISERROR(C20/B20),"",C20/B20) -> 83.591147
A21: =A20+1 -> 1988 | B21: ='MER Quantity Data'!B52 -> 57.845857 | C21: =VLOOKUP($A21,INDIRECT(C$1),MATCH(C$2,INDIRECT(C$1&"_col"),),) -> 4998.283 | D21: =IF(ISERROR(C21/B21),"",C21/B21) -> 86.406931
A22: =A21+1 -> 1989 | B22: ='MER Quantity Data'!B53 -> 57.447703 | C22: =VLOOKUP($A22,INDIRECT(C$1),MATCH(C$2,INDIRECT(C$1&"_col"),),) -> 5084.633 | D22: =IF(ISERROR(C22/B22),"",C22/B22) -> 88.5089
A23: =A22+1 -> 1990 | B23: ='MER Quantity Data'!B54 -> 58.523186 | C23: =VLOOKUP($A23,INDIRECT(C$1),MATCH(C$2,INDIRECT(C$1&"_col"),),) -> 5037.975 | D23: =IF(ISERROR(C23/B23),"",C23/B23) -> 86.085112
A24: =A23+1 -> 1991 | B24: ='MER Quantity Data'!B55 -> 57.831148 | C24: =VLOOKUP($A24,INDIRECT(C$1),MATCH(C$2,INDIRECT(C$1&"_col"),),) -> 4990.804 | D24: =IF(ISERROR(C24/B24),"",C24/B24) -> 86.299584
A25: =A24+1 -> 1992 | B25: ='MER Quantity Data'!B56 -> 57.614681 | C25: =VLOOKUP($A25,INDIRECT(C$1),MATCH(C$2,INDIRECT(C$1&"_col"),),) -> 5088.755 | D25: =IF(ISERROR(C25/B25),"",C25/B25) -> 88.323929
... A54: =A53+1 -> 2021 | B54: ='MER Quantity Data'!B85 -> 77.891227 | C54: =VLOOKUP($A54,INDIRECT(C$1),MATCH(C$2,INDIRECT(C$1&"_col"),),) -> 4903.572 | D54: =IF(ISERROR(C54/B54),"",C54/B54) -> 62.954099

Sheet EIA SEDS Codes
B2: State Energy Data System
B3: Data Series Names (MSN) and Descriptions
B6: The MSNs are five-character codes, most of which are structured as follows:
B7: First and second characters - describes an energy source (for example, NG for natural gas, MG for motor gasoline)
B8: Third and fourth characters - describes an energy sector or an energy activity (for example, RC for residential consumption, PR for production)
B9: Fifth character - describes a type of data (for example, P for data in physical unit, B for data in billion Btu)
B11: MSN | C11: Description | D11: Unit
B12: ABICB | C12: Aviation gasoline blending components consumed by the industrial sector | D12: Billion Btu
B13: ABICP | C13: Aviation gasoline blending components consumed by the industrial sector | D13: Thousand barrels
B14: ARICB | C14: Asphalt and road oil consumed by the industrial sector | D14: Billion Btu
B15: ARICD | C15: Asphalt and road oil price in the industrial sector | D15: Dollars per million Btu
B16: ARICP | C16: Asphalt and road oil consumed by the industrial sector | D16: Thousand barrels
B17: ARICV | C17: Asphalt and road oil expenditures in the industrial sector | D17: Million dollars
B18: ARTCB | C18: Asphalt and road oil total consumption | D18: Billion Btu
B19: ARTCD | C19: Asphalt and road oil average price, all sectors | D19: Dollars per million Btu
B20: ARTCP | C20: Asphalt and road oil total consumption | D20: Thousand barrels
B21: ARTCV | C21: Asphalt and road oil total expenditures | D21: Million dollars
B22: ARTXB | C22: Asphalt and road oil total end-use consumption | D22: Billion Btu
... B770: ZWHDP | C770: Heating degree days (HDD) | D770: Days

Sheet SEDS Quantities
A1: Data_Status | B1: State | C1: MSN | D1: 1960 | E1: 1961 | F1: 1962 | G1: 1963 | H1: 1964 | I1: 1965 | J1: 1966 | K1: 1967 | L1: 1968 | M1: 1969 | N1: 1970 | O1: 1971 | P1: 1972 | Q1: 1973 | R1: 1974 | S1: 1975 | T1: 1976 | U1: 1977 | V1: 1978 | W1: 1979 | X1: 1980 | Y1: 1981 | Z1: 1982 | AA1: 1983 | AB1: 1984 | AC1: 1985 | AD1: 1986 | AE1: 1987 | AF1: 1988 | AG1: 1989 | AH1: 1990 | AI1: 1991 | AJ1: 1992 | AK1: 1993 | AL1: 1994 | AM1: 1995 | AN1: 1996 | AO1: 1997 | AP1: 1998 | AQ1: 1999 | AR1: 2000 | AS1: 2001 | AT1: 2002 | AU1: 2003 | AV1: 2004 | AW1: 2005 | AX1: 2006 | AY1: 2007 | AZ1: 2008 | BA1: 2009 | BB1: 2010 | BC1: 2011 | BD1: 2012 | BE1: 2013 | BF1: 2014 | BG1: 2015 | BH1: 2016 | BI1: 2017 | BJ1: 2018 | BK1: 2019 | BL1: 2020 | BM1: 2021
A2: 2021F | B2: US | C2: ABICB | D2: 0 | E2: 0 | F2: 0 | G2: 0 | H2: 0 | I2: 0 | J2: 0 | K2: 0 | L2: 0 | M2: 0 | N2: 0 | O2: 0 | P2: 0 | Q2: 0 | R2: 0 | S2: 0 | T2: 0 | U2: 0 | V2: 0 | W2: 0 | X2: 0 | Y2: 5169 | Z2: 4937 | AA2: 712 | AB2: 86 | AC2: 3867 | AD2: 545 | AE2: 45 | AF2: -1070 | AG2: 106 | AH2: 237 | AI2: -81 | AJ2: 156 | AK2: 146 | AL2: 6098 | AM2: 5290 | AN2: 6951 | AO2: 9056 | AP2: 4003 | AQ2: 6396 | AR2: 3816 | AS2: 6073 | AT2: 7516 | AU2: 7471 | AV2: 10616 | AW2: 8324 | AX2: 641 | AY2: 1782 | AZ2: 96 | BA2: -793 | BB2: -242 | BC2: 10 | BD2: -5 | BE2: -379 | BF2: -141 | BG2: -348 | BH2: -293 | BI2: -192 | BJ2: -1555 | BK2: -1191 | BL2: -787 | BM2: -833
A3: 2021F | B3: US | C3: ABICP | D3: 0 | E3: 0 | F3: 0 | G3: 0 | H3: 0 | I3: 0 | J3: 0 | K3: 0 | L3: 0 | M3: 0 | N3: 0 | O3: 0 | P3: 0 | Q3: 0 | R3: 0 | S3: 0 | T3: 0 | U3: 0 | V3: 0 | W3: 0 | X3: 0 | Y3: 1024 | Z3: 978 | AA3: 141 | AB3: 17 | AC3: 766 | AD3: 108 | AE3: 9 | AF3: -212 | AG3: 21 | AH3: 47 | AI3: -16 | AJ3: 31 | AK3: 29 | AL3: 1208 | AM3: 1048 | AN3: 1377 | AO3: 1794 | AP3: 793 | AQ3: 1267 | AR3: 756 | AS3: 1203 | AT3: 1489 | AU3: 1480 | AV3: 2103 | AW3: 1649 | AX3: 127 | AY3: 353 | AZ3: 19 | BA3: -157 | BB3: -48 | BC3: 2 | BD3: -1 | BE3: -75 | BF3: -28 | BG3: -69 | BH3: -58 | BI3: -38 | BJ3: -308 | BK3: -236 | BL3: -156 | BM3: -165
A4: 2021F | B4: US | C4: ARICB | D4: 733782 | E4: 753551 | F4: 803533 | G4: 824642 | H4: 840781 | I4: 890266 | J4: 935557 | K4: 917215 | L4: 983661 | M4: 1008977 | N4: 1082451 | O4: 1108298 | P4: 1136919 | Q4: 1263720 | R4: 1165375 | S4: 1014226 | T4: 998121 | U4: 1056365 | V4: 1159621 | W4: 1153032 | X4: 962207 | Y4: 827788 | Z4: 829407 | AA4: 904095 | AB4: 992095 | AC4: 1029482 | AD4: 1085736 | AE4: 1130011 | AF4: 1136322 | AG4: 1096028 | AH4: 1170192 | AI4: 1076538 | AJ4: 1102220 | AK4: 1149017 | AL4: 1172920 | AM4: 1178175 | AN4: 1175932 | AO4: 1223566 | AP4: 1262552 | AQ4: 1324413 | AR4: 1275678 | AS4: 1256865 | AT4: 1239950 | AU4: 1219538 | AV4: 1303848 | AW4: 1323238 | AX4: 1261165 | AY4: 1197041 | AZ4: 1011970 | BA4: 873085 | BB4: 877770 | BC4: 859488 | BD4: 826700 | BE4: 783347 | BF4: 792637 | BG4: 831663 | BH4: 853363 | BI4: 849182 | BJ4: 792763 | BK4: 843880 | BL4: 832274 | BM4: 898083
A5: 2021F | B5: US | C5: ARICP | D5: 110576 | E5: 113555 | F5: 121087 | G5: 124268 | H5: 126700 | I5: 134157 | J5: 140982 | K5: 138218 | L5: 148231 | M5: 152046 | N5: 163118 | O5: 167013 | P5: 171326 | Q5: 190434 | R5: 175614 | S5: 152837 | T5: 150410 | U5: 159187 | V5: 174747 | W5: 173754 | X5: 144998 | Y5: 124742 | Z5: 124986 | AA5: 136241 | AB5: 149502 | AC5: 155136 | AD5: 163613 | AE5: 170285 | AF5: 171236 | AG5: 165164 | AH5: 176340 | AI5: 162227 | AJ5: 166097 | AK5: 173149 | AL5: 176751 | AM5: 177543 | AN5: 177205 | AO5: 184383 | AP5: 190258 | AQ5: 199580 | AR5: 192236 | AS5: 189401 | AT5: 186852 | AU5: 183776 | AV5: 196481 | AW5: 199403 | AX5: 190049 | AY5: 180386 | AZ5: 152497 | BA5: 131568 | BB5: 132274 | BC5: 129519 | BD5: 124578 | BE5: 118045 | BF5: 119445 | BG5: 125326 | BH5: 128596 | BI5: 127966 | BJ5: 119464 | BK5: 127167 | BL5: 125418 | BM5: 135335
A6: 2021F | B6: US | C6: ARTCB | D6: 733782 | E6: 753551 | F6: 803533 | G6: 824642 | H6: 840781 | I6: 890266 | J6: 935557 | K6: 917215 | L6: 983661 | M6: 1008977 | N6: 1082451 | O6: 1108298 | P6: 1136919 | Q6: 1263720 | R6: 1165375 | S6: 1014226 | T6: 998121 | U6: 1056365 | V6: 1159621 | W6: 1153032 | X6: 962207 | Y6: 827788 | Z6: 829407 | AA6: 904095 | AB6: 992095 | AC6: 1029482 | AD6: 1085736 | AE6: 1130011 | AF6: 1136322 | AG6: 1096028 | AH6: 1170192 | AI6: 1076538 | AJ6: 1102220 | AK6: 1149017 | AL6: 1172920 | AM6: 1178175 | AN6: 1175932 | AO6: 1223566 | AP6: 1262552 | AQ6: 1324413 | AR6: 1275678 | AS6: 1256865 | AT6: 1239950 | AU6: 1219538 | AV6: 1303848 | AW6: 1323238 | AX6: 1261165 | AY6: 1197041 | AZ6: 1011970 | BA6: 873085 | BB6: 877770 | BC6: 859488 | BD6: 826700 | BE6: 783347 | BF6: 792637 | BG6: 831663 | BH6: 853363 | BI6: 849182 | BJ6: 792763 | BK6: 843880 | BL6: 832274 | BM6: 898083
A7: 2021F | B7: US | C7: ARTCP | D7: 110576 | E7: 113555 | F7: 121087 | G7: 124268 | H7: 126700 | I7: 134157 | J7: 140982 | K7: 138218 | L7: 148231 | M7: 152046 | N7: 163118 | O7: 167013 | P7: 171326 | Q7: 190434 | R7: 175614 | S7: 152837 | T7: 150410 | U7: 159187 | V7: 174747 | W7: 173754 | X7: 144998 | Y7: 124742 | Z7: 124986 | AA7: 136241 | AB7: 149502 | AC7: 155136 | AD7: 163613 | AE7: 170285 | AF7: 171236 | AG7: 165164 | AH7: 176340 | AI7: 162227 | AJ7: 166097 | AK7: 173149 | AL7: 176751 | AM7: 177543 | AN7: 177205 | AO7: 184383 | AP7: 190258 | AQ7: 199580 | AR7: 192236 | AS7: 189401 | AT7: 186852 | AU7: 183776 | AV7: 196481 | AW7: 199403 | AX7: 190049 | AY7: 180386 | AZ7: 152497 | BA7: 131568 | BB7: 132274 | BC7: 129519 | BD7: 124578 | BE7: 118045 | BF7: 119445 | BG7: 125326 | BH7: 128596 | BI7: 127966 | BJ7: 119464 | BK7: 127167 | BL7: 125418 | BM7: 135335
A8: 2021F | B8: US | C8: ARTXB | D8: 733782 | E8: 753551 | F8: 803533 | G8: 824642 | H8: 840781 | I8: 890266 | J8: 935557 | K8: 917215 | L8: 983661 | M8: 1008977 | N8: 1082451 | O8: 1108298 | P8: 1136919 | Q8: 1263720 | R8: 1165375 | S8: 1014226 | T8: 998121 | U8: 1056365 | V8: 1159621 | W8: 1153032 | X8: 962207 | Y8: 827788 | Z8: 829407 | AA8: 904095 | AB8: 992095 | AC8: 1029482 | AD8: 1085736 | AE8: 1130011 | AF8: 1136322 | AG8: 1096028 | AH8: 1170192 | AI8: 1076538 | AJ8: 1102220 | AK8: 1149017 | AL8: 1172920 | AM8: 1178175 | AN8: 1175932 | AO8: 1223566 | AP8: 1262552 | AQ8: 1324413 | AR8: 1275678 | AS8: 1256865 | AT8: 1239950 | AU8: 1219538 | AV8: 1303848 | AW8: 1323238 | AX8: 1261165 | AY8: 1197041 | AZ8: 1011970 | BA8: 873085 | BB8: 877770 | BC8: 859488 | BD8: 826700 | BE8: 783347 | BF8: 792637 | BG8: 831663 | BH8: 853363 | BI8: 849182 | BJ8: 792763 | BK8: 843880 | BL8: 832274 | BM8: 898083
A9: 2021F | B9: US | C9: ARTXP | D9: 110576 | E9: 113555 | F9: 121087 | G9: 124268 | H9: 126700 | I9: 134157 | J9: 140982 | K9: 138218 | L9: 148231 | M9: 152046 | N9: 163118 | O9: 167013 | P9: 171326 | Q9: 190434 | R9: 175614 | S9: 152837 | T9: 150410 | U9: 159187 | V9: 174747 | W9: 173754 | X9: 144998 | Y9: 124742 | Z9: 124986 | AA9: 136241 | AB9: 149502 | AC9: 155136 | AD9: 163613 | AE9: 170285 | AF9: 171236 | AG9: 165164 | AH9: 176340 | AI9: 162227 | AJ9: 166097 | AK9: 173149 | AL9: 176751 | AM9: 177543 | AN9: 177205 | AO9: 184383 | AP9: 190258 | AQ9: 199580 | AR9: 192236 | AS9: 189401 | AT9: 186852 | AU9: 183776 | AV9: 196481 | AW9: 199403 | AX9: 190049 | AY9: 180386 | AZ9: 152497 | BA9: 131568 | BB9: 132274 | BC9: 129519 | BD9: 124578 | BE9: 118045 | BF9: 119445 | BG9: 125326 | BH9: 128596 | BI9: 127966 | BJ9: 119464 | BK9: 127167 | BL9: 125418 | BM9: 135335
A10: 2021F | B10: US | C10: AVACB | D10: 297903 | E10: 290396 | F10: 262915 | G10: 253193 | H10: 235025 | I10: 221592 | J10: 194091 | K10: 166099 | L10: 154590 | M10: 128981 | N10: 100470 | O10: 90319 | P10: 85437 | Q10: 83448 | R10: 81853 | S10: 71010 | T10: 67451 | U10: 70329 | V10: 71454 | W10: 70314 | X10: 64347 | Y10: 56270 | Z10: 46977 | AA10: 47673 | AB10: 43877 | AC10: 50324 | AD10: 58925 | AE10: 45639 | AF10: 48991 | AG10: 47587 | AH10: 44978 | AI10: 41722 | AJ10: 41055 | AK10: 38395 | AL10: 38138 | AM10: 39581 | AN10: 37355 | AO10: 39697 | AP10: 35498 | AQ10: 39172 | AR10: 36285 | AS10: 34937 | AT10: 33731 | AU10: 30222 | AV10: 31242 | AW10: 35366 | AX10: 33448 | AY10: 31590 | AZ10: 28284 | BA10: 26558 | BB10: 27047 | BC10: 27057 | BD10: 25114 | BE10: 22358 | BF10: 21696 | BG10: 21141 | BH10: 20465 | BI10: 20949 | BJ10: 22393 | BK10: 23387 | BL10: 20202 | BM10: 21550
A11: 2021F | B11: US | C11: AVACP | D11: 59014 | E11: 57527 | F11: 52083 | G11: 50157 | H11: 46558 | I11: 43897 | J11: 38449 | K11: 32904 | L11: 30624 | M11: 25551 | N11: 19903 | O11: 17892 | P11: 16925 | Q11: 16531 | R11: 16215 | S11: 14067 | T11: 13362 | U11: 13932 | V11: 14155 | W11: 13929 | X11: 12747 | Y11: 11147 | Z11: 9306 | AA11: 9444 | AB11: 8692 | AC11: 9969 | AD11: 11673 | AE11: 9041 | AF11: 9705 | AG11: 9427 | AH11: 8910 | AI11: 8265 | AJ11: 8133 | AK11: 7606 | AL11: 7555 | AM11: 7841 | AN11: 7400 | AO11: 7864 | AP11: 7032 | AQ11: 7760 | AR11: 7188 | AS11: 6921 | AT11: 6682 | AU11: 5987 | AV11: 6189 | AW11: 7006 | AX11: 6626 | AY11: 6258 | AZ11: 5603 | BA11: 5261 | BB11: 5358 | BC11: 5360 | BD11: 4975 | BE11: 4429 | BF11: 4298 | BG11: 4188 | BH11: 4054 | BI11: 4150 | BJ11: 4436 | BK11: 4633 | BL11: 4002 | BM11: 4269
A12: 2021F | B12: US | C12: AVTCB | D12: 297903 | E12: 290396 | F12: 262915 | G12: 253193 | H12: 235025 | I12: 221592 | J12: 194091 | K12: 166099 | L12: 154590 | M12: 128981 | N12: 100470 | O12: 90319 | P12: 85437 | Q12: 83448 | R12: 81853 | S12: 71010 | T12: 67451 | U12: 70329 | V12: 71454 | W12: 70314 | X12: 64347 | Y12: 56270 | Z12: 46977 | AA12: 47673 | AB12: 43877 | AC12: 50324 | AD12: 58925 | AE12: 45639 | AF12: 48991 | AG12: 47587 | AH12: 44978 | AI12: 41722 | AJ12: 41055 | AK12: 38395 | AL12: 38138 | AM12: 39581 | AN12: 37355 | AO12: 39697 | AP12: 35498 | AQ12: 39172 | AR12: 36285 | AS12: 34937 | AT12: 33731 | AU12: 30222 | AV12: 31242 | AW12: 35366 | AX12: 33448 | AY12: 31590 | AZ12: 28284 | BA12: 26558 | BB12: 27047 | BC12: 27057 | BD12: 25114 | BE12: 22358 | BF12: 21696 | BG12: 21141 | BH12: 20465 | BI12: 20949 | BJ12: 22393 | BK12: 23387 | BL12: 20202 | BM12: 21550
... A31: 2021F | B31: US | C31: BOTCP | D31: 0 | E31: 0 | F31: 0 | G31: 0 | H31: 0 | I31: 0 | J31: 0 | K31: 0 | L31: 0 | M31: 0 | N31: 0 | O31: 0 | P31: 0 | Q31: 0 | R31: 0 | S31: 0 | T31: 0 | U31: 0 | V31: 0 | W31: 0 | X31: 0 | Y31: 0 | Z31: 0 | AA31: 0 | AB31: 0 | AC31: 0 | AD31: 0 | AE31: 0 | AF31: 0 | AG31: 0 | AH31: 0 | AI31: 0 | AJ31: 0 | AK31: 0 | AL31: 0 | AM31: 0 | AN31: 0 | AO31: 0 | AP31: 0 | AQ31: 0 | AR31: 0 | AS31: 0 | AT31: 0 | AU31: 0 | AV31: 0 | AW31: 0 | AX31: 0 | AY31: 0 | AZ31: 0 | BA31: 0 | BB31: 0 | BC31: 0 | BD31: 0 | BE31: 0 | BF31: 288 | BG31: 396 | BH31: 464 | BI31: 585 | BJ31: 585 | BK31: 795 | BL31: 784 | BM31: 1885
A32: 2021F | B32: US | C32: BQICB | BB32: 164731 | BC32: 107136 | BD32: 122276 | BE32: 187558 | BF32: 186108 | BG32: 203877 | BH32: 133089 | BI32: 61003 | BJ32: 55331 | BK32: 80243 | BL32: -17072 | BM32: 36160
A33: 2021F | B33: US | C33: BQICP | BB33: 37843 | BC33: 24612 | BD33: 28090 | BE33: 43087 | BF33: 42754 | BG33: 46836 | BH33: 30574 | BI33: 14014 | BJ33: 12711 | BK33: 18434 | BL33: -3922 | BM33: 8307
A34: 2021F | B34: US | C34: BQTCB | BB34: 164731 | BC34: 107136 | BD34: 122276 | BE34: 187558 | BF34: 186108 | BG34: 203877 | BH34: 133089 | BI34: 61003 | BJ34: 55331 | BK34: 80243 | BL34: -17072 | BM34: 36160
A35: 2021F | B35: US | C35: BQTCP | BB35: 37843 | BC35: 24612 | BD35: 28090 | BE35: 43087 | BF35: 42754 | BG35: 46836 | BH35: 30574 | BI35: 14014 | BJ35: 12711 | BK35: 18434 | BL35: -3922 | BM35: 8307
A36: 2021F | B36: US | C36: BTGBP | AZ36: 0 | BA36: 0 | BB36: 28 | BC36: 68 | BD36: 142 | BE36: 146 | BF36: 156 | BG36: 292 | BH36: 559 | BI36: 665 | BJ36: 852 | BK36: 1015 | BL36: 1508 | BM36: 4747
A37: 2021F | B37: US | C37: BYICB | BB37: 6636 | BC37: 889 | BD37: 626 | BE37: -5563 | BF37: 2486 | BG37: -8610 | BH37: -3847 | BI37: 5257 | BJ37: 13547 | BK37: 26 | BL37: -5694 | BM37: -4460
A38: 2021F | B38: US | C38: BYICP | BB38: 1516 | BC38: 203 | BD38: 143 | BE38: -1271 | BF38: 568 | BG38: -1967 | BH38: -879 | BI38: 1201 | BJ38: 3095 | BK38: 6 | BL38: -1301 | BM38: -1019
A39: 2021F | B39: US | C39: BYTCB | BB39: 6636 | BC39: 889 | BD39: 626 | BE39: -5563 | BF39: 2486 | BG39: -8610 | BH39: -3847 | BI39: 5257 | BJ39: 13547 | BK39: 26 | BL39: -5694 | BM39: -4460
A40: 2021F | B40: US | C40: BYTCP | BB40: 1516 | BC40: 203 | BD40: 143 | BE40: -1271 | BF40: 568 | BG40: -1967 | BH40: -879 | BI40: 1201 | BJ40: 3095 | BK40: 6 | BL40: -1301 | BM40: -1019
A41: 2021F | B41: US | C41: CCEXB | D41: 8754 | E41: 11036 | F41: 9027 | G41: 11185 | H41: 12995 | I41: 20683 | J41: 27330 | K41: 17608 | L41: 19642 | M41: 40399 | N41: 61454 | O41: 37423 | P41: 30554 | Q41: 34596 | R41: 31694 | S41: 31570 | T41: 32612 | U41: 30777 | V41: 17186 | W41: 35712 | X41: 51362 | Y41: 29020 | Z41: 24632 | AA41: 16504 | AB41: 25911 | AC41: 27833 | AD41: 24909 | AE41: 14243 | AF41: 27112 | AG41: 26918 | AH41: 14189 | AI41: 19645 | AJ41: 17402 | AK41: 26333 | AL41: 24456 | AM41: 33678 | AN41: 40233 | AO41: 31405 | AP41: 27999 | AQ41: 22261 | AR41: 28414 | AS41: 33373 | AT41: 19637 | AU41: 17900 | AV41: 32701 | AW41: 43335 | AX41: 40089 | AY41: 35807 | AZ41: 48582 | BA41: 32409 | BB41: 36278 | BC41: 24058 | BD41: 24162 | BE41: 20833 | BF41: 23461 | BG41: 21251 | BH41: 24808 | BI41: 30048 | BJ41: 28549 | BK41: 23990 | BL41: 16949 | BM41: 51618
A42: 2021F | B42: US | C42: CCEXP | D42: 353 | E42: 445 | F42: 364 | G42: 451 | H42: 524 | I42: 834 | J42: 1102 | K42: 710 | L42: 792 | M42: 1629 | N42: 2478 | O42: 1509 | P42: 1232 | Q42: 1395 | R42: 1278 | S42: 1273 | T42: 1315 | U42: 1241 | V42: 693 | W42: 1440 | X42: 2071 | Y42: 1170 | Z42: 993 | AA42: 665 | AB42: 1045 | AC42: 1122 | AD42: 1004 | AE42: 574 | AF42: 1093 | AG42: 1085 | AH42: 572 | AI42: 792 | AJ42: 702 | AK42: 1062 | AL42: 986 | AM42: 1358 | AN42: 1622 | AO42: 1266 | AP42: 1129 | AQ42: 898 | AR42: 1146 | AS42: 1346 | AT42: 792 | AU42: 722 | AV42: 1319 | AW42: 1747 | AX42: 1616 | AY42: 1444 | AZ42: 1959 | BA42: 1307 | BB42: 1463 | BC42: 970 | BD42: 974 | BE42: 840 | BF42: 946 | BG42: 857 | BH42: 1000 | BI42: 1212 | BJ42: 1151 | BK42: 967 | BL42: 683 | BM42: 2081
A43: 2021F | B43: US | C43: CCIMB | D43: 3125 | E43: 3150 | F43: 3522 | G43: 3794 | H43: 2554 | I43: 2232 | J43: 2381 | K43: 2282 | L43: 2331 | M43: 4290 | N43: 3794 | O43: 4315 | P43: 4588 | Q43: 27131 | R43: 87792 | S43: 45111 | T43: 32513 | U43: 45359 | V43: 141906 | W43: 98555 | X43: 16332 | Y43: 13071 | Z43: 2976 | AA43: 868 | AB43: 14423 | AC43: 14341 | AD43: 8155 | AE43: 22873 | AF43: 66663 | AG43: 57322 | AH43: 18966 | AI43: 29334 | AJ43: 52027 | AK43: 53442 | AL43: 82785 | AM43: 94739 | AN43: 63044 | AO43: 77844 | AP43: 95094 | AQ43: 79953 | AR43: 93777 | AS43: 62633 | AT43: 80395 | AU43: 68415 | AV43: 170463 | AW43: 87526 | AX43: 100876 | AY43: 60998 | AZ43: 89354 | BA43: 8598 | BB43: 30107 | BC43: 35162 | BD43: 28146 | BE43: 3411 | BF43: 1901 | BG43: 3470 | BH43: 5669 | BI43: 1450 | BJ43: 2895 | BK43: 2868 | BL43: 4010 | BM43: 2904
A44: 2021F | B44: US | C44: CCIMP | D44: 126 | E44: 127 | F44: 142 | G44: 153 | H44: 103 | I44: 90 | J44: 96 | K44: 92 | L44: 94 | M44: 173 | N44: 153 | O44: 174 | P44: 185 | Q44: 1094 | R44: 3540 | S44: 1819 | T44: 1311 | U44: 1829 | V44: 5722 | W44: 3974 | X44: 659 | Y44: 527 | Z44: 120 | AA44: 35 | AB44: 582 | AC44: 578 | AD44: 329 | AE44: 922 | AF44: 2688 | AG44: 2311 | AH44: 765 | AI44: 1183 | AJ44: 2098 | AK44: 2155 | AL44: 3338 | AM44: 3820 | AN44: 2542 | AO44: 3139 | AP44: 3834 | AQ44: 3224 | AR44: 3781 | AS44: 2526 | AT44: 3242 | AU44: 2759 | AV44: 6873 | AW44: 3529 | AX44: 4068 | AY44: 2460 | AZ44: 3603 | BA44: 347 | BB44: 1214 | BC44: 1418 | BD44: 1135 | BE44: 138 | BF44: 77 | BG44: 140 | BH44: 229 | BI44: 58 | BJ44: 117 | BK44: 116 | BL44: 162 | BM44: 117
A45: 2021F | B45: US | C45: CCNIB | D45: -5630 | E45: -7886 | F45: -5506 | G45: -7390 | H45: -10441 | I45: -18451 | J45: -24949 | K45: -15326 | L45: -17310 | M45: -36109 | N45: -57660 | O45: -33108 | P45: -25966 | Q45: -7465 | R45: 56098 | S45: 13541 | T45: -99 | U45: 14582 | V45: 124719 | W45: 62843 | X45: -35030 | Y45: -15949 | Z45: -21656 | AA45: -15636 | AB45: -11488 | AC45: -13492 | AD45: -16754 | AE45: 8630 | AF45: 39551 | AG45: 30404 | AH45: 4778 | AI45: 9688 | AJ45: 34625 | AK45: 27110 | AL45: 58329 | AM45: 61061 | AN45: 22811 | AO45: 46440 | AP45: 67095 | AQ45: 57692 | AR45: 65363 | AS45: 29260 | AT45: 60758 | AU45: 50515 | AV45: 137762 | AW45: 44191 | AX45: 60787 | AY45: 25191 | AZ45: 40772 | BA45: -23811 | BB45: -6171 | BC45: 11104 | BD45: 3983 | BE45: -17422 | BF45: -21560 | BG45: -17781 | BH45: -19139 | BI45: -28598 | BJ45: -25654 | BK45: -21122 | BL45: -12939 | BM45: -48713
A46: 2021F | B46: US | C46: CCNIP | D46: -227 | E46: -318 | F46: -222 | G46: -298 | H46: -421 | I46: -744 | J46: -1006 | K46: -618 | L46: -698 | M46: -1456 | N46: -2325 | O46: -1335 | P46: -1047 | Q46: -301 | R46: 2262 | S46: 546 | T46: -4 | U46: 588 | V46: 5029 | W46: 2534 | X46: -1413 | Y46: -643 | Z46: -873 | AA46: -630 | AB46: -463 | AC46: -544 | AD46: -676 | AE46: 348 | AF46: 1595 | AG46: 1226 | AH46: 193 | AI46: 391 | AJ46: 1396 | AK46: 1093 | AL46: 2352 | AM46: 2462 | AN46: 920 | AO46: 1873 | AP46: 2705 | AQ46: 2326 | AR46: 2636 | AS46: 1180 | AT46: 2450 | AU46: 2037 | AV46: 5555 | AW46: 1782 | AX46: 2451 | AY46: 1016 | AZ46: 1644 | BA46: -960 | BB46: -249 | BC46: 448 | BD46: 161 | BE46: -703 | BF46: -869 | BG46: -717 | BH46: -772 | BI46: -1153 | BJ46: -1034 | BK46: -852 | BL46: -522 | BM46: -1964
A47: 2021F | B47: US | C47: CLACB | D47: 75624 | E47: 19096 | F47: 17032 | G47: 16593 | H47: 17586 | I47: 16135 | J47: 14898 | K47: 11351 | L47: 10139 | M47: 7502 | N47: 6917 | O47: 4738 | P47: 3705 | Q47: 2633 | R47: 1801 | S47: 542 | T47: 273 | U47: 204 | V47: 0 | W47: 0 | X47: 0 | Y47: 0 | Z47: 0 | AA47: 0 | AB47: 0 | AC47: 0 | AD47: 0 | AE47: 0 | AF47: 0 | AG47: 0 | AH47: 0 | AI47: 0 | AJ47: 0 | AK47: 0 | AL47: 0 | AM47: 0 | AN47: 0 | AO47: 0 | AP47: 0 | AQ47: 0 | AR47: 0 | AS47: 0 | AT47: 0 | AU47: 0 | AV47: 0 | AW47: 0 | AX47: 0 | AY47: 0 | AZ47: 0 | BA47: 0 | BB47: 0 | BC47: 0 | BD47: 0 | BE47: 0 | BF47: 0 | BG47: 0 | BH47: 0 | BI47: 0 | BJ47: 0 | BK47: 0 | BL47: 0 | BM47: 0
A48: 2021F | B48: US | C48: CLACK | D48: 24.604 | E48: 24.569 | F48: 24.558 | G48: 24.524 | H48: 24.49 | I48: 24.387 | J48: 24.227 | K48: 24.056 | L48: 24.034 | M48: 23.737 | N48: 22.973 | O48: 22.653 | P48: 22.539 | Q48: 22.585 | R48: 22.42 | S48: 22.439 | T48: 22.528 | U48: 22.29 | V48: 22.175 | W48: 22.436 | X48: 22.69 | Y48: 22.572 | Z48: 22.695 | AA48: 22.68 | AB48: 22.525 | AC48: 22.013 | AD48: 22.185 | AE48: 22.36 | AF48: 22.341 | AG48: 22.324 | AH48: 22.444 | AI48: 22.448 | AJ48: 22.242 | AK48: 22.111 | AL48: 22.046 | AM48: 21.931 | AN48: 22.087 | AO48: 22.157 | AP48: 22.093 | AQ48: 22.093 | AR48: 0 | AS48: 0 | AT48: 0 | AU48: 0 | AV48: 0 | AW48: 0 | AX48: 0 | AY48: 0 | AZ48: 0 | BA48: 0 | BB48: 0 | BC48: 0 | BD48: 0 | BE48: 0 | BF48: 0 | BG48: 0 | BH48: 0 | BI48: 0 | BJ48: 0 | BK48: 0 | BL48: 0 | BM48: 0
A49: 2021F | B49: US | C49: CLACP | D49: 3046 | E49: 770 | F49: 687 | G49: 670 | H49: 711 | I49: 655 | J49: 609 | K49: 467 | L49: 417 | M49: 313 | N49: 298 | O49: 207 | P49: 163 | Q49: 116 | R49: 80 | S49: 24 | T49: 12 | U49: 9 | V49: 0 | W49: 0 | X49: 0 | Y49: 0 | Z49: 0 | AA49: 0 | AB49: 0 | AC49: 0 | AD49: 0 | AE49: 0 | AF49: 0 | AG49: 0 | AH49: 0 | AI49: 0 | AJ49: 0 | AK49: 0 | AL49: 0 | AM49: 0 | AN49: 0 | AO49: 0 | AP49: 0 | AQ49: 0 | AR49: 0 | AS49: 0 | AT49: 0 | AU49: 0 | AV49: 0 | AW49: 0 | AX49: 0 | AY49: 0 | AZ49: 0 | BA49: 0 | BB49: 0 | BC49: 0 | BD49: 0 | BE49: 0 | BF49: 0 | BG49: 0 | BH49: 0 | BI49: 0 | BJ49: 0 | BK49: 0 | BL49: 0 | BM49: 0
A50: 2021F | B50: US | C50: CLCCB | D50: 401969 | E50: 366139 | F50: 357649 | G50: 314331 | H50: 271710 | I50: 262503 | J50: 260256 | K50: 223054 | L50: 205459 | M50: 192705 | N50: 163002 | O50: 177549 | P50: 152546 | Q50: 159585 | R50: 173737 | S50: 145705 | T50: 144001 | U50: 147778 | V50: 164620 | W50: 150807 | X50: 116684 | Y50: 137034 | Z50: 155495 | AA50: 161912 | AB50: 169172 | AC50: 137630 | AD50: 135642 | AE50: 127108 | AF50: 131184 | AG50: 115299 | AH50: 123829 | AI50: 115432 | AJ50: 116757 | AK50: 116507 | AL50: 117116 | AM50: 116329 | AN50: 120065 | AO50: 128728 | AP50: 100594 | AQ50: 101615 | AR50: 85811 | AS50: 88293 | AT50: 87814 | AU50: 82868 | AV50: 102859 | AW50: 95743 | AX50: 64346 | AY50: 70384 | AZ50: 80427 | BA50: 73249 | BB50: 69590 | BC50: 61732 | BD50: 43654 | BE50: 41479 | BF50: 40461 | BG50: 31071 | BH50: 24027 | BI50: 20807 | BJ50: 18772 | BK50: 16714 | BL50: 14481 | BM50: 14645
A51: 2021F | B51: US | C51: CLCCP | D51: 16789 | E51: 15293 | F51: 14972 | G51: 13211 | H51: 11409 | I51: 11041 | J51: 11002 | K51: 9518 | L51: 8793 | M51: 8305 | N51: 7090 | O51: 7753 | P51: 6674 | Q51: 7004 | R51: 7764 | S51: 6587 | T51: 6330 | U51: 6447 | V51: 7323 | W51: 6710 | X51: 5097 | Y51: 6085 | Z51: 6839 | AA51: 7096 | AB51: 7395 | AC51: 6068 | AD51: 5904 | AE51: 5324 | AF51: 5561 | AG51: 4872 | AH51: 5379 | AI51: 4997 | AJ51: 5045 | AK51: 5101 | AL51: 5111 | AM51: 5052 | AN51: 5285 | AO51: 5752 | AP51: 4322 | AQ51: 4293 | AR51: 3673 | AS51: 3888 | AT51: 3912 | AU51: 3685 | AV51: 4610 | AW51: 4342 | AX51: 2936 | AY51: 3173 | AZ51: 3506 | BA51: 3210 | BB51: 3081 | BC51: 2793 | BD51: 2045 | BE51: 1951 | BF51: 1887 | BG51: 1503 | BH51: 1183 | BI51: 1061 | BJ51: 972 | BK51: 876 | BL51: 793 | BM51: 811
A52: 2021F | B52: US | C52: CLEIB | D52: 4226595 | E52: 4355064 | F52: 4622438 | G52: 5050061 | H52: 5379761 | I52: 5821355 | J52: 6301552 | K52: 6444876 | L52: 6993577 | M52: 7219168 | N52: 7228006 | O52: 7299249 | P52: 7842523 | Q52: 8659920 | R52: 8538706 | S52: 8789280 | T52: 9730659 | U52: 10258749 | V52: 10253442 | W52: 11270255 | X52: 12157926 | Y52: 12622872 | Z52: 12537754 | AA52: 13184982 | AB52: 13961625 | AC52: 14586431 | AD52: 14418435 | AE52: 15114830 | AF52: 15886154 | AG52: 16135278 | AH52: 16258995 | AI52: 16247935 | AJ52: 16463621 | AK52: 17194422 | AL52: 17259079 | AM52: 17465065 | AN52: 18427577 | AO52: 18902863 | AP52: 19215808 | AQ52: 19279063 | AR52: 20219797 | AS52: 19613575 | AT52: 19782944 | AU52: 20183337 | AV52: 20303713 | AW52: 20735427 | AX52: 20459989 | AY52: 20805249 | AZ52: 20510599 | BA52: 18223766 | BB52: 19133366 | BC52: 18035415 | BD52: 15821257 | BE52: 16450431 | BF52: 16427232 | BG52: 14138235 | BH52: 12996648 | BI52: 12622220 | BJ52: 12053020 | BK52: 10181470 | BL52: 8229142 | BM52: 9496416
... A54: 2021F | B54: US | C54: CLEIP | D54: 176685 | E54: 182185 | F54: 193316 | G54: 211332 | H54: 225425 | I54: 244788 | J54: 266477 | K54: 274185 | L54: 297779 | M54: 310641 | N54: 320182 | O54: 327301 | P54: 351768 | Q54: 389212 | R54: 391811 | S54: 405962 | T54: 448371 | U54: 477126 | V54: 481235 | W54: 527051 | X54: 569274 | Y54: 596797 | Z54: 593666 | AA54: 625211 | AB54: 664399 | AC54: 693841 | AD54: 685056 | AE54: 717894 | AF54: 758372 | AG54: 772190 | AH54: 782567 | AI54: 783874 | AJ54: 795094 | AK54: 831645 | AL54: 838354 | AM54: 850230 | AN54: 896921 | AO54: 921364 | AP54: 936619 | AQ54: 940922 | AR54: 985821 | AS54: 964433 | AT54: 977507 | AU54: 1005063 | AV54: 1016208 | AW54: 1037419 | AX54: 1026571 | AY54: 1045056 | AZ54: 1040483 | BA54: 933539 | BB54: 975052 | BC54: 932484 | BD54: 823551 | BE54: 857962 | BF54: 851602 | BG54: 738444 | BH54: 678554 | BI54: 664993 | BJ54: 637217 | BK54: 538606 | BL54: 435827 | BM54: 501366
A55: 2021F | B55: US | C55: CLGBP | AZ55: 313322 | BA55: 314294 | BB55: 317339 | BC55: 317640 | BD55: 309680 | BE55: 303306 | BF55: 299094 | BG55: 279720 | BH55: 266620 | BI55: 256547 | BJ55: 242786 | BK55: 228657 | BL55: 215554 | BM55: 209826
A56: 2021F | B56: US | C56: CLHCK | D56: 23.943 | E56: 23.942 | F56: 23.889 | G56: 23.794 | H56: 23.815 | I56: 23.776 | J56: 23.654 | K56: 23.436 | L56: 23.368 | M56: 23.205 | N56: 22.99 | O56: 22.902 | P56: 22.858 | Q56: 22.786 | R56: 22.378 | S56: 22.12 | T56: 22.748 | U56: 22.922 | V56: 22.478 | W56: 22.474 | X56: 22.892 | Y56: 22.519 | Z56: 22.736 | AA56: 22.817 | AB56: 22.876 | AC56: 22.682 | AD56: 22.975 | AE56: 23.875 | AF56: 23.588 | AG56: 23.665 | AH56: 23.021 | AI56: 23.099 | AJ56: 23.142 | AK56: 22.838 | AL56: 22.916 | AM56: 23.027 | AN56: 22.718 | AO56: 22.379 | AP56: 23.276 | AQ56: 23.668 | AR56: 23.364 | AS56: 22.706 | AT56: 22.449 | AU56: 22.488 | AV56: 22.314 | AW56: 22.053 | AX56: 21.915 | AY56: 22.179 | AZ56: 22.941 | BA56: 22.82 | BB56: 22.59 | BC56: 22.105 | BD56: 21.35 | BE56: 21.259 | BF56: 21.442 | BG56: 20.667 | BH56: 20.316 | BI56: 19.608 | BJ56: 19.321 | BK56: 19.082 | BL56: 18.258 | BM56: 18.067
A57: 2021F | B57: US | C57: CLICB | D57: 4547884 | E57: 4350831 | F57: 4392800 | G57: 4599452 | H57: 4923268 | I57: 5134435 | J57: 5223593 | K57: 4942087 | L57: 4866866 | M57: 4718533 | N57: 4663514 | O57: 3951081 | P57: 3995678 | Q57: 4044258 | R57: 3855006 | S57: 3657641 | T57: 3642139 | U57: 3442911 | V57: 3302449 | W57: 3582888 | X57: 3155354 | Y57: 3147737 | Z57: 2543952 | AA57: 2489325 | AB57: 2843097 | AC57: 2777190 | AD57: 2646289 | AE57: 2669971 | AF57: 2831324 | AG57: 2773940 | AH57: 2753900 | AI57: 2600434 | AJ57: 2511793 | AK57: 2499623 | AL57: 2506697 | AM57: 2500067 | AN57: 2438143 | AO57: 2396101 | AP57: 2254489 | AQ57: 2187568 | AR57: 2259324 | AS57: 2193574 | AT57: 2020119 | AU57: 2044047 | AV57: 2046302 | AW57: 1953954 | AX57: 1913516 | AY57: 1864461 | AZ57: 1791789 | BA57: 1394326 | BB57: 1625426 | BC57: 1566710 | BD57: 1516013 | BE57: 1546861 | BF57: 1528884 | BG57: 1379678 | BH57: 1206462 | BI57: 1196605 | BJ57: 1178166 | BK57: 1116741 | BL57: 939074 | BM57: 1036702
A58: 2021F | B58: US | C58: CLICP | D58: 177402 | E58: 170098 | F58: 171741 | G58: 180024 | H58: 192369 | I58: 200846 | J58: 205076 | K58: 194645 | L58: 191648 | M58: 186586 | N58: 186637 | O58: 158866 | P58: 160624 | Q58: 162139 | R58: 155094 | S58: 147244 | T58: 146491 | U58: 139202 | V58: 134479 | W58: 145085 | X58: 127003 | Y58: 128410 | Z58: 105004 | AA58: 103013 | AB58: 117767 | AC58: 116429 | AD58: 111446 | AE58: 112052 | AF58: 118140 | AG58: 116643 | AH58: 115207 | AI58: 109259 | AJ58: 106408 | AK58: 106215 | AL58: 106919 | AM58: 106067 | AN58: 103395 | AO58: 101718 | AP58: 95628 | AQ58: 92846 | AR58: 94147 | AS58: 91344 | AT58: 84403 | AU58: 85509 | AV58: 85865 | AW58: 83774 | AX58: 82429 | AY58: 79331 | AZ58: 76463 | BA58: 60641 | BB58: 70381 | BC58: 67671 | BD58: 63589 | BE58: 64529 | BF58: 64243 | BG58: 58167 | BH58: 51333 | BI58: 50801 | BJ58: 49917 | BK58: 47062 | BL58: 40073 | BM58: 43434
A59: 2021F | B59: US | C59: CLKCB | D59: 2180349 | E59: 1987969 | F59: 2000581 | G59: 2091438 | H59: 2390576 | I59: 2552406 | J59: 2582365 | K59: 2485301 | L59: 2444894 | M59: 2502344 | N59: 2584122 | O59: 2229205 | P59: 2349983 | Q59: 2519980 | R59: 2415134 | S59: 2238950 | T59: 2268478 | U59: 2082406 | V59: 1912597 | W59: 2072555 | X59: 1785716 | Y59: 1634799 | Z59: 1096201 | AA59: 992417 | AB59: 1179737 | AC59: 1100196 | AD59: 961026 | AE59: 988279 | AF59: 1122560 | AG59: 1085642 | AH59: 1041846 | AI59: 907260 | AJ59: 867397 | AK59: 839450 | AL59: 850640 | AM59: 884699 | AN59: 849714 | AO59: 809440 | AP59: 773092 | AQ59: 770879 | AR59: 793680 | AS59: 715129 | AT59: 648778 | AU59: 665003 | AV59: 649166 | AW59: 615998 | AX59: 603030 | AY59: 597930 | AZ59: 580198 | BA59: 403421 | BB59: 554747 | BC59: 563997 | BD59: 594238 | BE59: 616422 | BF59: 606019 | BG59: 562064 | BH59: 471626 | BI59: 502867 | BJ59: 524533 | BK59: 514538 | BL59: 413420 | BM59: 504154
A60: 2021F | B60: US | C60: CLKCK | D60: 26.791 | E60: 26.792 | F60: 26.788 | G60: 26.784 | H60: 26.785 | I60: 26.787 | J60: 26.786 | K60: 26.781 | L60: 26.78 | M60: 26.779 | N60: 26.784 | O60: 26.784 | P60: 26.782 | Q60: 26.78 | R60: 26.778 | S60: 26.782 | T60: 26.781 | U60: 26.787 | V60: 26.789 | W60: 26.788 | X60: 26.79 | Y60: 26.794 | Z60: 26.797 | AA60: 26.798 | AB60: 26.799 | AC60: 26.797 | AD60: 26.798 | AE60: 26.799 | AF60: 26.799 | AG60: 26.8 | AH60: 26.799 | AI60: 26.799 | AJ60: 26.799 | AK60: 26.8 | AL60: 26.8 | AM60: 26.8 | AN60: 26.8 | AO60: 26.8 | AP60: 27.426 | AQ60: 27.426 | AR60: 27.426 | AS60: 27.426 | AT60: 27.426 | AU60: 27.425 | AV60: 27.426 | AW60: 26.286 | AX60: 26.268 | AY60: 26.323 | AZ60: 26.289 | BA60: 26.322 | BB60: 26.301 | BC60: 26.313 | BD60: 28.636 | BE60: 28.706 | BF60: 28.456 | BG60: 28.519 | BH60: 28.61 | BI60: 28.674 | BJ60: 28.606 | BK60: 28.639 | BL60: 28.683 | BM60: 28.664
A61: 2021F | B61: US | C61: CLKCP | D61: 81385 | E61: 74201 | F61: 74682 | G61: 78084 | H61: 89249 | I61: 95286 | J61: 96407 | K61: 92800 | L61: 91297 | M61: 93444 | N61: 96481 | O61: 83230 | P61: 87746 | Q61: 94101 | R61: 90191 | S61: 83598 | T61: 84704 | U61: 77739 | V61: 71394 | W61: 77368 | X61: 66656 | Y61: 61014 | Z61: 40907 | AA61: 37033 | AB61: 44022 | AC61: 41056 | AD61: 35862 | AE61: 36877 | AF61: 41888 | AG61: 40508 | AH61: 38877 | AI61: 33854 | AJ61: 32366 | AK61: 31323 | AL61: 31740 | AM61: 33011 | AN61: 31706 | AO61: 30203 | AP61: 28189 | AQ61: 28108 | AR61: 28939 | AS61: 26075 | AT61: 23656 | AU61: 24248 | AV61: 23670 | AW61: 23434 | AX61: 22957 | AY61: 22715 | AZ61: 22070 | BA61: 15326 | BB61: 21092 | BC61: 21434 | BD61: 20751 | BE61: 21474 | BF61: 21297 | BG61: 19708 | BH61: 16485 | BI61: 17538 | BJ61: 18337 | BK61: 17967 | BL61: 14414 | BM61: 17589
A62: 2021F | B62: US | C62: CLOCB | D62: 2367535 | E62: 2362862 | F62: 2392219 | G62: 2508014 | H62: 2532692 | I62: 2582030 | J62: 2641228 | K62: 2456786 | L62: 2421972 | M62: 2216189 | N62: 2079392 | O62: 1721875 | P62: 1645695 | Q62: 1524278 | R62: 1439872 | S62: 1418691 | T62: 1373661 | U62: 1360504 | V62: 1389852 | W62: 1510333 | X62: 1369639 | Y62: 1512939 | Z62: 1447751 | AA62: 1496908 | AB62: 1663360 | AC62: 1676994 | AD62: 1685264 | AE62: 1681692 | AF62: 1708764 | AG62: 1688297 | AH62: 1712054 | AI62: 1693175 | AJ62: 1644396 | AK62: 1660172 | AL62: 1656056 | AM62: 1615368 | AN62: 1588428 | AO62: 1586661 | AP62: 1481397 | AQ62: 1416689 | AR62: 1465644 | AS62: 1478445 | AT62: 1371341 | AU62: 1379044 | AV62: 1397136 | AW62: 1337956 | AX62: 1310486 | AY62: 1266531 | AZ62: 1211592 | BA62: 990905 | BB62: 1070679 | BC62: 1002713 | BD62: 921775 | BE62: 930439 | BF62: 922865 | BG62: 817615 | BH62: 734836 | BI62: 693739 | BJ62: 653633 | BK62: 602203 | BL62: 525654 | BM62: 532548
A63: 2021F | B63: US | C63: CLOCK | D63: 24.657 | E63: 24.64 | F63: 24.647 | G63: 24.603 | H63: 24.561 | I63: 24.46 | J63: 24.305 | K63: 24.123 | L63: 24.135 | M63: 23.794 | N63: 23.064 | O63: 22.765 | P63: 22.582 | Q63: 22.403 | R63: 22.185 | S63: 22.29 | T63: 22.232 | U63: 22.135 | V63: 22.031 | W63: 22.304 | X63: 22.696 | Y63: 22.449 | Z63: 22.587 | AA63: 22.687 | AB63: 22.556 | AC63: 22.249 | AD63: 22.297 | AE63: 22.37 | AF63: 22.409 | AG63: 22.175 | AH63: 22.43 | AI63: 22.454 | AJ63: 22.209 | AK63: 22.168 | AL63: 22.028 | AM63: 22.112 | AN63: 22.157 | AO63: 22.187 | AP63: 21.966 | AQ63: 21.883 | AR63: 22.476 | AS63: 22.652 | AT63: 22.575 | AU63: 22.511 | AV63: 22.464 | AW63: 22.174 | AX63: 22.035 | AY63: 22.371 | AZ63: 22.275 | BA63: 21.867 | BB63: 21.722 | BC63: 21.686 | BD63: 21.518 | BE63: 21.611 | BF63: 21.489 | BG63: 21.26 | BH63: 21.086 | BI63: 20.856 | BJ63: 20.698 | BK63: 20.698 | BL63: 20.486 | BM63: 20.605
A64: 2021F | B64: US | C64: CLOCP | D64: 96017 | E64: 95897 | F64: 97059 | G64: 101940 | H64: 103120 | I64: 105560 | J64: 108669 | K64: 101845 | L64: 100351 | M64: 93142 | N64: 90156 | O64: 75636 | P64: 72878 | Q64: 68038 | R64: 64903 | S64: 63646 | T64: 61787 | U64: 61463 | V64: 63085 | W64: 67717 | X64: 60347 | Y64: 67395 | Z64: 64097 | AA64: 65980 | AB64: 73745 | AC64: 75372 | AD64: 75583 | AE64: 75175 | AF64: 76252 | AG64: 76134 | AH64: 76330 | AI64: 75405 | AJ64: 74042 | AK64: 74892 | AL64: 75179 | AM64: 73055 | AN64: 71689 | AO64: 71515 | AP64: 67439 | AQ64: 64738 | AR64: 65208 | AS64: 65268 | AT64: 60747 | AU64: 61261 | AV64: 62195 | AW64: 60340 | AX64: 59472 | AY64: 56615 | AZ64: 54393 | BA64: 45314 | BB64: 49289 | BC64: 46238 | BD64: 42838 | BE64: 43055 | BF64: 42946 | BG64: 38459 | BH64: 34849 | BI64: 33264 | BJ64: 31580 | BK64: 29095 | BL64: 25660 | BM64: 25845
A65: 2021F | B65: US | C65: CLRCB | D65: 578443 | E65: 526883 | F65: 514666 | G65: 434076 | H65: 375218 | I65: 347969 | J65: 344991 | K65: 295676 | L65: 261494 | M65: 245260 | N65: 207457 | O65: 170586 | P65: 115079 | Q65: 93725 | R65: 81758 | S65: 62445 | T65: 58817 | U65: 57469 | V65: 49172 | W65: 37702 | X65: 31017 | Y65: 30081 | Z65: 31848 | AA65: 30840 | AB65: 39682 | AC65: 38819 | AD65: 40517 | AE65: 37967 | AF65: 37001 | AG65: 30649 | AH65: 30957 | AI65: 25339 | AJ65: 25630 | AK65: 25575 | AL65: 20667 | AM65: 17382 | AN65: 16372 | AO65: 15910 | AP65: 12433 | AQ65: 13857 | AR65: 10606 | AS65: 10913 | AT65: 11975 | AU65: 12383 | AV65: 11429 | AW65: 8325 | AX65: 6364 | AY65: 7820 | AZ65: 0 | BA65: 0 | BB65: 0 | BC65: 0 | BD65: 0 | BE65: 0 | BF65: 0 | BG65: 0 | BH65: 0 | BI65: 0 | BJ65: 0 | BK65: 0 | BL65: 0 | BM65: 0
A66: 2021F | B66: US | C66: CLRCP | D66: 24159 | E66: 22006 | F66: 21544 | G66: 18243 | H66: 15756 | I66: 14635 | J66: 14585 | K66: 12616 | L66: 11190 | M66: 10569 | N66: 9024 | O66: 7448 | P66: 5034 | Q66: 4113 | R66: 3653 | S66: 2823 | T66: 2586 | U66: 2507 | V66: 2188 | W66: 1678 | X66: 1355 | Y66: 1336 | Z66: 1401 | AA66: 1352 | AB66: 1735 | AC66: 1711 | AD66: 1763 | AE66: 1590 | AF66: 1569 | AG66: 1295 | AH66: 1345 | AI66: 1097 | AJ66: 1107 | AK66: 1120 | AL66: 902 | AM66: 755 | AN66: 721 | AO66: 711 | AP66: 534 | AQ66: 585 | AR66: 454 | AS66: 481 | AT66: 533 | AU66: 551 | AV66: 512 | AW66: 378 | AX66: 290 | AY66: 353 | AZ66: 0 | BA66: 0 | BB66: 0 | BC66: 0 | BD66: 0 | BE66: 0 | BF66: 0 | BG66: 0 | BH66: 0 | BI66: 0 | BJ66: 0 | BK66: 0 | BL66: 0 | BM66: 0
A67: 2021F | B67: US | C67: CLTCB | D67: 9830513 | E67: 9618013 | F67: 9904585 | G67: 10414512 | H67: 10967543 | I67: 11582398 | J67: 12145291 | K67: 11917043 | L67: 12337535 | M67: 12383168 | N67: 12268895 | O67: 11603202 | P67: 12109530 | Q67: 12960121 | R67: 12651009 | S67: 12655613 | T67: 13575890 | U67: 13907111 | V67: 13769684 | W67: 15041652 | X67: 15460982 | Y67: 15937724 | Z67: 15269049 | AA67: 15867060 | AB67: 17013578 | AC67: 17540071 | AD67: 17240884 | AE67: 17949877 | AF67: 18885663 | AG67: 19055165 | AH67: 19167682 | AI67: 18989140 | AJ67: 19117802 | AK67: 19836126 | AL67: 19903559 | AM67: 20098843 | AN67: 21002157 | AO67: 21443603 | AP67: 21583324 | AQ67: 21582103 | AR67: 22575538 | AS67: 21906355 | AT67: 21902852 | AU67: 22322634 | AV67: 22464302 | AW67: 22793450 | AX67: 22444214 | AY67: 22747914 | AZ67: 22382816 | BA67: 19691342 | BB67: 20828382 | BC67: 19663856 | BD67: 17380923 | BE67: 18038771 | BF67: 17996577 | BG67: 15548985 | BH67: 14227138 | BI67: 13839632 | BJ67: 13249958 | BK67: 11314925 | BL67: 9182696 | BM67: 10547764
... A94: 2021F | B94: US | C94: ELEXP | D94: 788 | E94: 917 | F94: 1661 | G94: 1985 | H94: 4253 | I94: 3699 | J94: 3176 | K94: 4350 | L94: 4285 | M94: 3830 | N94: 4209 | O94: 3514 | P94: 2809 | Q94: 2570 | R94: 2726 | S94: 5083 | T94: 2378 | U94: 2744 | V94: 1478 | W94: 2182 | X94: 4096 | Y94: 3060 | Z94: 3536 | AA94: 3337 | AB94: 2558 | AC94: 4965 | AD94: 4816 | AE94: 5882 | AF94: 7067 | AG94: 15135 | AH94: 16134 | AI94: 2305 | AJ94: 2826 | AK94: 3541 | AL94: 2010 | AM94: 3623 | AN94: 3302 | AO94: 8974 | AP94: 13656 | AQ94: 14222 | AR94: 14829 | AS94: 16473 | AT94: 15796 | AU94: 23975 | AV94: 22898 | AW94: 19151 | AX94: 24271 | AY94: 20144 | AZ94: 24198 | BA94: 18138 | BB94: 19106 | BC94: 15049 | BD94: 11996 | BE94: 11373 | BF94: 13298 | BG94: 9118 | BH94: 6214 | BI94: 9371 | BJ94: 13804 | BK94: 20008 | BL94: 14135 | BM94: 13855
A95: 2021F | B95: US | C95: ELGBP | AZ95: 1010171 | BA95: 1025400 | BB95: 1039062 | BC95: 1051251 | BD95: 1063033 | BE95: 1060064 | BF95: 1068422 | BG95: 1064055 | BH95: 1074333 | BI95: 1084370 | BJ95: 1094740 | BK95: 1099110 | BL95: 1115682 | BM95: 1145857
A96: 2021F | B96: US | C96: ELIMB | D96: 18163 | E96: 10816 | F96: 7495 | G96: 7107 | H96: 21184 | I96: 12140 | J96: 14563 | K96: 13823 | L96: 12467 | M96: 16725 | N96: 21051 | O96: 24035 | P96: 35811 | Q96: 57484 | R96: 52612 | S96: 38446 | T96: 37493 | U96: 68783 | V96: 72360 | W96: 76824 | X96: 85373 | Y96: 123847 | Z96: 112092 | AA96: 131934 | AB96: 144052 | AC96: 156595 | AD96: 138912 | AE96: 178171 | AF96: 132510 | AG96: 89089 | AH96: 62936 | AI96: 74829 | AJ96: 96377 | AK96: 106992 | AL96: 159795 | AM96: 146216 | AN96: 148410 | AO96: 146823 | AP96: 134819 | AQ96: 147449 | AR96: 165797 | AS96: 131363 | AT96: 125491 | AU96: 103706 | AV96: 116725 | AW96: 149887 | AX96: 145663 | AY96: 175362 | AZ96: 194550 | BA96: 178074 | BB96: 153824 | BC96: 178447 | BD96: 202185 | BE96: 236278 | BF96: 226933 | BG96: 257928 | BH96: 248108 | BI96: 224117 | BJ96: 198785 | BK96: 201487 | BL96: 209664 | BM96: 181406
A97: 2021F | B97: US | C97: ELIMP | D97: 5323 | E97: 3170 | F97: 2197 | G97: 2083 | H97: 6209 | I97: 3558 | J97: 4268 | K97: 4051 | L97: 3654 | M97: 4902 | N97: 6170 | O97: 7044 | P97: 10495 | Q97: 16848 | R97: 15420 | S97: 11268 | T97: 10988 | U97: 20159 | V97: 21208 | W97: 22516 | X97: 25021 | Y97: 36298 | Z97: 32852 | AA97: 38668 | AB97: 42219 | AC97: 45895 | AD97: 40713 | AE97: 52219 | AF97: 38837 | AG97: 26110 | AH97: 18445 | AI97: 21931 | AJ97: 28247 | AK97: 31358 | AL97: 46833 | AM97: 42854 | AN97: 43497 | AO97: 43031 | AP97: 39513 | AQ97: 43215 | AR97: 48592 | AS97: 38500 | AT97: 36779 | AU97: 30395 | AV97: 34210 | AW97: 43929 | AX97: 42691 | AY97: 51396 | AZ97: 57019 | BA97: 52191 | BB97: 45083 | BC97: 52300 | BD97: 59257 | BE97: 69249 | BF97: 66510 | BG97: 75594 | BH97: 72716 | BI97: 65685 | BJ97: 58261 | BK97: 59052 | BL97: 61449 | BM97: 53167
A98: 2021F | B98: US | C98: ELISB | D98: 0 | E98: 0 | F98: 0 | G98: 0 | H98: 0 | I98: 0 | J98: 0 | K98: 0 | L98: 0 | M98: 0 | N98: 0 | O98: 0 | P98: 0 | Q98: 0 | R98: 0 | S98: 0 | T98: 0 | U98: 0 | V98: 0 | W98: 0 | X98: 0 | Y98: 0 | Z98: 0 | AA98: 0 | AB98: 0 | AC98: 0 | AD98: 0 | AE98: 0 | AF98: 0 | AG98: 0 | AH98: 0 | AI98: 0 | AJ98: 0 | AK98: 0 | AL98: 0 | AM98: 0 | AN98: 0 | AO98: 0 | AP98: 0 | AQ98: 0 | AR98: 0 | AS98: 0 | AT98: 0 | AU98: 0 | AV98: 0 | AW98: 0 | AX98: 0 | AY98: 0 | AZ98: 0 | BA98: 0 | BB98: 0 | BC98: 0 | BD98: 0 | BE98: 0 | BF98: 0 | BG98: 0 | BH98: 0 | BI98: 0 | BJ98: 0 | BK98: 0 | BL98: 0 | BM98: 0
A99: 2021F | B99: US | C99: ELISP | AH99: 0 | AI99: 0 | AJ99: 0 | AK99: 0 | AL99: 0 | AM99: 0 | AN99: 0 | AO99: 0 | AP99: 0 | AQ99: 0 | AR99: 0 | AS99: 0 | AT99: 0 | AU99: 0 | AV99: 0 | AW99: 0 | AX99: 0 | AY99: 0 | AZ99: 0 | BA99: 0 | BB99: 0 | BC99: 0 | BD99: 0 | BE99: 0 | BF99: 0 | BG99: 0 | BH99: 0 | BI99: 0 | BJ99: 0 | BK99: 0 | BL99: 0 | BM99: 0
A100: 2021F | B100: US | C100: ELNIB | D100: 15474 | E100: 7689 | F100: 1829 | G100: 334 | H100: 6671 | I100: -482 | J100: 3725 | K100: -1020 | L100: -2152 | M100: 3656 | N100: 6688 | O100: 12046 | P100: 26227 | Q100: 48715 | R100: 43311 | S100: 21103 | T100: 29378 | U100: 59422 | V100: 67318 | W100: 69381 | X100: 71399 | Y100: 113406 | Z100: 100026 | AA100: 120547 | AB100: 135323 | AC100: 139655 | AD100: 122481 | AE100: 158101 | AF100: 108399 | AG100: 37450 | AH100: 7888 | AI100: 66965 | AJ100: 86737 | AK100: 94910 | AL100: 152937 | AM100: 133856 | AN100: 137144 | AO100: 116203 | AP100: 88224 | AQ100: 98924 | AR100: 115199 | AS100: 75156 | AT100: 71596 | AU100: 21905 | AV100: 38597 | AW100: 84544 | AX100: 62849 | AY100: 106632 | AZ100: 111986 | BA100: 116188 | BB100: 88634 | BC100: 127101 | BD100: 161256 | BE100: 197472 | BF100: 181559 | BG100: 226819 | BH100: 226906 | BI100: 192144 | BJ100: 151684 | BK100: 133220 | BL100: 161436 | BM100: 134131
A101: 2021F | B101: US | C101: ELNIP | D101: 4535 | E101: 2254 | F101: 536 | G101: 98 | H101: 1955 | I101: -141 | J101: 1092 | K101: -299 | L101: -631 | M101: 1072 | N101: 1960 | O101: 3530 | P101: 7687 | Q101: 14278 | R101: 12694 | S101: 6185 | T101: 8610 | U101: 17416 | V101: 19730 | W101: 20334 | X101: 20926 | Y101: 33237 | Z101: 29316 | AA101: 35330 | AB101: 39661 | AC101: 40931 | AD101: 35897 | AE101: 46337 | AF101: 31770 | AG101: 10976 | AH101: 2312 | AI101: 19626 | AJ101: 25421 | AK101: 27817 | AL101: 44823 | AM101: 39231 | AN101: 40195 | AO101: 34057 | AP101: 25857 | AQ101: 28993 | AR101: 33763 | AS101: 22027 | AT101: 20984 | AU101: 6420 | AV101: 11312 | AW101: 24778 | AX101: 18420 | AY101: 31252 | AZ101: 32821 | BA101: 34053 | BB101: 25977 | BC101: 37251 | BD101: 47261 | BE101: 57876 | BF101: 53212 | BG101: 66477 | BH101: 66502 | BI101: 56314 | BJ101: 44456 | BK101: 39044 | BL101: 47314 | BM101: 39312
A102: 2021F | B102: US | C102: EMACB | D102: 0 | E102: 0 | F102: 0 | G102: 0 | H102: 0 | I102: 0 | J102: 0 | K102: 0 | L102: 0 | M102: 0 | N102: 0 | O102: 0 | P102: 0 | Q102: 0 | R102: 0 | S102: 0 | T102: 0 | U102: 0 | V102: 0 | W102: 0 | X102: 0 | Y102: 6559 | Z102: 17999 | AA102: 33561 | AB102: 40953 | AC102: 49509 | AD102: 57178 | AE102: 65794 | AF102: 66825 | AG102: 67814 | AH102: 60254 | AI102: 69774 | AJ102: 79277 | AK102: 93188 | AL102: 104446 | AM102: 112145 | AN102: 80484 | AO102: 101196 | AP102: 112221 | AQ102: 117411 | AR102: 134597 | AS102: 140409 | AT102: 167052 | AU102: 227531 | AV102: 286229 | AW102: 327770 | AX102: 442403 | AY102: 557570 | AZ102: 785807 | BA102: 893957 | BB102: 1041483 | BC102: 1045041 | BD102: 1044666 | BE102: 1071703 | BF102: 1093418 | BG102: 1109733 | BH102: 1143028 | BI102: 1155526 | BJ102: 1152372 | BK102: 1161542 | BL102: 1004238 | BM102: 1109441
A103: 2021F | B103: US | C103: EMCCB | D103: 0 | E103: 0 | F103: 0 | G103: 0 | H103: 0 | I103: 0 | J103: 0 | K103: 0 | L103: 0 | M103: 0 | N103: 0 | O103: 0 | P103: 0 | Q103: 0 | R103: 0 | S103: 0 | T103: 0 | U103: 0 | V103: 0 | W103: 0 | X103: 0 | Y103: 60 | Z103: 155 | AA103: 279 | AB103: 366 | AC103: 361 | AD103: 489 | AE103: 567 | AF103: 646 | AG103: 566 | AH103: 506 | AI103: 483 | AJ103: 480 | AK103: 293 | AL103: 218 | AM103: 176 | AN103: 206 | AO103: 672 | AP103: 618 | AQ103: 259 | AR103: 402 | AS103: 420 | AT103: 540 | AU103: 1088 | AV103: 903 | AW103: 586 | AX103: 1109 | AY103: 1349 | AZ103: 2099 | BA103: 2802 | BB103: 3259 | BC103: 2863 | BD103: 2552 | BE103: 2639 | BF103: 3706 | BG103: 25701 | BH103: 25772 | BI103: 25129 | BJ103: 25495 | BK103: 25962 | BL103: 26261 | BM103: 26690
A104: 2021F | B104: US | C104: EMICB | D104: 0 | E104: 0 | F104: 0 | G104: 0 | H104: 0 | I104: 0 | J104: 0 | K104: 0 | L104: 0 | M104: 0 | N104: 0 | O104: 0 | P104: 0 | Q104: 0 | R104: 0 | S104: 0 | T104: 0 | U104: 0 | V104: 0 | W104: 0 | X104: 0 | Y104: 241 | Z104: 466 | AA104: 460 | AB104: 821 | AC104: 1089 | AD104: 1133 | AE104: 1259 | AF104: 1129 | AG104: 1200 | AH104: 980 | AI104: 1284 | AJ104: 1583 | AK104: 1565 | AL104: 1772 | AM104: 1849 | AN104: 1202 | AO104: 1829 | AP104: 1744 | AQ104: 1463 | AR104: 1535 | AS104: 2912 | AT104: 3600 | AU104: 4744 | AV104: 6197 | AW104: 6792 | AX104: 9108 | AY104: 9678 | AZ104: 11713 | BA104: 12894 | BB104: 16476 | BC104: 16731 | BD104: 16629 | BE104: 17483 | BF104: 14164 | BG104: 17621 | BH104: 18081 | BI104: 18471 | BJ104: 18765 | BK104: 18775 | BL104: 19045 | BM104: 18822
A105: 2021F | B105: US | C105: EMLCB | D105: 0 | E105: 0 | F105: 0 | G105: 0 | H105: 0 | I105: 0 | J105: 0 | K105: 0 | L105: 0 | M105: 0 | N105: 0 | O105: 0 | P105: 0 | Q105: 0 | R105: 0 | S105: 0 | T105: 0 | U105: 0 | V105: 0 | W105: 0 | X105: 0 | Y105: 5860 | Z105: 15784 | AA105: 28843 | AB105: 35162 | AC105: 42191 | AD105: 48299 | AE105: 55105 | AF105: 55458 | AG105: 55798 | AH105: 49127 | AI105: 56460 | AJ105: 63665 | AK105: 74016 | AL105: 81955 | AM105: 85627 | AN105: 60897 | AO105: 79931 | AP105: 86451 | AQ105: 89834 | AR105: 99179 | AS105: 107582 | AT105: 130036 | AU105: 167976 | AV105: 200975 | AW105: 227117 | AX105: 279906 | AY105: 368222 | AZ105: 517598 | BA105: 601686 | BB105: 725970 | BC105: 753993 | BD105: 709127 | BE105: 711235 | BF105: 764221 | BG105: 788345 | BH105: 818059 | BI105: 844342 | BJ105: 851961 | BK105: 831945 | BL105: 731951 | BM105: 786485
A106: 2021F | B106: US | C106: EMTCB | D106: 0 | E106: 0 | F106: 0 | G106: 0 | H106: 0 | I106: 0 | J106: 0 | K106: 0 | L106: 0 | M106: 0 | N106: 0 | O106: 0 | P106: 0 | Q106: 0 | R106: 0 | S106: 0 | T106: 0 | U106: 0 | V106: 0 | W106: 0 | X106: 0 | Y106: 6860 | Z106: 18620 | AA106: 34300 | AB106: 42140 | AC106: 50960 | AD106: 58800 | AE106: 67620 | AF106: 68600 | AG106: 69580 | AH106: 61740 | AI106: 71540 | AJ106: 81340 | AK106: 95047 | AL106: 106436 | AM106: 114170 | AN106: 81892 | AO106: 103696 | AP106: 114583 | AQ106: 119133 | AR106: 136533 | AS106: 143740 | AT106: 171191 | AU106: 233363 | AV106: 293328 | AW106: 335148 | AX106: 452620 | AY106: 568597 | AZ106: 799619 | BA106: 909653 | BB106: 1061218 | BC106: 1064634 | BD106: 1063847 | BE106: 1091826 | BF106: 1111288 | BG106: 1153054 | BH106: 1186881 | BI106: 1199125 | BJ106: 1196632 | BK106: 1206278 | BL106: 1049544 | BM106: 1154953
A107: 2021F | B107: US | C107: ENACP | D107: 0 | E107: 0 | F107: 0 | G107: 0 | H107: 0 | I107: 0 | J107: 0 | K107: 0 | L107: 0 | M107: 0 | N107: 0 | O107: 0 | P107: 0 | Q107: 0 | R107: 0 | S107: 0 | T107: 0 | U107: 0 | V107: 0 | W107: 0 | X107: 0 | Y107: 1891 | Z107: 5190 | AA107: 9677 | AB107: 11808 | AC107: 14275 | AD107: 16486 | AE107: 18971 | AF107: 19268 | AG107: 19553 | AH107: 17373 | AI107: 20118 | AJ107: 22858 | AK107: 26869 | AL107: 30115 | AM107: 32335 | AN107: 23206 | AO107: 29178 | AP107: 32357 | AQ107: 33853 | AR107: 38809 | AS107: 40485 | AT107: 48166 | AU107: 65605 | AV107: 82529 | AW107: 94507 | AX107: 127559 | AY107: 160765 | AZ107: 226574 | BA107: 258242 | BB107: 300462 | BC107: 301334 | BD107: 301181 | BE107: 308859 | BF107: 314948 | BG107: 319588 | BH107: 329188 | BI107: 332342 | BJ107: 330643 | BK107: 333619 | BL107: 288892 | BM107: 318927
A108: 2021F | B108: US | C108: ENCCP | D108: 0 | E108: 0 | F108: 0 | G108: 0 | H108: 0 | I108: 0 | J108: 0 | K108: 0 | L108: 0 | M108: 0 | N108: 0 | O108: 0 | P108: 0 | Q108: 0 | R108: 0 | S108: 0 | T108: 0 | U108: 0 | V108: 0 | W108: 0 | X108: 0 | Y108: 17 | Z108: 45 | AA108: 80 | AB108: 106 | AC108: 104 | AD108: 141 | AE108: 163 | AF108: 186 | AG108: 163 | AH108: 146 | AI108: 139 | AJ108: 138 | AK108: 84 | AL108: 63 | AM108: 51 | AN108: 59 | AO108: 194 | AP108: 178 | AQ108: 75 | AR108: 116 | AS108: 121 | AT108: 156 | AU108: 314 | AV108: 260 | AW108: 169 | AX108: 320 | AY108: 389 | AZ108: 605 | BA108: 810 | BB108: 940 | BC108: 826 | BD108: 736 | BE108: 761 | BF108: 1068 | BG108: 7401 | BH108: 7422 | BI108: 7227 | BJ108: 7315 | BK108: 7457 | BL108: 7555 | BM108: 7673
A109: 2021F | B109: US | C109: ENICP | D109: 0 | E109: 0 | F109: 0 | G109: 0 | H109: 0 | I109: 0 | J109: 0 | K109: 0 | L109: 0 | M109: 0 | N109: 0 | O109: 0 | P109: 0 | Q109: 0 | R109: 0 | S109: 0 | T109: 0 | U109: 0 | V109: 0 | W109: 0 | X109: 0 | Y109: 69 | Z109: 134 | AA109: 133 | AB109: 237 | AC109: 314 | AD109: 327 | AE109: 363 | AF109: 326 | AG109: 346 | AH109: 283 | AI109: 370 | AJ109: 456 | AK109: 451 | AL109: 511 | AM109: 533 | AN109: 346 | AO109: 527 | AP109: 503 | AQ109: 422 | AR109: 443 | AS109: 839 | AT109: 1038 | AU109: 1368 | AV109: 1787 | AW109: 1958 | AX109: 2626 | AY109: 2791 | AZ109: 3377 | BA109: 3725 | BB109: 4753 | BC109: 4824 | BD109: 4794 | BE109: 5039 | BF109: 4080 | BG109: 5075 | BH109: 5207 | BI109: 5312 | BJ109: 5384 | BK109: 5392 | BL109: 5479 | BM109: 5411
A110: 2021F | B110: US | C110: ENTCK | D110: 0 | E110: 0 | F110: 0 | G110: 0 | H110: 0 | I110: 0 | J110: 0 | K110: 0 | L110: 0 | M110: 0 | N110: 0 | O110: 0 | P110: 0 | Q110: 0 | R110: 0 | S110: 0 | T110: 0 | U110: 0 | V110: 0 | W110: 0 | X110: 0 | Y110: 3.564 | Z110: 3.564 | AA110: 3.564 | AB110: 3.564 | AC110: 3.564 | AD110: 3.564 | AE110: 3.564 | AF110: 3.564 | AG110: 3.564 | AH110: 3.564 | AI110: 3.564 | AJ110: 3.564 | AK110: 3.564 | AL110: 3.564 | AM110: 3.564 | AN110: 3.564 | AO110: 3.564 | AP110: 3.564 | AQ110: 3.564 | AR110: 3.564 | AS110: 3.564 | AT110: 3.564 | AU110: 3.564 | AV110: 3.564 | AW110: 3.564 | AX110: 3.564 | AY110: 3.564 | AZ110: 3.564 | BA110: 3.564 | BB110: 3.562 | BC110: 3.561 | BD110: 3.56 | BE110: 3.56 | BF110: 3.559 | BG110: 3.558 | BH110: 3.558 | BI110: 3.556 | BJ110: 3.553 | BK110: 3.555 | BL110: 3.557 | BM110: 3.555
A111: 2021F | B111: US | C111: ENTCP | D111: 0 | E111: 0 | F111: 0 | G111: 0 | H111: 0 | I111: 0 | J111: 0 | K111: 0 | L111: 0 | M111: 0 | N111: 0 | O111: 0 | P111: 0 | Q111: 0 | R111: 0 | S111: 0 | T111: 0 | U111: 0 | V111: 0 | W111: 0 | X111: 0 | Y111: 1978 | Z111: 5369 | AA111: 9890 | AB111: 12150 | AC111: 14693 | AD111: 16954 | AE111: 19497 | AF111: 19780 | AG111: 20062 | AH111: 17802 | AI111: 20627 | AJ111: 23453 | AK111: 27405 | AL111: 30689 | AM111: 32919 | AN111: 23612 | AO111: 29899 | AP111: 33038 | AQ111: 34350 | AR111: 39367 | AS111: 41445 | AT111: 49360 | AU111: 67286 | AV111: 84576 | AW111: 96634 | AX111: 130505 | AY111: 163945 | AZ111: 230556 | BA111: 262776 | BB111: 306155 | BC111: 306984 | BD111: 306711 | BE111: 314658 | BF111: 320095 | BG111: 332064 | BH111: 341817 | BI111: 344882 | BJ111: 343342 | BK111: 346468 | BL111: 301925 | BM111: 332010
A112: 2021F | B112: US | C112: EQICB | BB112: 887849 | BC112: 963463 | BD112: 967432 | BE112: 1010788 | BF112: 1057816 | BG112: 1091028 | BH112: 1150498 | BI112: 1259906 | BJ112: 1502628 | BK112: 1560923 | BL112: 1749770 | BM112: 1835425
A113: 2021F | B113: US | C113: EQICP | BB113: 319026 | BC113: 346196 | BD113: 347622 | BE113: 363201 | BF113: 380099 | BG113: 392033 | BH113: 413402 | BI113: 452715 | BJ113: 539931 | BK113: 560878 | BL113: 628735 | BM113: 659513
A114: 2021F | B114: US | C114: EQTCB | BB114: 887849 | BC114: 963463 | BD114: 967432 | BE114: 1010788 | BF114: 1057816 | BG114: 1091028 | BH114: 1150498 | BI114: 1259906 | BJ114: 1502628 | BK114: 1560923 | BL114: 1749770 | BM114: 1835425
A115: 2021F | B115: US | C115: EQTCP | BB115: 319026 | BC115: 346196 | BD115: 347622 | BE115: 363201 | BF115: 380099 | BG115: 392033 | BH115: 413402 | BI115: 452715 | BJ115: 539931 | BK115: 560878 | BL115: 628735 | BM115: 659513
A116: 2021F | B116: US | C116: ESACB | D116: 10460 | E116: 10315 | F116: 10166 | G116: 9955 | H116: 10011 | I116: 9974 | J116: 9642 | K116: 10010 | L116: 10215 | M116: 10420 | N116: 10627 | O116: 10463 | P116: 10372 | Q116: 10533 | R116: 9721 | S116: 10150 | T116: 10060 | U116: 10429 | V116: 10027 | W116: 10117 | X116: 11069 | Y116: 10871 | Z116: 11002 | AA116: 12675 | AB116: 14293 | AC116: 14148 | AD116: 15058 | AE116: 15565 | AF116: 15930 | AG116: 16275 | AH116: 16212 | AI116: 16234 | AJ116: 16055 | AK116: 16278 | AL116: 17039 | AM116: 16971 | AN116: 16797 | AO116: 16745 | AP116: 16929 | AQ116: 17489 | AR116: 18362 | AS116: 18714 | AT116: 18866 | AU116: 23482 | AV116: 24647 | AW116: 25612 | AX116: 25104 | AY116: 27885 | AZ116: 26113 | BA116: 26504 | BB116: 26315 | BC116: 26177 | BD116: 24976 | BE116: 26017 | BF116: 26469 | BG116: 26056 | BH116: 25579 | BI116: 25667 | BJ116: 26152 | BK116: 26041 | BL116: 22341 | BM116: 21613
A117: 2021F | B117: US | C117: ESACP | D117: 3066 | E117: 3023 | F117: 2980 | G117: 2918 | H117: 2934 | I117: 2923 | J117: 2826 | K117: 2934 | L117: 2994 | M117: 3054 | N117: 3114 | O117: 3066 | P117: 3040 | Q117: 3087 | R117: 2849 | S117: 2975 | T117: 2948 | U117: 3056 | V117: 2939 | W117: 2965 | X117: 3244 | Y117: 3186 | Z117: 3225 | AA117: 3715 | AB117: 4189 | AC117: 4147 | AD117: 4413 | AE117: 4562 | AF117: 4669 | AG117: 4770 | AH117: 4751 | AI117: 4758 | AJ117: 4705 | AK117: 4771 | AL117: 4994 | AM117: 4974 | AN117: 4923 | AO117: 4908 | AP117: 4962 | AQ117: 5126 | AR117: 5382 | AS117: 5485 | AT117: 5529 | AU117: 6882 | AV117: 7224 | AW117: 7506 | AX117: 7358 | AY117: 8173 | AZ117: 7653 | BA117: 7768 | BB117: 7712 | BC117: 7672 | BD117: 7320 | BE117: 7625 | BF117: 7758 | BG117: 7637 | BH117: 7497 | BI117: 7523 | BJ117: 7665 | BK117: 7632 | BL117: 6548 | BM117: 6334
A118: 2021F | B118: US | C118: ESCCB | D118: 542999 | E118: 572043 | F118: 620863 | G118: 687563 | H118: 737790 | I118: 788603 | J118: 859233 | K118: 925179 | L118: 1013959 | M118: 1107733 | N118: 1201163 | O118: 1288009 | P118: 1407566 | Q118: 1516652 | R118: 1501335 | S118: 1597825 | T118: 1677942 | U118: 1753866 | V118: 1813271 | W118: 1854121 | X118: 1906093 | Y118: 2033237 | Z118: 2077046 | AA118: 2116437 | AB118: 2264475 | AC118: 2351282 | AD118: 2438628 | AE118: 2538757 | AF118: 2675108 | AG118: 2766641 | AH118: 2860153 | AI118: 2918093 | AJ118: 2900225 | AK118: 3018755 | AL118: 3115518 | AM118: 3252038 | AN118: 3343968 | AO118: 3502847 | AP118: 3677989 | AQ118: 3766240 | AR118: 3955691 | AS118: 4062865 | AT118: 4109820 | AU118: 4090059 | AV118: 4198209 | AW118: 4350570 | AX118: 4434725 | AY118: 4559507 | AZ118: 4558887 | BA118: 4458981 | BB118: 4538640 | BC118: 4531332 | BD118: 4528069 | BE118: 4562113 | BF118: 4613564 | BG118: 4642884 | BH118: 4664857 | BI118: 4616053 | BJ118: 4714548 | BK118: 4643311 | BL118: 4392744 | BM118: 4532636
A119: 2021F | B119: US | C119: ESCCP | D119: 159144 | E119: 167656 | F119: 181965 | G119: 201513 | H119: 216234 | I119: 231126 | J119: 251827 | K119: 271154 | L119: 297174 | M119: 324658 | N119: 352041 | O119: 377494 | P119: 412534 | Q119: 444505 | R119: 440016 | S119: 468296 | T119: 491777 | U119: 514029 | V119: 531439 | W119: 543412 | X119: 558644 | Y119: 595908 | Z119: 608747 | AA119: 620292 | AB119: 663680 | AC119: 689121 | AD119: 714721 | AE119: 744067 | AF119: 784029 | AG119: 810856 | AH119: 838263 | AI119: 855244 | AJ119: 850007 | AK119: 884746 | AL119: 913106 | AM119: 953118 | AN119: 980061 | AO119: 1026626 | AP119: 1077957 | AQ119: 1103822 | AR119: 1159347 | AS119: 1190758 | AT119: 1204519 | AU119: 1198728 | AV119: 1230425 | AW119: 1275079 | AX119: 1299744 | AY119: 1336315 | AZ119: 1336133 | BA119: 1306853 | BB119: 1330199 | BC119: 1328057 | BD119: 1327101 | BE119: 1337079 | BF119: 1352158 | BG119: 1360752 | BH119: 1367191 | BI119: 1352888 | BJ119: 1381755 | BK119: 1360877 | BL119: 1287440 | BM119: 1328439
A120: 2021F | B120: US | C120: ESICB | D120: 1106859 | E120: 1149250 | F120: 1227821 | G120: 1287790 | H120: 1382027 | I120: 1462817 | J120: 1581815 | K120: 1654872 | L120: 1778105 | M120: 1908623 | N120: 1947755 | O120: 2011197 | P120: 2187017 | Q120: 2340923 | R120: 2336794 | S120: 2346363 | T120: 2572883 | U120: 2681959 | V120: 2760575 | W120: 2872573 | X120: 2781005 | Y120: 2817436 | Z120: 2541765 | AA120: 2647710 | AB120: 2858697 | AC120: 2855066 | AD120: 2833770 | AE120: 2928291 | AF120: 3058852 | AG120: 3158347 | AH120: 3226120 | AI120: 3229743 | AJ120: 3318900 | AK120: 3334084 | AL120: 3439232 | AM120: 3455310 | AN120: 3526750 | AO120: 3542328 | AP120: 3586705 | AQ120: 3610635 | AR120: 3631185 | AS120: 3400431 | AT120: 3378691 | AU120: 3454218 | AV120: 3472903 | AW120: 3477360 | AX120: 3450547 | AY120: 3506963 | AZ120: 3444469 | BA120: 3130225 | BB120: 3313807 | BC120: 3382369 | BD120: 3363256 | BE120: 3362021 | BF120: 3403730 | BG120: 3365964 | BH120: 3332552 | BI120: 3358425 | BJ120: 3414295 | BK120: 3420028 | BL120: 3272388 | BM120: 3414093
A121: 2021F | B121: US | C121: ESICP | D121: 324402 | E121: 336826 | F121: 359854 | G121: 377430 | H121: 405049 | I121: 428727 | J121: 463603 | K121: 485015 | L121: 521133 | M121: 559385 | N121: 570854 | O121: 589448 | P121: 640978 | Q121: 686085 | R121: 684875 | S121: 687680 | T121: 754069 | U121: 786037 | V121: 809078 | W121: 841903 | X121: 815066 | Y121: 825743 | Z121: 744949 | AA121: 775999 | AB121: 837836 | AC121: 836772 | AD121: 830531 | AE121: 858233 | AF121: 896498 | AG121: 925659 | AH121: 945522 | AI121: 946583 | AJ121: 972714 | AK121: 977164 | AL121: 1007981 | AM121: 1012693 | AN121: 1033631 | AO121: 1038197 | AP121: 1051203 | AQ121: 1058217 | AR121: 1064239 | AS121: 996609 | AT121: 990238 | AU121: 1012373 | AV121: 1017850 | AW121: 1019156 | AX121: 1011298 | AY121: 1027832 | AZ121: 1009516 | BA121: 917416 | BB121: 971221 | BC121: 991316 | BD121: 985714 | BE121: 985352 | BF121: 997576 | BG121: 986508 | BH121: 976715 | BI121: 984298 | BJ121: 1000673 | BK121: 1002353 | BL121: 959082 | BM121: 1000613
A122: 2021F | B122: US | C122: ESRCB | D122: 687393 | E122: 731686 | F122: 794320 | G122: 855568 | H122: 927525 | I122: 992935 | J122: 1081223 | K122: 1160469 | L122: 1301916 | M122: 1456024 | N122: 1590983 | O122: 1704403 | P122: 1837735 | Q122: 1976337 | R122: 1972763 | S122: 2006735 | T122: 2069215 | U122: 2201555 | V122: 2301276 | W122: 2329778 | X122: 2448086 | Y122: 2464367 | Z122: 2489120 | AA122: 2562235 | AB122: 2661673 | AC122: 2708902 | AD122: 2794729 | AE122: 2901600 | AF122: 3046459 | AG122: 3089650 | AH122: 3152752 | AI122: 3259884 | AJ122: 3193423 | AK122: 3394192 | AL122: 3440939 | AM122: 3557015 | AN122: 3693530 | AO122: 3670903 | AP122: 3855932 | AQ122: 3906478 | AR122: 4068627 | AS122: 4099882 | AT122: 4316794 | AU122: 4353111 | AV122: 4408241 | AW122: 4637683 | AX122: 4611386 | AY122: 4750326 | AZ122: 4710818 | BA122: 4656555 | BB122: 4932757 | BC122: 4854597 | BD122: 4689844 | BE122: 4759099 | BF122: 4801395 | BG122: 4790777 | BH122: 4814530 | BI122: 4703946 | BJ122: 5012546 | BK122: 4914266 | BL122: 4997232 | BM122: 5017301
A123: 2021F | B123: US | C123: ESRCP | D123: 201463 | E123: 214445 | F123: 232802 | G123: 250753 | H123: 271842 | I123: 291013 | J123: 316888 | K123: 340114 | L123: 381570 | M123: 426736 | N123: 466291 | O123: 499532 | P123: 538609 | Q123: 579231 | R123: 578184 | S123: 588140 | T123: 606452 | U123: 645239 | V123: 674466 | W123: 682819 | X123: 717493 | Y123: 722265 | Z123: 729519 | AA123: 750948 | AB123: 780092 | AC123: 793934 | AD123: 819088 | AE123: 850410 | AF123: 892866 | AG123: 905525 | AH123: 924019 | AI123: 955417 | AJ123: 935939 | AK123: 994781 | AL123: 1008482 | AM123: 1042501 | AN123: 1082512 | AO123: 1075880 | AP123: 1130109 | AQ123: 1144923 | AR123: 1192446 | AS123: 1201607 | AT123: 1265180 | AU123: 1275824 | AV123: 1291982 | AW123: 1359227 | AX123: 1351520 | AY123: 1392241 | AZ123: 1380662 | BA123: 1364758 | BB123: 1445708 | BC123: 1422801 | BD123: 1374515 | BE123: 1394812 | BF123: 1407208 | BG123: 1404096 | BH123: 1411058 | BI123: 1378648 | BJ123: 1469093 | BK123: 1440289 | BL123: 1464605 | BM123: 1470487
A124: 2021F | B124: US | C124: ESRPP | D124: 1115 | E124: 1167 | F124: 1248 | G124: 1325 | H124: 1417 | I124: 1498 | J124: 1612 | K124: 1712 | L124: 1901 | M124: 2105 | N124: 2274 | O124: 2406 | P124: 2566 | Q124: 2733 | R124: 2704 | S124: 2723 | T124: 2781 | U124: 2930 | V124: 3030 | W124: 3034 | X124: 3158 | Y124: 3148 | Z124: 3149 | AA124: 3212 | AB124: 3308 | AC124: 3337 | AD124: 3411 | AE124: 3510 | AF124: 3652 | AG124: 3669 | AH124: 3702 | AI124: 3777 | AJ124: 3649 | AK124: 3827 | AL124: 3833 | AM124: 3915 | AN124: 4018 | AO124: 3946 | AP124: 4097 | AQ124: 4103 | AR124: 4226 | AS124: 4217 | AT124: 4399 | AU124: 4398 | AV124: 4412 | AW124: 4599 | AX124: 4530 | AY124: 4622 | AZ124: 4540 | BA124: 4449 | BB124: 4674 | BC124: 4566 | BD124: 4379 | BE124: 4413 | BF124: 4420 | BG124: 4378 | BH124: 4368 | BI124: 4240 | BJ124: 4495 | BK124: 4387 | BL124: 4418 | BM124: 4429
A125: 2021F | B125: US | C125: ESTCB | D125: 2347711 | E125: 2463294 | F125: 2653170 | G125: 2840876 | H125: 3057353 | I125: 3254329 | J125: 3531913 | K125: 3750529 | L125: 4104196 | M125: 4482799 | N125: 4750527 | O125: 5014071 | P125: 5442688 | Q125: 5844445 | R125: 5820612 | S125: 5961073 | T125: 6330100 | U125: 6647808 | V125: 6885149 | W125: 7066590 | X125: 7146253 | Y125: 7325911 | Z125: 7118934 | AA125: 7339057 | AB125: 7799137 | AC125: 7929399 | AD125: 8082185 | AE125: 8384213 | AF125: 8796349 | AG125: 9030913 | AH125: 9255237 | AI125: 9423954 | AJ125: 9428603 | AK125: 9763310 | AL125: 10012728 | AM125: 10281334 | AN125: 10581045 | AO125: 10732823 | AP125: 11137555 | AQ125: 11300841 | AR125: 11673865 | AS125: 11581891 | AT125: 11824170 | AU125: 11920869 | AV125: 12104000 | AW125: 12491225 | AX125: 12521763 | AY125: 12844681 | AZ125: 12740287 | BA125: 12272265 | BB125: 12811519 | BC125: 12794475 | BD125: 12606145 | BE125: 12709249 | BF125: 12845157 | BG125: 12825682 | BH125: 12837519 | BI125: 12704091 | BJ125: 13167540 | BK125: 13003645 | BL125: 12684705 | BM125: 12985643
A126: 2021F | B126: US | C126: ESTCP | D126: 688075 | E126: 721950 | F126: 777600 | G126: 832613 | H126: 896059 | I126: 953789 | J126: 1035145 | K126: 1099217 | L126: 1202871 | M126: 1313833 | N126: 1392300 | O126: 1469540 | P126: 1595161 | Q126: 1712909 | R126: 1705924 | S126: 1747091 | T126: 1855246 | U126: 1948361 | V126: 2017922 | W126: 2071099 | X126: 2094447 | Y126: 2147102 | Z126: 2086440 | AA126: 2150955 | AB126: 2285796 | AC126: 2323974 | AD126: 2368753 | AE126: 2457272 | AF126: 2578063 | AG126: 2646809 | AH126: 2712555 | AI126: 2762003 | AJ126: 2763365 | AK126: 2861462 | AL126: 2934563 | AM126: 3013287 | AN126: 3101127 | AO126: 3145610 | AP126: 3264231 | AQ126: 3312087 | AR126: 3421414 | AS126: 3394458 | AT126: 3465466 | AU126: 3493807 | AV126: 3547479 | AW126: 3660969 | AX126: 3669919 | AY126: 3764561 | AZ126: 3733965 | BA126: 3596795 | BB126: 3754841 | BC126: 3749846 | BD126: 3694650 | BE126: 3724868 | BF126: 3764700 | BG126: 3758992 | BH126: 3762462 | BI126: 3723356 | BJ126: 3859185 | BK126: 3811150 | BL126: 3717674 | BM126: 3805874
A127: 2021F | B127: US | C127: ESTPP | D127: 3808 | E127: 3930 | F127: 4169 | G127: 4400 | H127: 4670 | I127: 4909 | J127: 5266 | K127: 5532 | L127: 5993 | M127: 6482 | N127: 6790 | O127: 7077 | P127: 7600 | Q127: 8083 | R127: 7977 | S127: 8089 | T127: 8509 | U127: 8847 | V127: 9066 | W127: 9203 | X127: 9218 | Y127: 9357 | Z127: 9006 | AA127: 9200 | AB127: 9693 | AC127: 9768 | AD127: 9864 | AE127: 10142 | AF127: 10544 | AG127: 10724 | AH127: 10867 | AI127: 10918 | AJ127: 10773 | AK127: 11009 | AL127: 11153 | AM127: 11316 | AN127: 11511 | AO127: 11537 | AP127: 11833 | AQ127: 11870 | AR127: 12126 | AS127: 11912 | AT127: 12049 | AU127: 12043 | AV127: 12115 | AW127: 12388 | AX127: 12299 | AY127: 12497 | AZ127: 12279 | BA127: 11725 | BB127: 12139 | BC127: 12035 | BD127: 11771 | BE127: 11785 | BF127: 11824 | BG127: 11720 | BH127: 11646 | BI127: 11452 | BJ127: 11808 | BK127: 11608 | BL127: 11214 | BM127: 11462
... A129: 2021F | B129: US | C129: ESTXP | D129: 688075 | E129: 721950 | F129: 777600 | G129: 832613 | H129: 896059 | I129: 953789 | J129: 1035145 | K129: 1099217 | L129: 1202871 | M129: 1313833 | N129: 1392300 | O129: 1469540 | P129: 1595161 | Q129: 1712909 | R129: 1705924 | S129: 1747091 | T129: 1855246 | U129: 1948361 | V129: 2017922 | W129: 2071099 | X129: 2094447 | Y129: 2147102 | Z129: 2086440 | AA129: 2150955 | AB129: 2285796 | AC129: 2323974 | AD129: 2368753 | AE129: 2457272 | AF129: 2578063 | AG129: 2646809 | AH129: 2712555 | AI129: 2762003 | AJ129: 2763365 | AK129: 2861462 | AL129: 2934563 | AM129: 3013287 | AN129: 3101127 | AO129: 3145610 | AP129: 3264231 | AQ129: 3312087 | AR129: 3421414 | AS129: 3394458 | AT129: 3465466 | AU129: 3493807 | AV129: 3547479 | AW129: 3660969 | AX129: 3669919 | AY129: 3764561 | AZ129: 3733965 | BA129: 3596795 | BB129: 3754841 | BC129: 3749846 | BD129: 3694650 | BE129: 3724868 | BF129: 3764700 | BG129: 3758992 | BH129: 3762462 | BI129: 3723356 | BJ129: 3859185 | BK129: 3811150 | BL129: 3717674 | BM129: 3805874
A130: 2021F | B130: US | C130: EYICB | BB130: 5269 | BC130: 5267 | BD130: 4572 | BE130: 755 | BF130: 950 | BG130: 816 | BH130: 646 | BI130: 658 | BJ130: 219 | BK130: 309 | BL130: 551 | BM130: 675
A131: 2021F | B131: US | C131: EYICP | BB131: 2163 | BC131: 2162 | BD131: 1877 | BE131: 310 | BF131: 390 | BG131: 335 | BH131: 265 | BI131: 270 | BJ131: 90 | BK131: 127 | BL131: 226 | BM131: 277
A132: 2021F | B132: US | C132: EYTCB | BB132: 5269 | BC132: 5267 | BD132: 4572 | BE132: 755 | BF132: 950 | BG132: 816 | BH132: 646 | BI132: 658 | BJ132: 219 | BK132: 309 | BL132: 551 | BM132: 675
A133: 2021F | B133: US | C133: EYTCP | BB133: 2163 | BC133: 2162 | BD133: 1877 | BE133: 310 | BF133: 390 | BG133: 335 | BH133: 265 | BI133: 270 | BJ133: 90 | BK133: 127 | BL133: 226 | BM133: 277
A134: 2021F | B134: US | C134: FFETK | D134: 10.76 | E134: 10.65 | F134: 10.558 | G134: 10.482 | H134: 10.462 | I134: 10.453 | J134: 10.415 | K134: 10.432 | L134: 10.398 | M134: 10.447 | N134: 10.494 | O134: 10.478 | P134: 10.379 | Q134: 10.389 | R134: 10.442 | S134: 10.406 | T134: 10.373 | U134: 10.435 | V134: 10.361 | W134: 10.353 | X134: 10.388 | Y134: 10.453 | Z134: 10.454 | AA134: 10.52 | AB134: 10.44 | AC134: 10.447 | AD134: 10.446 | AE134: 10.419 | AF134: 10.324 | AG134: 10.432 | AH134: 10.402 | AI134: 10.436 | AJ134: 10.342 | AK134: 10.309 | AL134: 10.316 | AM134: 10.312 | AN134: 10.34 | AO134: 10.213 | AP134: 10.197 | AQ134: 10.226 | AR134: 10.201 | AS134: 10.333 | AT134: 10.173 | AU134: 10.125 | AV134: 10.016 | AW134: 9.999 | AX134: 9.919 | AY134: 9.884 | AZ134: 9.854 | BA134: 9.76 | BB134: 9.756 | BC134: 9.716 | BD134: 9.516 | BE134: 9.541 | BF134: 9.509 | BG134: 9.314 | BH134: 9.228 | BI134: 9.208 | BJ134: 9.098 | BK134: 8.899 | BL134: 8.767 | BM134: 8.844
A135: 2021F | B135: US | C135: FFGBP | AZ135: 769945 | BA135: 773937 | BB135: 780260 | BC135: 786247 | BD135: 781158 | BE135: 774327 | BF135: 774294 | BG135: 758476 | BH135: 750282 | BI135: 748241 | BJ135: 747785 | BK135: 739125 | BL135: 731207 | BM135: 731789
A136: 2021F | B136: US | C136: FFTCB | D136: 42083902 | E136: 42704559 | F136: 44627400 | G136: 46470718 | H136: 48494993 | I136: 50527367 | J136: 53460558 | K136: 55139222 | L136: 58489657 | M136: 61326650 | N136: 63404057 | O136: 64476796 | P136: 67685221 | Q136: 70354027 | R136: 67857280 | S136: 65345011 | T136: 69099003 | U136: 70976813 | V136: 71881184 | W136: 72867854 | X136: 69812418 | Y136: 67555477 | Z136: 63793964 | AA136: 63060674 | AB136: 66384740 | AC136: 66107397 | AD136: 65978279 | AE136: 68423683 | AF136: 71559100 | AG136: 72857627 | AH136: 72301158 | AI136: 71822126 | AJ136: 73345161 | AK136: 74710100 | AL136: 76176875 | AM136: 77226112 | AN136: 79768878 | AO136: 80931627 | AP136: 81286078 | AQ136: 82301903 | AR136: 84612876 | AS136: 82770890 | AT136: 83599295 | AU136: 83909170 | AV136: 85677710 | AW136: 85632050 | AX136: 84473648 | AY136: 85827701 | AZ136: 83051474 | BA136: 77868164 | BB136: 80711267 | BC136: 79268449 | BD136: 77293973 | BE136: 79208532 | BF136: 80010104 | BG136: 79079337 | BH136: 78313136 | BI136: 77911754 | BJ136: 81279836 | BK136: 80397213 | BL136: 73065281 | BM136: 77406947
A137: 2021F | B137: US | C137: FNICB | D137: 0 | E137: 0 | F137: 0 | G137: 115571 | H137: 129012 | I137: 123438 | J137: 209154 | K137: 264232 | L137: 291883 | M137: 302122 | N137: 300600 | O137: 298197 | P137: 304778 | Q137: 298202 | R137: 324741 | S137: 280831 | T137: 384663 | U137: 389806 | V137: 393038 | W137: 455070 | X137: 474797 | Y137: 440517 | Z137: 316129 | AA137: 283744 | AB137: 276108 | AC137: 235798 | AD137: 341382 | AE137: 347900 | AF137: 355583 | AG137: 388583 | AH137: 347801 | AI137: 298947 | AJ137: 377127 | AK137: 350593 | AL137: 398339 | AM137: 372965 | AN137: 479310 | AO137: 536377 | AP137: 583992 | AQ137: 502076 | AR137: 613533 | AS137: 493716 | AT137: 582554 | AU137: 612956 | AV137: 749430 | AW137: 698666 | AX137: 628852 | AY137: 562454 | AZ137: 477174 | BA137: 471869 | BB137: 490573 | BC137: 487319 | BD137: 453921 | BE137: 517836 | BF137: 442606 | BG137: 428058 | BH137: 420024 | BI137: 436177 | BJ137: 447088 | BK137: 396691 | BL137: 354607 | BM137: 354817
A138: 2021F | B138: US | C138: FNICP | D138: 0 | E138: 0 | F138: 0 | G138: 22022 | H138: 24583 | I138: 23521 | J138: 39854 | K138: 50349 | L138: 55618 | M138: 57569 | N138: 57279 | O138: 56821 | P138: 58075 | Q138: 56822 | R138: 61879 | S138: 53512 | T138: 73297 | U138: 74277 | V138: 74893 | W138: 86713 | X138: 90472 | Y138: 83940 | Z138: 60238 | AA138: 54067 | AB138: 52612 | AC138: 44931 | AD138: 65050 | AE138: 66292 | AF138: 67756 | AG138: 74044 | AH138: 66273 | AI138: 56964 | AJ138: 71861 | AK138: 66805 | AL138: 75903 | AM138: 71068 | AN138: 91332 | AO138: 102206 | AP138: 111279 | AQ138: 95670 | AR138: 116908 | AS138: 94077 | AT138: 111005 | AU138: 116798 | AV138: 142803 | AW138: 133130 | AX138: 119827 | AY138: 107175 | AZ138: 90925 | BA138: 89914 | BB138: 93478 | BC138: 92858 | BD138: 86494 | BE138: 98673 | BF138: 84338 | BG138: 81566 | BH138: 80035 | BI138: 83113 | BJ138: 85192 | BK138: 75589 | BL138: 67570 | BM138: 67610
A139: 2021F | B139: US | C139: FOICB | D139: 0 | E139: 0 | F139: 0 | G139: 131785 | H139: 147477 | I139: 130643 | J139: 139066 | K139: 140115 | L139: 160036 | M139: 157823 | N139: 182556 | O139: 218705 | P139: 296749 | Q139: 353455 | R139: 327447 | S139: 276909 | T139: 361797 | U139: 571858 | V139: 711582 | W139: 846361 | X139: 858821 | Y139: 727665 | Z139: 521833 | AA139: 511720 | AB139: 470013 | AC139: 505261 | AD139: 610186 | AE139: 555297 | AF139: 583117 | AG139: 545453 | AH139: 753924 | AI139: 827296 | AJ139: 814516 | AK139: 844077 | AL139: 838643 | AM139: 801013 | AN139: 729645 | AO139: 861244 | AP139: 818669 | AQ139: 811143 | AR139: 722154 | AS139: 662454 | AT139: 632065 | AU139: 699379 | AV139: 779490 | AW139: 707982 | AX139: 790639 | AY139: 744091 | AZ139: 647763 | BA139: 424776 | BB139: 452521 | BC139: 388528 | BD139: 287242 | BE139: 223919 | BF139: 247225 | BG139: 229039 | BH139: 222457 | BI139: 262929 | BJ139: 239081 | BK139: 234089 | BL139: 217010 | BM139: 216894
A140: 2021F | B140: US | C140: FOICP | D140: 0 | E140: 0 | F140: 0 | G140: 22624 | H140: 25318 | I140: 22428 | J140: 23874 | K140: 24054 | L140: 27474 | M140: 27094 | N140: 31340 | O140: 37546 | P140: 50944 | Q140: 60679 | R140: 56214 | S140: 47538 | T140: 62111 | U140: 98173 | V140: 122160 | W140: 145298 | X140: 147437 | Y140: 124921 | Z140: 89585 | AA140: 87849 | AB140: 80689 | AC140: 86740 | AD140: 104753 | AE140: 95330 | AF140: 100106 | AG140: 93640 | AH140: 129429 | AI140: 142025 | AJ140: 139831 | AK140: 144906 | AL140: 143973 | AM140: 137513 | AN140: 125261 | AO140: 147853 | AP140: 140544 | AQ140: 139252 | AR140: 123975 | AS140: 113726 | AT140: 108509 | AU140: 120065 | AV140: 133818 | AW140: 121542 | AX140: 135732 | AY140: 127741 | AZ140: 111204 | BA140: 72923 | BB140: 77686 | BC140: 66700 | BD140: 49312 | BE140: 38441 | BF140: 42442 | BG140: 39320 | BH140: 38190 | BI140: 45138 | BJ140: 41044 | BK140: 40187 | BL140: 37255 | BM140: 37235
A141: 2021F | B141: US | C141: FSICB | D141: 0 | E141: 0 | F141: 0 | G141: 47004 | H141: 46188 | I141: 53556 | J141: 60408 | K141: 57192 | L141: 59064 | M141: 59910 | N141: 75384 | O141: 96948 | P141: 88068 | Q141: 74568 | R141: 86250 | S141: 94338 | T141: 104688 | U141: 105624 | V141: 119868 | W141: 78852 | X141: 91920 | Y141: 42756 | Z141: 44604 | AA141: 54930 | AB141: 69396 | AC141: 75690 | AD141: 0 | AE141: 0 | AF141: 0 | AG141: 0 | AH141: 0 | AI141: 0 | AJ141: 0 | AK141: 0 | AL141: 0 | AM141: 0 | AN141: 0 | AO141: 0 | AP141: 0 | AQ141: 0 | AR141: 0 | AS141: 0 | AT141: 0 | AU141: 0 | AV141: 0 | AW141: 0 | AX141: 0 | AY141: 0 | AZ141: 0 | BA141: 0 | BB141: 0 | BC141: 0 | BD141: 0 | BE141: 0 | BF141: 0 | BG141: 0 | BH141: 0 | BI141: 0 | BJ141: 0 | BK141: 0 | BL141: 0 | BM141: 0
A142: 2021F | B142: US | C142: FSICP | D142: 0 | E142: 0 | F142: 0 | G142: 7834 | H142: 7698 | I142: 8926 | J142: 10068 | K142: 9532 | L142: 9844 | M142: 9985 | N142: 12564 | O142: 16158 | P142: 14678 | Q142: 12428 | R142: 14375 | S142: 15723 | T142: 17448 | U142: 17604 | V142: 19978 | W142: 13142 | X142: 15320 | Y142: 7126 | Z142: 7434 | AA142: 9155 | AB142: 11566 | AC142: 12615 | AD142: 0 | AE142: 0 | AF142: 0 | AG142: 0 | AH142: 0 | AI142: 0 | AJ142: 0 | AK142: 0 | AL142: 0 | AM142: 0 | AN142: 0 | AO142: 0 | AP142: 0 | AQ142: 0 | AR142: 0 | AS142: 0 | AT142: 0 | AU142: 0 | AV142: 0 | AW142: 0 | AX142: 0 | AY142: 0 | AZ142: 0 | BA142: 0 | BB142: 0 | BC142: 0 | BD142: 0 | BE142: 0 | BF142: 0 | BG142: 0 | BH142: 0 | BI142: 0 | BJ142: 0 | BK142: 0 | BL142: 0 | BM142: 0
A143: 2021F | B143: US | C143: GDPRV | AO143: 8577552 | AP143: 9062817 | AQ143: 9631172 | AR143: 10250952 | AS143: 10581929 | AT143: 10929108 | AU143: 11456450 | AV143: 12217196 | AW143: 13039197 | AX143: 13815583 | AY143: 14474228 | AZ143: 14769862 | BA143: 14478067 | BB143: 15048970 | BC143: 15599731 | BD143: 16253970 | BE143: 16843196 | BF143: 17550687 | BG143: 18206023 | BH143: 18695106 | BI143: 19477337 | BJ143: 20533058 | BK143: 21380976 | BL143: 21060474 | BM143: 23315081
A144: 2021F | B144: US | C144: GDPRX | AO144: 11529157 | AP144: 12045824 | AQ144: 12623361 | AR144: 13138035 | AS144: 13263417 | AT144: 13488357 | AU144: 13865519 | AV144: 14399696 | AW144: 14901269 | AX144: 15315943 | AY144: 15623871 | AZ144: 15642962 | BA144: 15236262 | BB144: 15648991 | BC144: 15891534 | BD144: 16253970 | BE144: 16553348 | BF144: 16932051 | BG144: 17390295 | BH144: 17680274 | BI144: 18076651 | BJ144: 18609078 | BK144: 19036052 | BL144: 18509143 | BM144: 19609812
A145: 2021F | B145: US | C145: GECCB | D145: 0 | E145: 0 | F145: 0 | G145: 0 | H145: 0 | I145: 0 | J145: 0 | K145: 0 | L145: 0 | M145: 0 | N145: 0 | O145: 0 | P145: 0 | Q145: 0 | R145: 0 | S145: 0 | T145: 0 | U145: 0 | V145: 0 | W145: 0 | X145: 0 | Y145: 0 | Z145: 0 | AA145: 0 | AB145: 0 | AC145: 0 | AD145: 0 | AE145: 0 | AF145: 0 | AG145: 2500 | AH145: 2754 | AI145: 2970 | AJ145: 3186 | AK145: 3375 | AL145: 4234 | AM145: 4512 | AN145: 5320 | AO145: 5670 | AP145: 7116 | AQ145: 7472 | AR145: 7572 | AS145: 8270 | AT145: 8753 | AU145: 11000 | AV145: 12000 | AW145: 13600 | AX145: 14000 | AY145: 14400 | AZ145: 14800 | BA145: 16700 | BB145: 18500 | BC145: 19700 | BD145: 19700 | BE145: 19700 | BF145: 19700 | BG145: 19700 | BH145: 19700 | BI145: 19700 | BJ145: 19700 | BK145: 19700 | BL145: 19700 | BM145: 19700
A146: 2021F | B146: US | C146: GEEGB | D146: 359 | E146: 1001 | F146: 1061 | G146: 1760 | H146: 2132 | I146: 1978 | J146: 1958 | K146: 3300 | L146: 4532 | M146: 6422 | N146: 5511 | O146: 5739 | P146: 15079 | Q146: 20422 | R146: 25610 | S146: 33780 | T146: 37513 | U146: 37382 | V146: 30851 | W146: 40262 | X146: 52699 | Y146: 59437 | Z146: 50627 | AA146: 63910 | AB146: 80811 | AC146: 97421 | AD146: 107677 | AE146: 112270 | AF146: 106338 | AG146: 152239 | AH146: 160547 | AI146: 166626 | AJ146: 166899 | AK146: 173073 | AL146: 160264 | AM146: 137957 | AN146: 148159 | AO146: 150398 | AP146: 150650 | AQ146: 151621 | AR146: 143764 | AS146: 141981 | AT146: 147420 | AU146: 146045 | AV146: 148347 | AW146: 146903 | AX146: 144500 | AY146: 144674 | AZ146: 146233 | BA146: 146485 | BB146: 148479 | BC146: 148811 | BD146: 148092 | BE146: 150506 | BF146: 150974 | BG146: 148256 | BH146: 146041 | BI146: 146654 | BJ146: 145269 | BK146: 137692 | BL146: 139305 | BM146: 141284
...

Sheet Intermediate (old)
A1: dataset: | B1: sedsQ | C1: sedsQ | D1: sedsQ | E1: sedsQ | H1: emissions
B2: CLTCB | C2: PATCB | D2: NGTCB | E2: RETCB | H2: CO2 Emissions
A3: Original Description | B3: =IF(ISERROR(VLOOKUP(B$2,code,2,)),"",VLOOKUP(B$2,code,2,)) -> Coal total consumption | C3: =IF(ISERROR(VLOOKUP(C$2,code,2,)),"",VLOOKUP(C$2,code,2,)) -> All petroleum products total consumption | D3: =IF(ISERROR(VLOOKUP(D$2,code,2,)),"",VLOOKUP(D$2,code,2,)) -> Natural gas total consumption (including supplemental gaseous fuels) | E3: =IF(ISERROR(VLOOKUP(E$2,code,2,)),"",VLOOKUP(E$2,code,2,)) -> Renewable energy total consumption | G3: =IF(ISERROR(VLOOKUP(G$2,code,2,)),"",VLOOKUP(G$2,code,2,)) | I3: =IF(ISERROR(VLOOKUP(I$2,code,2,)),"",VLOOKUP(I$2,code,2,)) | J3: =IF(ISERROR(VLOOKUP(J$2,code,2,)),"",VLOOKUP(J$2,code,2,)) | K3: =IF(ISERROR(VLOOKUP(K$2,code,2,)),"",VLOOKUP(K$2,code,2,)) | L3: =IF(ISERROR(VLOOKUP(L$2,code,2,)),"",VLOOKUP(L$2,code,2,)) | M3: =IF(ISERROR(VLOOKUP(M$2,code,2,)),"",VLOOKUP(M$2,code,2,)) | N3: =IF(ISERROR(VLOOKUP(N$2,code,2,)),"",VLOOKUP(N$2,code,2,)) | O3: =IF(ISERROR(VLOOKUP(O$2,code,2,)),"",VLOOKUP(O$2,code,2,)) | P3: =IF(ISERROR(VLOOKUP(P$2,code,2,)),"",VLOOKUP(P$2,code,2,)) | ... AR3: =IF(ISERROR(VLOOKUP(AR$2,code,2,)),"",VLOOKUP(AR$2,code,2,))
A5: outgoing ID:
B9: Primary Energy Quantities
B10: Coal | C10: Oil | D10: Natural Gas | E10: Renewables | G10: Total Fossil | H10: Total emssions | I10: Carbon intensity of fossil energy
A11: Units | B11: =VLOOKUP(B$2,code,3,) -> Billion Btu | C11: =VLOOKUP(C$2,code,3,) -> Billion Btu | D11: =VLOOKUP(D$2,code,3,) -> Billion Btu
A12: Year/Average | B12: =AVERAGE(B13:B64) -> 17433425 | C12: =AVERAGE(C13:C64) -> 35332071 | D12: =AVERAGE(D13:D64) -> 22904890 | E12: =AVERAGE(E13:E64) -> 6827001 | G12: =AVERAGE(G13:G64) -> 75670386 | H12: =AVERAGE(H13:H64) -> #DIV/0! | I12: =AVERAGE(I13:I64) -> #DIV/0!
A13: 1970 | B13: =IF(ISERROR(VLOOKUP(B$2,INDIRECT(B$1),MATCH($A13,INDIRECT(B$1&"_col"),),)),"",VLOOKUP(B$2,INDIRECT(B$1),MATCH($A13,INDIRECT(B$1&"_col"),),)) -> 12268895 | C13: =IF(ISERROR(VLOOKUP(C$2,INDIRECT(C$1),MATCH($A13,INDIRECT(C$1&"_col"),),)),"",VLOOKUP(C$2,INDIRECT(C$1),MATCH($A13,INDIRECT(C$1&"_col"),),)) -> 29500112 | D13: =IF(ISERROR(VLOOKUP(D$2,INDIRECT(D$1),MATCH($A13,INDIRECT(D$1&"_col"),),)),"",VLOOKUP(D$2,INDIRECT(D$1),MATCH($A13,INDIRECT(D$1&"_col"),),)) -> 21692710 | E13: =IF(ISERROR(VLOOKUP(E$2,INDIRECT(E$1),MATCH($A13,INDIRECT(E$1&"_col"),),)),"",VLOOKUP(E$2,INDIRECT(E$1),MATCH($A13,INDIRECT(E$1&"_col"),),)) -> 4070021 | G13: =SUM(B13:D13) -> 63461717 | H13: =IF(ISERROR(VLOOKUP(A13,INDIRECT($H$1),MATCH($H$2,INDIRECT($H$1&"_col"),),)),"",VLOOKUP(A13,INDIRECT($H$1),MATCH($H$2,INDIRECT($H$1&"_col"),),)) | I13: =IF(ISERROR(H13/G13),"",H13/G13)
A14: =A13+1 -> 1971 | B14: =IF(ISERROR(VLOOKUP(B$2,INDIRECT(B$1),MATCH($A14,INDIRECT(B$1&"_col"),),)),"",VLOOKUP(B$2,INDIRECT(B$1),MATCH($A14,INDIRECT(B$1&"_col"),),)) -> 11603202 | C14: =IF(ISERROR(VLOOKUP(C$2,INDIRECT(C$1),MATCH($A14,INDIRECT(C$1&"_col"),),)),"",VLOOKUP(C$2,INDIRECT(C$1),MATCH($A14,INDIRECT(C$1&"_col"),),)) -> 30541454 | D14: =IF(ISERROR(VLOOKUP(D$2,INDIRECT(D$1),MATCH($A14,INDIRECT(D$1&"_col"),),)),"",VLOOKUP(D$2,INDIRECT(D$1),MATCH($A14,INDIRECT(D$1&"_col"),),)) -> 22365248 | E14: =IF(ISERROR(VLOOKUP(E$2,INDIRECT(E$1),MATCH($A14,INDIRECT(E$1&"_col"),),)),"",VLOOKUP(E$2,INDIRECT(E$1),MATCH($A14,INDIRECT(E$1&"_col"),),)) -> 4262212 | G14: =SUM(B14:D14) -> 64509904 | H14: =IF(ISERROR(VLOOKUP(A14,INDIRECT($H$1),MATCH($H$2,INDIRECT($H$1&"_col"),),)),"",VLOOKUP(A14,INDIRECT($H$1),MATCH($H$2,INDIRECT($H$1&"_col"),),)) | I14: =IF(ISERROR(H14/G14),"",H14/G14) | K14: Growth Rate Calculation
A15: =A14+1 -> 1972 | B15: =IF(ISERROR(VLOOKUP(B$2,INDIRECT(B$1),MATCH($A15,INDIRECT(B$1&"_col"),),)),"",VLOOKUP(B$2,INDIRECT(B$1),MATCH($A15,INDIRECT(B$1&"_col"),),)) -> 12109530 | C15: =IF(ISERROR(VLOOKUP(C$2,INDIRECT(C$1),MATCH($A15,INDIRECT(C$1&"_col"),),)),"",VLOOKUP(C$2,INDIRECT(C$1),MATCH($A15,INDIRECT(C$1&"_col"),),)) -> 32919160 | D15: =IF(ISERROR(VLOOKUP(D$2,INDIRECT(D$1),MATCH($A15,INDIRECT(D$1&"_col"),),)),"",VLOOKUP(D$2,INDIRECT(D$1),MATCH($A15,INDIRECT(D$1&"_col"),),)) -> 22682497 | E15: =IF(ISERROR(VLOOKUP(E$2,INDIRECT(E$1),MATCH($A15,INDIRECT(E$1&"_col"),),)),"",VLOOKUP(E$2,INDIRECT(E$1),MATCH($A15,INDIRECT(E$1&"_col"),),)) -> 4382009 | G15: =SUM(B15:D15) -> 67711187 | H15: =IF(ISERROR(VLOOKUP(A15,INDIRECT($H$1),MATCH($H$2,INDIRECT($H$1&"_col"),),)),"",VLOOKUP(A15,INDIRECT($H$1),MATCH($H$2,INDIRECT($H$1&"_col"),),)) | I15: =IF(ISERROR(H15/G15),"",H15/G15) | K15: Annual: | L15: {=LOGEST(I16:I64)} -> #VALUE!
A16: =A15+1 -> 1973 | B16: =IF(ISERROR(VLOOKUP(B$2,INDIRECT(B$1),MATCH($A16,INDIRECT(B$1&"_col"),),)),"",VLOOKUP(B$2,INDIRECT(B$1),MATCH($A16,INDIRECT(B$1&"_col"),),)) -> 12960121 | C16: =IF(ISERROR(VLOOKUP(C$2,INDIRECT(C$1),MATCH($A16,INDIRECT(C$1&"_col"),),)),"",VLOOKUP(C$2,INDIRECT(C$1),MATCH($A16,INDIRECT(C$1&"_col"),),)) -> 34806025 | D16: =IF(ISERROR(VLOOKUP(D$2,INDIRECT(D$1),MATCH($A16,INDIRECT(D$1&"_col"),),)),"",VLOOKUP(D$2,INDIRECT(D$1),MATCH($A16,INDIRECT(D$1&"_col"),),)) -> 22595346 | E16: =IF(ISERROR(VLOOKUP(E$2,INDIRECT(E$1),MATCH($A16,INDIRECT(E$1&"_col"),),)),"",VLOOKUP(E$2,INDIRECT(E$1),MATCH($A16,INDIRECT(E$1&"_col"),),)) -> 4410938 | G16: =SUM(B16:D16) -> 70361492 | H16: =IF(ISERROR(VLOOKUP(A16,INDIRECT($H$1),MATCH($H$2,INDIRECT($H$1&"_col"),),)),"",VLOOKUP(A16,INDIRECT($H$1),MATCH($H$2,INDIRECT($H$1&"_col"),),)) | I16: =IF(ISERROR(H16/G16),"",H16/G16) | K16: 10 Year: | L16: =L15^10-1 -> #VALUE!
A17: =A16+1 -> 1974 | B17: =IF(ISERROR(VLOOKUP(B$2,INDIRECT(B$1),MATCH($A17,INDIRECT(B$1&"_col"),),)),"",VLOOKUP(B$2,INDIRECT(B$1),MATCH($A17,INDIRECT(B$1&"_col"),),)) -> 12651009 | C17: =IF(ISERROR(VLOOKUP(C$2,INDIRECT(C$1),MATCH($A17,INDIRECT(C$1&"_col"),),)),"",VLOOKUP(C$2,INDIRECT(C$1),MATCH($A17,INDIRECT(C$1&"_col"),),)) -> 33420613 | D17: =IF(ISERROR(VLOOKUP(D$2,INDIRECT(D$1),MATCH($A17,INDIRECT(D$1&"_col"),),)),"",VLOOKUP(D$2,INDIRECT(D$1),MATCH($A17,INDIRECT(D$1&"_col"),),)) -> 21729561 | E17: =IF(ISERROR(VLOOKUP(E$2,INDIRECT(E$1),MATCH($A17,INDIRECT(E$1&"_col"),),)),"",VLOOKUP(E$2,INDIRECT(E$1),MATCH($A17,INDIRECT(E$1&"_col"),),)) -> 4741851 | G17: =SUM(B17:D17) -> 67801183 | H17: =IF(ISERROR(VLOOKUP(A17,INDIRECT($H$1),MATCH($H$2,INDIRECT($H$1&"_col"),),)),"",VLOOKUP(A17,INDIRECT($H$1),MATCH($H$2,INDIRECT($H$1&"_col"),),)) | I17: =IF(ISERROR(H17/G17),"",H17/G17)
A18: =A17+1 -> 1975 | B18: =IF(ISERROR(VLOOKUP(B$2,INDIRECT(B$1),MATCH($A18,INDIRECT(B$1&"_col"),),)),"",VLOOKUP(B$2,INDIRECT(B$1),MATCH($A18,INDIRECT(B$1&"_col"),),)) -> 12655613 | C18: =IF(ISERROR(VLOOKUP(C$2,INDIRECT(C$1),MATCH($A18,INDIRECT(C$1&"_col"),),)),"",VLOOKUP(C$2,INDIRECT(C$1),MATCH($A18,INDIRECT(C$1&"_col"),),)) -> 32698781 | D18: =IF(ISERROR(VLOOKUP(D$2,INDIRECT(D$1),MATCH($A18,INDIRECT(D$1&"_col"),),)),"",VLOOKUP(D$2,INDIRECT(D$1),MATCH($A18,INDIRECT(D$1&"_col"),),)) -> 19977076 | E18: =IF(ISERROR(VLOOKUP(E$2,INDIRECT(E$1),MATCH($A18,INDIRECT(E$1&"_col"),),)),"",VLOOKUP(E$2,INDIRECT(E$1),MATCH($A18,INDIRECT(E$1&"_col"),),)) -> 4687119 | G18: =SUM(B18:D18) -> 65331470 | H18: =IF(ISERROR(VLOOKUP(A18,INDIRECT($H$1),MATCH($H$2,INDIRECT($H$1&"_col"),),)),"",VLOOKUP(A18,INDIRECT($H$1),MATCH($H$2,INDIRECT($H$1&"_col"),),)) | I18: =IF(ISERROR(H18/G18),"",H18/G18)
A19: =A18+1 -> 1976 | B19: =IF(ISERROR(VLOOKUP(B$2,INDIRECT(B$1),MATCH($A19,INDIRECT(B$1&"_col"),),)),"",VLOOKUP(B$2,INDIRECT(B$1),MATCH($A19,INDIRECT(B$1&"_col"),),)) -> 13575890 | C19: =IF(ISERROR(VLOOKUP(C$2,INDIRECT(C$1),MATCH($A19,INDIRECT(C$1&"_col"),),)),"",VLOOKUP(C$2,INDIRECT(C$1),MATCH($A19,INDIRECT(C$1&"_col"),),)) -> 35141985 | D19: =IF(ISERROR(VLOOKUP(D$2,INDIRECT(D$1),MATCH($A19,INDIRECT(D$1&"_col"),),)),"",VLOOKUP(D$2,INDIRECT(D$1),MATCH($A19,INDIRECT(D$1&"_col"),),)) -> 20381227 | E19: =IF(ISERROR(VLOOKUP(E$2,INDIRECT(E$1),MATCH($A19,INDIRECT(E$1&"_col"),),)),"",VLOOKUP(E$2,INDIRECT(E$1),MATCH($A19,INDIRECT(E$1&"_col"),),)) -> 4727151 | G19: =SUM(B19:D19) -> 69099102 | H19: =IF(ISERROR(VLOOKUP(A19,INDIRECT($H$1),MATCH($H$2,INDIRECT($H$1&"_col"),),)),"",VLOOKUP(A19,INDIRECT($H$1),MATCH($H$2,INDIRECT($H$1&"_col"),),)) | I19: =IF(ISERROR(H19/G19),"",H19/G19)
A20: =A19+1 -> 1977 | B20: =IF(ISERROR(VLOOKUP(B$2,INDIRECT(B$1),MATCH($A20,INDIRECT(B$1&"_col"),),)),"",VLOOKUP(B$2,INDIRECT(B$1),MATCH($A20,INDIRECT(B$1&"_col"),),)) -> 13907111 | C20: =IF(ISERROR(VLOOKUP(C$2,INDIRECT(C$1),MATCH($A20,INDIRECT(C$1&"_col"),),)),"",VLOOKUP(C$2,INDIRECT(C$1),MATCH($A20,INDIRECT(C$1&"_col"),),)) -> 37082642 | D20: =IF(ISERROR(VLOOKUP(D$2,INDIRECT(D$1),MATCH($A20,INDIRECT(D$1&"_col"),),)),"",VLOOKUP(D$2,INDIRECT(D$1),MATCH($A20,INDIRECT(D$1&"_col"),),)) -> 19972477 | E20: =IF(ISERROR(VLOOKUP(E$2,INDIRECT(E$1),MATCH($A20,INDIRECT(E$1&"_col"),),)),"",VLOOKUP(E$2,INDIRECT(E$1),MATCH($A20,INDIRECT(E$1&"_col"),),)) -> 4208966 | G20: =SUM(B20:D20) -> 70962230 | H20: =IF(ISERROR(VLOOKUP(A20,INDIRECT($H$1),MATCH($H$2,INDIRECT($H$1&"_col"),),)),"",VLOOKUP(A20,INDIRECT($H$1),MATCH($H$2,INDIRECT($H$1&"_col"),),)) | I20: =IF(ISERROR(H20/G20),"",H20/G20)
A21: =A20+1 -> 1978 | B21: =IF(ISERROR(VLOOKUP(B$2,INDIRECT(B$1),MATCH($A21,INDIRECT(B$1&"_col"),),)),"",VLOOKUP(B$2,INDIRECT(B$1),MATCH($A21,INDIRECT(B$1&"_col"),),)) -> 13769684 | C21: =IF(ISERROR(VLOOKUP(C$2,INDIRECT(C$1),MATCH($A21,INDIRECT(C$1&"_col"),),)),"",VLOOKUP(C$2,INDIRECT(C$1),MATCH($A21,INDIRECT(C$1&"_col"),),)) -> 37919119 | D21: =IF(ISERROR(VLOOKUP(D$2,INDIRECT(D$1),MATCH($A21,INDIRECT(D$1&"_col"),),)),"",VLOOKUP(D$2,INDIRECT(D$1),MATCH($A21,INDIRECT(D$1&"_col"),),)) -> 20067662 | E21: =IF(ISERROR(VLOOKUP(E$2,INDIRECT(E$1),MATCH($A21,INDIRECT(E$1&"_col"),),)),"",VLOOKUP(E$2,INDIRECT(E$1),MATCH($A21,INDIRECT(E$1&"_col"),),)) -> 5005439 | G21: =SUM(B21:D21) -> 71756465 | H21: =IF(ISERROR(VLOOKUP(A21,INDIRECT($H$1),MATCH($H$2,INDIRECT($H$1&"_col"),),)),"",VLOOKUP(A21,INDIRECT($H$1),MATCH($H$2,INDIRECT($H$1&"_col"),),)) | I21: =IF(ISERROR(H21/G21),"",H21/G21)
A22: =A21+1 -> 1979 | B22: =IF(ISERROR(VLOOKUP(B$2,INDIRECT(B$1),MATCH($A22,INDIRECT(B$1&"_col"),),)),"",VLOOKUP(B$2,INDIRECT(B$1),MATCH($A22,INDIRECT(B$1&"_col"),),)) -> 15041652 | C22: =IF(ISERROR(VLOOKUP(C$2,INDIRECT(C$1),MATCH($A22,INDIRECT(C$1&"_col"),),)),"",VLOOKUP(C$2,INDIRECT(C$1),MATCH($A22,INDIRECT(C$1&"_col"),),)) -> 37075744 | D22: =IF(ISERROR(VLOOKUP(D$2,INDIRECT(D$1),MATCH($A22,INDIRECT(D$1&"_col"),),)),"",VLOOKUP(D$2,INDIRECT(D$1),MATCH($A22,INDIRECT(D$1&"_col"),),)) -> 20687615 | E22: =IF(ISERROR(VLOOKUP(E$2,INDIRECT(E$1),MATCH($A22,INDIRECT(E$1&"_col"),),)),"",VLOOKUP(E$2,INDIRECT(E$1),MATCH($A22,INDIRECT(E$1&"_col"),),)) -> 5122854 | G22: =SUM(B22:D22) -> 72805011 | H22: =IF(ISERROR(VLOOKUP(A22,INDIRECT($H$1),MATCH($H$2,INDIRECT($H$1&"_col"),),)),"",VLOOKUP(A22,INDIRECT($H$1),MATCH($H$2,INDIRECT($H$1&"_col"),),)) | I22: =IF(ISERROR(H22/G22),"",H22/G22)
A23: =A22+1 -> 1980 | B23: =IF(ISERROR(VLOOKUP(B$2,INDIRECT(B$1),MATCH($A23,INDIRECT(B$1&"_col"),),)),"",VLOOKUP(B$2,INDIRECT(B$1),MATCH($A23,INDIRECT(B$1&"_col"),),)) -> 15460982 | C23: =IF(ISERROR(VLOOKUP(C$2,INDIRECT(C$1),MATCH($A23,INDIRECT(C$1&"_col"),),)),"",VLOOKUP(C$2,INDIRECT(C$1),MATCH($A23,INDIRECT(C$1&"_col"),),)) -> 34159533 | D23: =IF(ISERROR(VLOOKUP(D$2,INDIRECT(D$1),MATCH($A23,INDIRECT(D$1&"_col"),),)),"",VLOOKUP(D$2,INDIRECT(D$1),MATCH($A23,INDIRECT(D$1&"_col"),),)) -> 20383954 | E23: =IF(ISERROR(VLOOKUP(E$2,INDIRECT(E$1),MATCH($A23,INDIRECT(E$1&"_col"),),)),"",VLOOKUP(E$2,INDIRECT(E$1),MATCH($A23,INDIRECT(E$1&"_col"),),)) -> 5424534 | G23: =SUM(B23:D23) -> 70004469 | H23: =IF(ISERROR(VLOOKUP(A23,INDIRECT($H$1),MATCH($H$2,INDIRECT($H$1&"_col"),),)),"",VLOOKUP(A23,INDIRECT($H$1),MATCH($H$2,INDIRECT($H$1&"_col"),),)) | I23: =IF(ISERROR(H23/G23),"",H23/G23)
A24: =A23+1 -> 1981 | B24: =IF(ISERROR(VLOOKUP(B$2,INDIRECT(B$1),MATCH($A24,INDIRECT(B$1&"_col"),),)),"",VLOOKUP(B$2,INDIRECT(B$1),MATCH($A24,INDIRECT(B$1&"_col"),),)) -> 15937724 | C24: =IF(ISERROR(VLOOKUP(C$2,INDIRECT(C$1),MATCH($A24,INDIRECT(C$1&"_col"),),)),"",VLOOKUP(C$2,INDIRECT(C$1),MATCH($A24,INDIRECT(C$1&"_col"),),)) -> 31884079 | D24: =IF(ISERROR(VLOOKUP(D$2,INDIRECT(D$1),MATCH($A24,INDIRECT(D$1&"_col"),),)),"",VLOOKUP(D$2,INDIRECT(D$1),MATCH($A24,INDIRECT(D$1&"_col"),),)) -> 19928435 | E24: =IF(ISERROR(VLOOKUP(E$2,INDIRECT(E$1),MATCH($A24,INDIRECT(E$1&"_col"),),)),"",VLOOKUP(E$2,INDIRECT(E$1),MATCH($A24,INDIRECT(E$1&"_col"),),)) -> 5417152 | G24: =SUM(B24:D24) -> 67750238 | H24: =IF(ISERROR(VLOOKUP(A24,INDIRECT($H$1),MATCH($H$2,INDIRECT($H$1&"_col"),),)),"",VLOOKUP(A24,INDIRECT($H$1),MATCH($H$2,INDIRECT($H$1&"_col"),),)) | I24: =IF(ISERROR(H24/G24),"",H24/G24)
A25: =A24+1 -> 1982 | B25: =IF(ISERROR(VLOOKUP(B$2,INDIRECT(B$1),MATCH($A25,INDIRECT(B$1&"_col"),),)),"",VLOOKUP(B$2,INDIRECT(B$1),MATCH($A25,INDIRECT(B$1&"_col"),),)) -> 15269049 | C25: =IF(ISERROR(VLOOKUP(C$2,INDIRECT(C$1),MATCH($A25,INDIRECT(C$1&"_col"),),)),"",VLOOKUP(C$2,INDIRECT(C$1),MATCH($A25,INDIRECT(C$1&"_col"),),)) -> 30179518 | D25: =IF(ISERROR(VLOOKUP(D$2,INDIRECT(D$1),MATCH($A25,INDIRECT(D$1&"_col"),),)),"",VLOOKUP(D$2,INDIRECT(D$1),MATCH($A25,INDIRECT(D$1&"_col"),),)) -> 18515242 | E25: =IF(ISERROR(VLOOKUP(E$2,INDIRECT(E$1),MATCH($A25,INDIRECT(E$1&"_col"),),)),"",VLOOKUP(E$2,INDIRECT(E$1),MATCH($A25,INDIRECT(E$1&"_col"),),)) -> 5980929 | G25: =SUM(B25:D25) -> 63963809 | H25: =IF(ISERROR(VLOOKUP(A25,INDIRECT($H$1),MATCH($H$2,INDIRECT($H$1&"_col"),),)),"",VLOOKUP(A25,INDIRECT($H$1),MATCH($H$2,INDIRECT($H$1&"_col"),),)) | I25: =IF(ISERROR(H25/G25),"",H25/G25)
A26: =A25+1 -> 1983 | B26: =IF(ISERROR(VLOOKUP(B$2,INDIRECT(B$1),MATCH($A26,INDIRECT(B$1&"_col"),),)),"",VLOOKUP(B$2,INDIRECT(B$1),MATCH($A26,INDIRECT(B$1&"_col"),),)) -> 15867060 | C26: =IF(ISERROR(VLOOKUP(C$2,INDIRECT(C$1),MATCH($A26,INDIRECT(C$1&"_col"),),)),"",VLOOKUP(C$2,INDIRECT(C$1),MATCH($A26,INDIRECT(C$1&"_col"),),)) -> 29997230 | D26: =IF(ISERROR(VLOOKUP(D$2,INDIRECT(D$1),MATCH($A26,INDIRECT(D$1&"_col"),),)),"",VLOOKUP(D$2,INDIRECT(D$1),MATCH($A26,INDIRECT(D$1&"_col"),),)) -> 17347750 | E26: =IF(ISERROR(VLOOKUP(E$2,INDIRECT(E$1),MATCH($A26,INDIRECT(E$1&"_col"),),)),"",VLOOKUP(E$2,INDIRECT(E$1),MATCH($A26,INDIRECT(E$1&"_col"),),)) -> 6495612 | G26: =SUM(B26:D26) -> 63212040 | H26: =IF(ISERROR(VLOOKUP(A26,INDIRECT($H$1),MATCH($H$2,INDIRECT($H$1&"_col"),),)),"",VLOOKUP(A26,INDIRECT($H$1),MATCH($H$2,INDIRECT($H$1&"_col"),),)) | I26: =IF(ISERROR(H26/G26),"",H26/G26)
A27: =A26+1 -> 1984 | B27: =IF(ISERROR(VLOOKUP(B$2,INDIRECT(B$1),MATCH($A27,INDIRECT(B$1&"_col"),),)),"",VLOOKUP(B$2,INDIRECT(B$1),MATCH($A27,INDIRECT(B$1&"_col"),),)) -> 17013578 | C27: =IF(ISERROR(VLOOKUP(C$2,INDIRECT(C$1),MATCH($A27,INDIRECT(C$1&"_col"),),)),"",VLOOKUP(C$2,INDIRECT(C$1),MATCH($A27,INDIRECT(C$1&"_col"),),)) -> 30993084 | D27: =IF(ISERROR(VLOOKUP(D$2,INDIRECT(D$1),MATCH($A27,INDIRECT(D$1&"_col"),),)),"",VLOOKUP(D$2,INDIRECT(D$1),MATCH($A27,INDIRECT(D$1&"_col"),),)) -> 18502834 | E27: =IF(ISERROR(VLOOKUP(E$2,INDIRECT(E$1),MATCH($A27,INDIRECT(E$1&"_col"),),)),"",VLOOKUP(E$2,INDIRECT(E$1),MATCH($A27,INDIRECT(E$1&"_col"),),)) -> 6438347 | G27: =SUM(B27:D27) -> 66509496 | H27: =IF(ISERROR(VLOOKUP(A27,INDIRECT($H$1),MATCH($H$2,INDIRECT($H$1&"_col"),),)),"",VLOOKUP(A27,INDIRECT($H$1),MATCH($H$2,INDIRECT($H$1&"_col"),),)) | I27: =IF(ISERROR(H27/G27),"",H27/G27)
A28: =A27+1 -> 1985 | B28: =IF(ISERROR(VLOOKUP(B$2,INDIRECT(B$1),MATCH($A28,INDIRECT(B$1&"_col"),),)),"",VLOOKUP(B$2,INDIRECT(B$1),MATCH($A28,INDIRECT(B$1&"_col"),),)) -> 17540071 | C28: =IF(ISERROR(VLOOKUP(C$2,INDIRECT(C$1),MATCH($A28,INDIRECT(C$1&"_col"),),)),"",VLOOKUP(C$2,INDIRECT(C$1),MATCH($A28,INDIRECT(C$1&"_col"),),)) -> 30867287 | D28: =IF(ISERROR(VLOOKUP(D$2,INDIRECT(D$1),MATCH($A28,INDIRECT(D$1&"_col"),),)),"",VLOOKUP(D$2,INDIRECT(D$1),MATCH($A28,INDIRECT(D$1&"_col"),),)) -> 17843043 | E28: =IF(ISERROR(VLOOKUP(E$2,INDIRECT(E$1),MATCH($A28,INDIRECT(E$1&"_col"),),)),"",VLOOKUP(E$2,INDIRECT(E$1),MATCH($A28,INDIRECT(E$1&"_col"),),)) -> 6084017 | G28: =SUM(B28:D28) -> 66250401 | H28: =IF(ISERROR(VLOOKUP(A28,INDIRECT($H$1),MATCH($H$2,INDIRECT($H$1&"_col"),),)),"",VLOOKUP(A28,INDIRECT($H$1),MATCH($H$2,INDIRECT($H$1&"_col"),),)) | I28: =IF(ISERROR(H28/G28),"",H28/G28)
... A64: =A63+1 -> 2021 | B64: =IF(ISERROR(VLOOKUP(B$2,INDIRECT(B$1),MATCH($A64,INDIRECT(B$1&"_col"),),)),"",VLOOKUP(B$2,INDIRECT(B$1),MATCH($A64,INDIRECT(B$1&"_col"),),)) -> 10547764 | C64: =IF(ISERROR(VLOOKUP(C$2,INDIRECT(C$1),MATCH($A64,INDIRECT(C$1&"_col"),),)),"",VLOOKUP(C$2,INDIRECT(C$1),MATCH($A64,INDIRECT(C$1&"_col"),),)) -> 36783544 | D64: =IF(ISERROR(VLOOKUP(D$2,INDIRECT(D$1),MATCH($A64,INDIRECT(D$1&"_col"),),)),"",VLOOKUP(D$2,INDIRECT(D$1),MATCH($A64,INDIRECT(D$1&"_col"),),)) -> 31725500 | E64: =IF(ISERROR(VLOOKUP(E$2,INDIRECT(E$1),MATCH($A64,INDIRECT(E$1&"_col"),),)),"",VLOOKUP(E$2,INDIRECT(E$1),MATCH($A64,INDIRECT(E$1&"_col"),),)) -> 12139977 | G64: =SUM(B64:D64) -> 79056808 | H64: =IF(ISERROR(VLOOKUP(A64,INDIRECT($H$1),MATCH($H$2,INDIRECT($H$1&"_col"),),)),"",VLOOKUP(A64,INDIRECT($H$1),MATCH($H$2,INDIRECT($H$1&"_col"),),)) | I64: =IF(ISERROR(H64/G64),"",H64/G64)

Sheet SEDS Prices and Expenditures
A1: Data_Status | B1: State | C1: MSN | D1: 1970 | E1: 1971 | F1: 1972 | G1: 1973 | H1: 1974 | I1: 1975 | J1: 1976 | K1: 1977 | L1: 1978 | M1: 1979 | N1: 1980 | O1: 1981 | P1: 1982 | Q1: 1983 | R1: 1984 | S1: 1985 | T1: 1986 | U1: 1987 | V1: 1988 | W1: 1989 | X1: 1990 | Y1: 1991 | Z1: 1992 | AA1: 1993 | AB1: 1994 | AC1: 1995 | AD1: 1996 | AE1: 1997 | AF1: 1998 | AG1: 1999 | AH1: 2000 | AI1: 2001 | AJ1: 2002 | AK1: 2003 | AL1: 2004 | AM1: 2005 | AN1: 2006 | AO1: 2007 | AP1: 2008 | AQ1: 2009 | AR1: 2010 | AS1: 2011 | AT1: 2012 | AU1: 2013 | AV1: 2014 | AW1: 2015 | AX1: 2016 | AY1: 2017 | AZ1: 2018 | BA1: 2019 | BB1: 2020 | BC1: 2021
A2: 2021F | B2: US | C2: ARICD | D2: 0.68 | E2: 0.79 | F2: 0.82 | G2: 0.84 | H2: 1.6 | I2: 1.89 | J2: 1.86 | K2: 1.95 | L2: 2.13 | M2: 2.58 | N2: 3.68 | O2: 5.02 | P2: 4.24 | Q2: 4.32 | R2: 4.54 | S2: 4.77 | T2: 4.34 | U2: 3.56 | V2: 3.39 | W2: 2.95 | X2: 3.02 | Y2: 3.14 | Z2: 2.5 | AA2: 2.9 | AB2: 2.93 | AC2: 3.18 | AD2: 3.29 | AE2: 3.54 | AF2: 3.43 | AG2: 3.31 | AH2: 3.99 | AI2: 3.99 | AJ2: 4.12 | AK2: 4.64 | AL2: 4.77 | AM2: 5.27 | AN2: 6.7 | AO2: 7.23 | AP2: 8.07 | AQ2: 11.86 | AR2: 13.35 | AS2: 14.9 | AT2: 16.35 | AU2: 15.55 | AV2: 15.98 | AW2: 13.28 | AX2: 9.52 | AY2: 9.89 | AZ2: 12.89 | BA2: 13.72 | BB2: 12.04 | BC2: 13.44
A3: 2021F | B3: US | C3: ARICV | D3: 730.8 | E3: 878 | F3: 928.1 | G3: 1057.8 | H3: 1865.4 | I3: 1913.6 | J3: 1856 | K3: 2064.9 | L3: 2470.5 | M3: 2976.6 | N3: 3542.9 | O3: 4156.2 | P3: 3513.5 | Q3: 3901.5 | R3: 4500.8 | S3: 4915.5 | T3: 4716.8 | U3: 4017.7 | V3: 3847.5 | W3: 3228.3 | X3: 3529.1 | Y3: 3381.7 | Z3: 2755.2 | AA3: 3335.9 | AB3: 3437.5 | AC3: 3747.6 | AD3: 3870.4 | AE3: 4331.1 | AF3: 4335.1 | AG3: 4380.8 | AH3: 5091.1 | AI3: 5015.1 | AJ3: 5107.5 | AK3: 5660.9 | AL3: 6220.9 | AM3: 6969 | AN3: 8448.4 | AO3: 8656.9 | AP3: 8171.1 | AQ3: 10357.4 | AR3: 11715.4 | AS3: 12806.5 | AT3: 13519.2 | AU3: 12184.5 | AV3: 12667.5 | AW3: 11040.7 | AX3: 8128.3 | AY3: 8397.9 | AZ3: 10220.6 | BA3: 11574.4 | BB3: 10024.2 | BC3: 12074.5
A4: 2021F | B4: US | C4: ARTCD | D4: 0.68 | E4: 0.79 | F4: 0.82 | G4: 0.84 | H4: 1.6 | I4: 1.89 | J4: 1.86 | K4: 1.95 | L4: 2.13 | M4: 2.58 | N4: 3.68 | O4: 5.02 | P4: 4.24 | Q4: 4.32 | R4: 4.54 | S4: 4.77 | T4: 4.34 | U4: 3.56 | V4: 3.39 | W4: 2.95 | X4: 3.02 | Y4: 3.14 | Z4: 2.5 | AA4: 2.9 | AB4: 2.93 | AC4: 3.18 | AD4: 3.29 | AE4: 3.54 | AF4: 3.43 | AG4: 3.31 | AH4: 3.99 | AI4: 3.99 | AJ4: 4.12 | AK4: 4.64 | AL4: 4.77 | AM4: 5.27 | AN4: 6.7 | AO4: 7.23 | AP4: 8.07 | AQ4: 11.86 | AR4: 13.35 | AS4: 14.9 | AT4: 16.35 | AU4: 15.55 | AV4: 15.98 | AW4: 13.28 | AX4: 9.52 | AY4: 9.89 | AZ4: 12.89 | BA4: 13.72 | BB4: 12.04 | BC4: 13.44
A5: 2021F | B5: US | C5: ARTCV | D5: 730.8 | E5: 878 | F5: 928.1 | G5: 1057.8 | H5: 1865.4 | I5: 1913.6 | J5: 1856 | K5: 2064.9 | L5: 2470.5 | M5: 2976.6 | N5: 3542.9 | O5: 4156.2 | P5: 3513.5 | Q5: 3901.5 | R5: 4500.8 | S5: 4915.5 | T5: 4716.8 | U5: 4017.7 | V5: 3847.5 | W5: 3228.3 | X5: 3529.1 | Y5: 3381.7 | Z5: 2755.2 | AA5: 3335.9 | AB5: 3437.5 | AC5: 3747.6 | AD5: 3870.4 | AE5: 4331.1 | AF5: 4335.1 | AG5: 4380.8 | AH5: 5091.1 | AI5: 5015.1 | AJ5: 5107.5 | AK5: 5660.9 | AL5: 6220.9 | AM5: 6969 | AN5: 8448.4 | AO5: 8656.9 | AP5: 8171.1 | AQ5: 10357.4 | AR5: 11715.4 | AS5: 12806.5 | AT5: 13519.2 | AU5: 12184.5 | AV5: 12667.5 | AW5: 11040.7 | AX5: 8128.3 | AY5: 8397.9 | AZ5: 10220.6 | BA5: 11574.4 | BB5: 10024.2 | BC5: 12074.5
A6: 2021F | B6: US | C6: ARTXD | D6: 0.68 | E6: 0.79 | F6: 0.82 | G6: 0.84 | H6: 1.6 | I6: 1.89 | J6: 1.86 | K6: 1.95 | L6: 2.13 | M6: 2.58 | N6: 3.68 | O6: 5.02 | P6: 4.24 | Q6: 4.32 | R6: 4.54 | S6: 4.77 | T6: 4.34 | U6: 3.56 | V6: 3.39 | W6: 2.95 | X6: 3.02 | Y6: 3.14 | Z6: 2.5 | AA6: 2.9 | AB6: 2.93 | AC6: 3.18 | AD6: 3.29 | AE6: 3.54 | AF6: 3.43 | AG6: 3.31 | AH6: 3.99 | AI6: 3.99 | AJ6: 4.12 | AK6: 4.64 | AL6: 4.77 | AM6: 5.27 | AN6: 6.7 | AO6: 7.23 | AP6: 8.07 | AQ6: 11.86 | AR6: 13.35 | AS6: 14.9 | AT6: 16.35 | AU6: 15.55 | AV6: 15.98 | AW6: 13.28 | AX6: 9.52 | AY6: 9.89 | AZ6: 12.89 | BA6: 13.72 | BB6: 12.04 | BC6: 13.44
A7: 2021F | B7: US | C7: ARTXV | D7: 730.8 | E7: 878 | F7: 928.1 | G7: 1057.8 | H7: 1865.4 | I7: 1913.6 | J7: 1856 | K7: 2064.9 | L7: 2470.5 | M7: 2976.6 | N7: 3542.9 | O7: 4156.2 | P7: 3513.5 | Q7: 3901.5 | R7: 4500.8 | S7: 4915.5 | T7: 4716.8 | U7: 4017.7 | V7: 3847.5 | W7: 3228.3 | X7: 3529.1 | Y7: 3381.7 | Z7: 2755.2 | AA7: 3335.9 | AB7: 3437.5 | AC7: 3747.6 | AD7: 3870.4 | AE7: 4331.1 | AF7: 4335.1 | AG7: 4380.8 | AH7: 5091.1 | AI7: 5015.1 | AJ7: 5107.5 | AK7: 5660.9 | AL7: 6220.9 | AM7: 6969 | AN7: 8448.4 | AO7: 8656.9 | AP7: 8171.1 | AQ7: 10357.4 | AR7: 11715.4 | AS7: 12806.5 | AT7: 13519.2 | AU7: 12184.5 | AV7: 12667.5 | AW7: 11040.7 | AX7: 8128.3 | AY7: 8397.9 | AZ7: 10220.6 | BA7: 11574.4 | BB7: 10024.2 | BC7: 12074.5
A8: 2021F | B8: US | C8: AVACD | D8: 2.17 | E8: 2.21 | F8: 2.19 | G8: 2.36 | H8: 3.23 | I8: 3.45 | J8: 3.59 | K8: 3.97 | L8: 4.29 | M8: 5.73 | N8: 9.02 | O8: 10.84 | P8: 10.92 | Q8: 10.44 | R8: 10.27 | S8: 9.99 | T8: 8.41 | U8: 7.55 | V8: 7.41 | W8: 8.28 | X8: 9.32 | Y8: 8.71 | Z8: 8.54 | AA8: 8.24 | AB8: 7.96 | AC8: 8.36 | AD8: 9.29 | AE8: 9.39 | AF8: 8.11 | AG8: 8.81 | AH8: 10.87 | AI8: 11.01 | AJ8: 10.72 | AK8: 12.42 | AL8: 15.13 | AM8: 18.56 | AN8: 22.31 | AO8: 23.7 | AP8: 27.23 | AQ8: 20.32 | AR8: 25.19 | AS8: 31.64 | AT8: 33.04 | AU8: 32.71 | AV8: 33.16 | AW8: 24.86 | AX8: 21.62 | AY8: 24.13 | AZ8: 27.04 | BA8: 25.57 | BB8: 22.34 | BC8: 28.86
A9: 2021F | B9: US | C9: AVACV | D9: 218 | E9: 199.8 | F9: 187.5 | G9: 196.8 | H9: 264.7 | I9: 244.7 | J9: 241.9 | K9: 279.1 | L9: 306.8 | M9: 403.1 | N9: 580.3 | O9: 610 | P9: 512.8 | Q9: 497.8 | R9: 450.5 | S9: 502.9 | T9: 495.7 | U9: 344.4 | V9: 363.2 | W9: 394 | X9: 419.1 | Y9: 363.4 | Z9: 350.8 | AA9: 316.3 | AB9: 303.7 | AC9: 331 | AD9: 346.9 | AE9: 372.6 | AF9: 288 | AG9: 345.1 | AH9: 394.3 | AI9: 384.6 | AJ9: 361.5 | AK9: 375.4 | AL9: 472.8 | AM9: 656.5 | AN9: 746.4 | AO9: 748.8 | AP9: 770.2 | AQ9: 539.6 | AR9: 681.4 | AS9: 856.1 | AT9: 829.7 | AU9: 731.4 | AV9: 719.5 | AW9: 525.6 | AX9: 442.5 | AY9: 505.5 | AZ9: 605.5 | BA9: 598 | BB9: 451.3 | BC9: 622
A10: 2021F | B10: US | C10: AVTCD | D10: 2.17 | E10: 2.21 | F10: 2.19 | G10: 2.36 | H10: 3.23 | I10: 3.45 | J10: 3.59 | K10: 3.97 | L10: 4.29 | M10: 5.73 | N10: 9.02 | O10: 10.84 | P10: 10.92 | Q10: 10.44 | R10: 10.27 | S10: 9.99 | T10: 8.41 | U10: 7.55 | V10: 7.41 | W10: 8.28 | X10: 9.32 | Y10: 8.71 | Z10: 8.54 | AA10: 8.24 | AB10: 7.96 | AC10: 8.36 | AD10: 9.29 | AE10: 9.39 | AF10: 8.11 | AG10: 8.81 | AH10: 10.87 | AI10: 11.01 | AJ10: 10.72 | AK10: 12.42 | AL10: 15.13 | AM10: 18.56 | AN10: 22.31 | AO10: 23.7 | AP10: 27.23 | AQ10: 20.32 | AR10: 25.19 | AS10: 31.64 | AT10: 33.04 | AU10: 32.71 | AV10: 33.16 | AW10: 24.86 | AX10: 21.62 | AY10: 24.13 | AZ10: 27.04 | BA10: 25.57 | BB10: 22.34 | BC10: 28.86
A11: 2021F | B11: US | C11: AVTCV | D11: 218 | E11: 199.8 | F11: 187.5 | G11: 196.8 | H11: 264.7 | I11: 244.7 | J11: 241.9 | K11: 279.1 | L11: 306.8 | M11: 403.1 | N11: 580.3 | O11: 610 | P11: 512.8 | Q11: 497.8 | R11: 450.5 | S11: 502.9 | T11: 495.7 | U11: 344.4 | V11: 363.2 | W11: 394 | X11: 419.1 | Y11: 363.4 | Z11: 350.8 | AA11: 316.3 | AB11: 303.7 | AC11: 331 | AD11: 346.9 | AE11: 372.6 | AF11: 288 | AG11: 345.1 | AH11: 394.3 | AI11: 384.6 | AJ11: 361.5 | AK11: 375.4 | AL11: 472.8 | AM11: 656.5 | AN11: 746.4 | AO11: 748.8 | AP11: 770.2 | AQ11: 539.6 | AR11: 681.4 | AS11: 856.1 | AT11: 829.7 | AU11: 731.4 | AV11: 719.5 | AW11: 525.6 | AX11: 442.5 | AY11: 505.5 | AZ11: 605.5 | BA11: 598 | BB11: 451.3 | BC11: 622
A12: 2021F | B12: US | C12: AVTXD | D12: 2.17 | E12: 2.21 | F12: 2.19 | G12: 2.36 | H12: 3.23 | I12: 3.45 | J12: 3.59 | K12: 3.97 | L12: 4.29 | M12: 5.73 | N12: 9.02 | O12: 10.84 | P12: 10.92 | Q12: 10.44 | R12: 10.27 | S12: 9.99 | T12: 8.41 | U12: 7.55 | V12: 7.41 | W12: 8.28 | X12: 9.32 | Y12: 8.71 | Z12: 8.54 | AA12: 8.24 | AB12: 7.96 | AC12: 8.36 | AD12: 9.29 | AE12: 9.39 | AF12: 8.11 | AG12: 8.81 | AH12: 10.87 | AI12: 11.01 | AJ12: 10.72 | AK12: 12.42 | AL12: 15.13 | AM12: 18.56 | AN12: 22.31 | AO12: 23.7 | AP12: 27.23 | AQ12: 20.32 | AR12: 25.19 | AS12: 31.64 | AT12: 33.04 | AU12: 32.71 | AV12: 33.16 | AW12: 24.86 | AX12: 21.62 | AY12: 24.13 | AZ12: 27.04 | BA12: 25.57 | BB12: 22.34 | BC12: 28.86
... A63: 2021F | B63: US | C63: ELIMV | D63: 40.4 | E63: 49.7 | F63: 78.1 | G63: 135.1 | H63: 167.1 | I63: 149.6 | J63: 155.8 | K63: 323.3 | L63: 379.5 | M63: 440.5 | N63: 592.2 | O63: 998.8 | P63: 1043 | Q63: 1230.1 | R63: 1307.9 | S63: 1463 | T63: 1287.4 | U63: 1598 | V63: 1171.2 | W63: 791.5 | X63: 527 | Y63: 538.5 | Z63: 635.9 | AA63: 706.9 | AB63: 1015.1 | AC63: 908.2 | AD63: 944.7 | AE63: 985.3 | AF63: 1060.5 | AG63: 1280.6 | AH63: 2782.7 | AI63: 2689.5 | AJ63: 1122.3 | AK63: 1369.8 | AL63: 1615.4 | AM63: 2478.2 | AN63: 2522.5 | AO63: 3199.9 | AP63: 3556 | AQ63: 2155.4 | AR63: 2046.9 | AS63: 2057.4 | AT63: 1923.4 | AU63: 2713.7 | AV63: 3020.1 | AW63: 2718.7 | AX63: 2167.8 | AY63: 2058.4 | AZ63: 2134.8 | BA63: 1853.9 | BB63: 1757.3 | BC63: 2324.8
A64: 2021F | B64: US | C64: EMACV | D64: 0 | E64: 0 | F64: 0 | G64: 0 | H64: 0 | I64: 0 | J64: 0 | K64: 0 | L64: 0 | M64: 0 | N64: 0 | O64: 72.5 | P64: 189.8 | Q64: 308.5 | R64: 366.9 | S64: 450.5 | T64: 390.5 | U64: 477.9 | V64: 487.4 | W64: 545.2 | X64: 551 | Y64: 622.5 | Z64: 702.1
A65: 2021F | B65: US | C65: EMCCV | D65: 0 | E65: 0 | F65: 0 | G65: 0 | H65: 0 | I65: 0 | J65: 0 | K65: 0 | L65: 0 | M65: 0 | N65: 0 | O65: 0.7 | P65: 1.6 | Q65: 2.6 | R65: 3.3 | S65: 3.3 | T65: 3.3 | U65: 4.1 | V65: 4.7 | W65: 4.6 | X65: 4.6 | Y65: 4.3 | Z65: 4.3
A66: 2021F | B66: US | C66: EMICV | D66: 0 | E66: 0 | F66: 0 | G66: 0 | H66: 0 | I66: 0 | J66: 0 | K66: 0 | L66: 0 | M66: 0 | N66: 0 | O66: 2.7 | P66: 4.9 | Q66: 4.3 | R66: 7.5 | S66: 10.1 | T66: 7.8 | U66: 9.2 | V66: 8.3 | W66: 9.8 | X66: 9.1 | Y66: 11.6 | Z66: 14.1
A67: 2021F | B67: US | C67: EMTCV | D67: 0 | E67: 0 | F67: 0 | G67: 0 | H67: 0 | I67: 0 | J67: 0 | K67: 0 | L67: 0 | M67: 0 | N67: 0 | O67: 75.9 | P67: 196.4 | Q67: 315.3 | R67: 377.6 | S67: 463.9 | T67: 401.6 | U67: 491.3 | V67: 500.4 | W67: 559.6 | X67: 564.7 | Y67: 638.4 | Z67: 720.5
A68: 2021F | B68: US | C68: ESACD | D68: 4.65 | E68: 5.35 | F68: 6.01 | G68: 6.7 | H68: 10.91 | I68: 11.72 | J68: 11.97 | K68: 10.85 | L68: 12.46 | M68: 13.65 | N68: 14.71 | O68: 16.9 | P68: 20.42 | Q68: 21.06 | R68: 20.29 | S68: 19.74 | T68: 19.63 | U68: 23.03 | V68: 22.05 | W68: 22.99 | X68: 20.26 | Y68: 20.38 | Z68: 21.77 | AA68: 22.43 | AB68: 22.61 | AC68: 22.63 | AD68: 22.59 | AE68: 22.47 | AF68: 21.72 | AG68: 20.57 | AH68: 20.71 | AI68: 21.59 | AJ68: 21.02 | AK68: 22.05 | AL68: 21.05 | AM68: 25.12 | AN68: 27.96 | AO68: 28.42 | AP68: 31.39 | AQ68: 31.25 | AR68: 30.95 | AS68: 30.67 | AT68: 29.93 | AU68: 30.93 | AV68: 30.62 | AW68: 29.57 | AX68: 28.22 | AY68: 28.38 | AZ68: 28.43 | BA68: 28.32 | BB68: 29.02 | BC68: 29.9
A69: 2021F | B69: US | C69: ESACV | D69: 49.4 | E69: 56 | F69: 62.3 | G69: 70.5 | H69: 106 | I69: 119 | J69: 120.4 | K69: 113.2 | L69: 124.9 | M69: 138.1 | N69: 162.8 | O69: 183.7 | P69: 224.7 | Q69: 267 | R69: 290 | S69: 279.3 | T69: 295.6 | U69: 358.5 | V69: 351.3 | W69: 374.2 | X69: 328.4 | Y69: 330.9 | Z69: 349.4 | AA69: 365.2 | AB69: 385.2 | AC69: 384.1 | AD69: 379.5 | AE69: 376.2 | AF69: 367.7 | AG69: 359.7 | AH69: 380.3 | AI69: 404 | AJ69: 396.5 | AK69: 517.7 | AL69: 518.8 | AM69: 643.2 | AN69: 702 | AO69: 792.5 | AP69: 819.8 | AQ69: 828.4 | AR69: 814.3 | AS69: 802.7 | AT69: 747.4 | AU69: 804.8 | AV69: 810.5 | AW69: 770.5 | AX69: 721.7 | AY69: 728.5 | AZ69: 743.6 | BA69: 737.5 | BB69: 648.4 | BC69: 646.2
A70: 2021F | B70: US | C70: ESCCD | D70: 6.09 | E70: 6.44 | F70: 6.71 | G70: 7.06 | H70: 8.91 | I70: 10.11 | J70: 10.82 | K70: 11.99 | L70: 12.78 | M70: 13.72 | N70: 16.06 | O70: 18.44 | P70: 20.11 | Q70: 20.57 | R70: 20.89 | S70: 21.3 | T70: 21.1 | U70: 20.44 | V70: 20.34 | W70: 20.77 | X70: 21.2 | Y70: 21.73 | Z70: 22.15 | AA70: 22.4 | AB70: 22.35 | AC70: 22.29 | AD70: 22.17 | AE70: 22.03 | AF70: 21.48 | AG70: 21.01 | AH70: 21.52 | AI70: 22.99 | AJ70: 22.81 | AK70: 23.54 | AL70: 23.95 | AM70: 25.4 | AN70: 27.72 | AO70: 28.27 | AP70: 30.06 | AQ70: 29.77 | AR70: 29.87 | AS70: 30 | AT70: 29.57 | AU70: 30.07 | AV70: 31.48 | AW70: 31.18 | AX70: 30.58 | AY70: 31.25 | AZ70: 31.27 | BA70: 31.29 | BB70: 31.04 | BC70: 32.87
A71: 2021F | B71: US | C71: ESCCV | D71: 7319.5 | E71: 8300.7 | F71: 9442.7 | G71: 10707.1 | H71: 13372.8 | I71: 16156.7 | J71: 18148.2 | K71: 21023.4 | L71: 23166.4 | M71: 25433.1 | N71: 30611.3 | O71: 37484 | P71: 41759.3 | Q71: 43529.1 | R71: 47304.1 | S71: 50091.7 | T71: 51449.3 | U71: 51899.7 | V71: 54411.2 | W71: 57460.1 | X71: 60626.6 | Y71: 63407.3 | Z71: 64233.4 | AA71: 67626.2 | AB71: 69637.3 | AC71: 72480.6 | AD71: 74120.5 | AE71: 77152.7 | AF71: 78999.5 | AG71: 79141.4 | AH71: 85129 | AI71: 93402.2 | AJ71: 93762.6 | AK71: 96263.4 | AL71: 100546.2 | AM71: 110521.6 | AN71: 122913.9 | AO71: 128903.2 | AP71: 137036 | AQ71: 132747 | AR71: 135553.7 | AS71: 135926.7 | AT71: 133898.4 | AU71: 137188.5 | AV71: 145253.2 | AW71: 144781.5 | AX71: 142642.5 | AY71: 144241.9 | AZ71: 147425.2 | BA71: 145279.8 | BB71: 136372.3 | BC71: 149008.2
A72: 2021F | B72: US | C72: ESICD | D72: 2.99 | E72: 3.22 | F72: 3.4 | G72: 3.66 | H72: 4.95 | I72: 6.07 | J72: 6.48 | K72: 7.33 | L72: 8.18 | M72: 8.94 | N72: 10.81 | O72: 12.57 | P72: 14.51 | Q72: 14.54 | R72: 14.16 | S72: 14.57 | T72: 14.45 | U72: 13.98 | V72: 13.78 | W72: 13.85 | X72: 13.92 | Y72: 14.18 | Z72: 14.18 | AA72: 14.22 | AB72: 14 | AC72: 13.68 | AD72: 13.49 | AE72: 13.29 | AF72: 13.13 | AG72: 12.98 | AH72: 13.6 | AI72: 14.78 | AJ72: 14.3 | AK72: 14.97 | AL72: 15.38 | AM72: 16.77 | AN72: 18.02 | AO72: 18.71 | AP72: 20.34 | AQ72: 20.05 | AR72: 19.89 | AS72: 20.02 | AT72: 19.6 | AU72: 20.26 | AV72: 20.86 | AW72: 20.33 | AX72: 19.91 | AY72: 20.23 | AZ72: 20.35 | BA72: 20.04 | BB72: 19.62 | BC72: 21.05
A73: 2021F | B73: US | C73: ESICV | D73: 5624.1 | E73: 6256 | F73: 7173 | G73: 8283.8 | H73: 11184 | I73: 13760.4 | J73: 16083.1 | K73: 18956.2 | L73: 21798.5 | M73: 24797.2 | N73: 28863.2 | O73: 34006.8 | P73: 35364.2 | Q73: 37016.8 | R73: 39049.7 | S73: 40189.9 | T73: 39271.5 | U73: 39108.9 | V73: 40507.5 | W73: 42254.8 | X73: 43357.5 | Y73: 44201 | Z73: 45474.4 | AA73: 45726.4 | AB73: 46256.5 | AC73: 45402.2 | AD73: 46102.4 | AE73: 45610.5 | AF73: 45634.1 | AG73: 45429.3 | AH73: 47858.8 | AI73: 48518.7 | AJ73: 46605.6 | AK73: 49962.3 | AL73: 51491 | AM73: 56229.4 | AN73: 59764.2 | AO73: 62934.1 | AP73: 67101.7 | AQ73: 59816.1 | AR73: 62766.6 | AS73: 64566 | AT73: 62936.6 | AU73: 64944.2 | AV73: 67630.4 | AW73: 65168.6 | AX73: 63125.8 | AY73: 64590.5 | AZ73: 66147.2 | BA73: 65321 | BB73: 61249.7 | BC73: 68815.7
A74: 2021F | B74: US | C74: ESISB | D74: 1881319 | E74: 1940500 | F74: 2109865 | G74: 2261143 | H74: 2257970 | I74: 2268146 | J74: 2483055 | K74: 2587146 | L74: 2665820 | M74: 2774038 | N74: 2668870 | O74: 2704689 | P74: 2437631 | Q74: 2546397 | R74: 2758541 | S74: 2759110 | T74: 2717936 | U74: 2796854 | V74: 2939548 | W74: 3050457 | X74: 3114947 | Y74: 3117631 | Z74: 3207990 | AA74: 3214961 | AB74: 3303902 | AC74: 3319980 | AD74: 3417119 | AE74: 3432697 | AF74: 3475518 | AG74: 3499032 | AH74: 3519172 | AI74: 3283785 | AJ74: 3260223 | AK74: 3338152 | AL74: 3348726 | AM74: 3352502 | AN74: 3316275 | AO74: 3364242 | AP74: 3298838 | AQ74: 2983444 | AR74: 3156080 | AS74: 3224751 | AT74: 3210961 | AU74: 3204806 | AV74: 3242598 | AW74: 3206071 | AX74: 3170858 | AY74: 3192728 | AZ74: 3250225 | BA74: 3259183 | BB74: 3122171 | BC74: 3268408
A75: 2021F | B75: US | C75: ESRCD | D75: 6.51 | E75: 6.8 | F75: 7.09 | G75: 7.44 | H75: 9.09 | I75: 10.29 | J75: 10.93 | K75: 11.87 | L75: 12.63 | M75: 13.6 | N75: 15.71 | O75: 18.17 | P75: 20.11 | Q75: 21.04 | R75: 20.96 | S75: 21.66 | T75: 21.75 | U75: 21.82 | V75: 21.92 | W75: 22.41 | X75: 22.96 | Y75: 23.57 | Z75: 24.06 | AA75: 24.4 | AB75: 24.57 | AC75: 24.63 | AD75: 24.5 | AE75: 24.71 | AF75: 24.21 | AG75: 23.93 | AH75: 24.14 | AI75: 25.16 | AJ75: 24.75 | AK75: 25.56 | AL75: 26.22 | AM75: 27.68 | AN75: 30.49 | AO75: 31.22 | AP75: 33.01 | AQ75: 33.73 | AR75: 33.81 | AS75: 34.34 | AT75: 34.82 | AU75: 35.54 | AV75: 36.69 | AW75: 37.08 | AX75: 36.78 | AY75: 37.77 | AZ75: 37.71 | BA75: 38.14 | BB75: 38.55 | BC75: 40.03
A76: 2021F | B76: US | C76: ESRCV | D76: 10351.7 | E76: 11589.1 | F76: 13034.3 | G76: 14712.5 | H76: 17923.7 | I76: 20643.7 | J76: 22620.7 | K76: 26132.2 | L76: 29069.5 | M76: 31682.8 | N76: 38457.6 | O76: 44780.4 | P76: 50045 | Q76: 53918.1 | R76: 55776.6 | S76: 58671.7 | T76: 60776.4 | U76: 63317.9 | V76: 66793.2 | W76: 69243.3 | X76: 72378.4 | Y76: 76828 | Z76: 76848.4 | AA76: 82813.8 | AB76: 84552.3 | AC76: 87609.6 | AD76: 90502.9 | AE76: 90703.9 | AF76: 93360.1 | AG76: 93482.4 | AH76: 98209.4 | AI76: 103157.9 | AJ76: 106833.6 | AK76: 111248.9 | AL76: 115577.1 | AM76: 128392.7 | AN76: 140582.4 | AO76: 148294.9 | AP76: 155496.5 | AQ76: 157043.6 | AR76: 166778 | AS76: 166713.9 | AT76: 163280.4 | AU76: 169130.6 | AV76: 176178 | AW76: 177623.6 | AX76: 177076.7 | AY76: 177661.2 | AZ76: 189033 | BA76: 187436 | BB76: 192663.2 | BC76: 200833.9
A77: 2021F | B77: US | C77: ESRFB | D77: 66435 | E77: 70697 | F77: 77152 | G77: 79779 | H77: 78824 | I77: 78217 | J77: 89828 | K77: 94813 | L77: 94755 | M77: 98535 | N77: 112135 | O77: 112746 | P77: 104134 | Q77: 101313 | R77: 100156 | S77: 95956 | T77: 115834 | U77: 131437 | V77: 119304 | W77: 107891 | X77: 111173 | Y77: 112111 | Z77: 110910 | AA77: 119123 | AB77: 135330 | AC77: 135330 | AD77: 109631 | AE77: 109631 | AF77: 111187 | AG77: 111603 | AH77: 112013 | AI77: 116646 | AJ77: 118468 | AK77: 116066 | AL77: 124176 | AM77: 124859 | AN77: 134272 | AO77: 142721 | AP77: 145631 | AQ77: 146781 | AR77: 157727 | AS77: 157617 | AT77: 152295 | AU77: 157215 | AV77: 161132 | AW77: 159893 | AX77: 161695 | AY77: 165697 | AZ77: 164069 | BA77: 160845 | BB77: 150217 | BC77: 145686
A78: 2021F | B78: US | C78: ESSCB | D78: 4684092 | E78: 4943375 | F78: 5365536 | G78: 5764665 | H78: 5741788 | I78: 5882857 | J78: 6240272 | K78: 6552996 | L78: 6790394 | M78: 6968055 | N78: 7034118 | O78: 7213165 | P78: 7014799 | Q78: 7237744 | R78: 7698981 | S78: 7833443 | T78: 7966351 | U78: 8252776 | V78: 8677045 | W78: 8923023 | X78: 9144063 | Y78: 9311843 | Z78: 9317693 | AA78: 9644186 | AB78: 9877398 | AC78: 10146004 | AD78: 10471414 | AE78: 10623192 | AF78: 11026368 | AG78: 11189238 | AH78: 11561853 | AI78: 11465245 | AJ78: 11705702 | AK78: 11804803 | AL78: 11979824 | AM78: 12366366 | AN78: 12387491 | AO78: 12701961 | AP78: 12594656 | AQ78: 12125484 | AR78: 12653792 | AS78: 12636858 | AT78: 12453850 | AU78: 12552034 | AV78: 12684026 | AW78: 12665789 | AX78: 12675824 | AY78: 12538394 | AZ78: 13003471 | BA78: 12842800 | BB78: 12534489 | BC78: 12839957
A79: 2021F | B79: US | C79: ESTCD | D79: 4.98 | E79: 5.3 | F79: 5.54 | G79: 5.86 | H79: 7.42 | I79: 8.61 | J79: 9.13 | K79: 10.11 | L79: 10.92 | M79: 11.78 | N79: 13.95 | O79: 16.14 | P79: 18.16 | Q79: 18.62 | R79: 18.5 | S79: 19.05 | T79: 19.05 | U79: 18.74 | V79: 18.68 | W79: 18.98 | X79: 19.32 | Y79: 19.84 | Z79: 20.06 | AA79: 20.38 | AB79: 20.33 | AC79: 20.29 | AD79: 20.16 | AE79: 20.13 | AF79: 19.8 | AG79: 19.52 | AH79: 20.03 | AI79: 21.41 | AJ79: 21.15 | AK79: 21.85 | AL79: 22.38 | AM79: 23.92 | AN79: 26.15 | AO79: 26.84 | AP79: 28.62 | AQ79: 28.9 | AR79: 28.92 | AS79: 29.12 | AT79: 28.98 | AU79: 29.64 | AV79: 30.74 | AW79: 30.66 | AX79: 30.26 | AY79: 30.88 | AZ79: 31.02 | BA79: 31.05 | BB79: 31.19 | BC79: 32.66
... A88: 2021F | B88: US | C88: FSICV | D88: 32.4 | E88: 44.2 | F88: 41.9 | G88: 39.2 | H88: 99 | I88: 123.9 | J88: 144.3 | K88: 175.1 | L88: 142.9 | M88: 227.4 | N88: 371 | O88: 190.7 | P88: 121.5 | Q88: 201.5 | R88: 251.4 | S88: 256.2 | T88: 0 | U88: 0 | V88: 0 | W88: 0 | X88: 0 | Y88: 0 | Z88: 0 | AA88: 0 | AB88: 0 | AC88: 0 | AD88: 0 | AE88: 0 | AF88: 0 | AG88: 0 | AH88: 0 | AI88: 0 | AJ88: 0 | AK88: 0 | AL88: 0 | AM88: 0 | AN88: 0 | AO88: 0 | AP88: 0 | AQ88: 0 | AR88: 0 | AS88: 0 | AT88: 0 | AU88: 0 | AV88: 0 | AW88: 0 | AX88: 0 | AY88: 0 | AZ88: 0 | BA88: 0 | BB88: 0 | BC88: 0
A89: 2021F | B89: US | C89: GDPRV | AE89: 8577552 | AF89: 9062817 | AG89: 9631172 | AH89: 10250952 | AI89: 10581929 | AJ89: 10929108 | AK89: 11456450 | AL89: 12217196 | AM89: 13039197 | AN89: 13815583 | AO89: 14474228 | AP89: 14769862 | AQ89: 14478067 | AR89: 15048970 | AS89: 15599731 | AT89: 16253970 | AU89: 16843196 | AV89: 17550687 | AW89: 18206023 | AX89: 18695106 | AY89: 19477337 | AZ89: 20533058 | BA89: 21380976 | BB89: 21060474 | BC89: 23315081
A90: 2021F | B90: US | C90: GDPRX | AE90: 11529157 | AF90: 12045824 | AG90: 12623361 | AH90: 13138035 | AI90: 13263417 | AJ90: 13488357 | AK90: 13865519 | AL90: 14399696 | AM90: 14901269 | AN90: 15315943 | AO90: 15623871 | AP90: 15642962 | AQ90: 15236262 | AR90: 15648991 | AS90: 15891534 | AT90: 16253970 | AU90: 16553348 | AV90: 16932051 | AW90: 17390295 | AX90: 17680274 | AY90: 18076651 | AZ90: 18609078 | BA90: 19036052 | BB90: 18509143 | BC90: 19609812
A91: 2021F | B91: US | C91: HLACD | D91: 1.1 | E91: 1.17 | F91: 1.18 | G91: 1.31 | H91: 2.4 | I91: 2.43 | J91: 2.63 | K91: 3.06 | L91: 3.07 | M91: 3.88 | N91: 4.97 | O91: 5.61 | P91: 6 | Q91: 6.45 | R91: 6.44 | S91: 9.61 | T91: 9.14 | U91: 8.91 | V91: 9.1 | W91: 8.78 | X91: 9.89 | Y91: 11.27 | Z91: 10.9 | AA91: 11.16 | AB91: 11.64 | AC91: 11.78 | AD91: 11.87 | AE91: 11.45 | AF91: 10.42 | AG91: 12.28 | AH91: 15.06 | AI91: 16.06 | AJ91: 14.45 | AK91: 16.29 | AL91: 18.1 | AM91: 20.5 | AN91: 22.22 | AO91: 24.46 | AP91: 28.7 | AQ91: 22.7 | AR91: 25.8 | AS91: 29.52 | AT91: 22.57 | AU91: 23.03 | AV91: 24.56 | AW91: 14.9 | AX91: 14.53 | AY91: 19.11 | AZ91: 20.32 | BA91: 17.08 | BB91: 15.81 | BC91: 24.64
A92: 2021F | B92: US | C92: HLACV | D92: 48.6 | E92: 59.7 | F92: 62.7 | G92: 64.8 | H92: 109.3 | I92: 104.9 | J92: 123.6 | K92: 153.2 | L92: 165.7 | M92: 84.4 | N92: 87.7 | O92: 190.8 | P92: 204.5 | Q92: 261.1 | R92: 274.5 | S92: 284 | T92: 249.6 | U92: 192.6 | V92: 212.1 | W92: 199.9 | X92: 226.6 | Y92: 238.4 | Z92: 211.9 | AA92: 226.1 | AB92: 396.4 | AC92: 209.1 | AD92: 185.8 | AE92: 163 | AF92: 184.1 | AG92: 175.5 | AH92: 179.3 | AI92: 220.6 | AJ92: 206.7 | AK92: 291.4 | AL92: 346.2 | AM92: 578.8 | AN92: 611 | AO92: 537.5 | AP92: 1153.5 | AQ92: 637.2 | AR92: 118 | AS92: 135.8 | AT92: 102 | AU92: 140.3 | AV92: 187.1 | AW92: 148.9 | AX92: 171.7 | AY92: 236.8 | AZ92: 256.4 | BA92: 213.3 | BB92: 136.7 | BC92: 240.6
A93: 2021F | B93: US | C93: HLCCD | D93: 1.24 | E93: 1.29 | F93: 1.3 | G93: 1.4 | H93: 2.44 | I93: 2.53 | J93: 2.77 | K93: 3.17 | L93: 3.36 | M93: 3.93 | N93: 4.96 | O93: 5.68 | P93: 6.03 | Q93: 6.47 | R93: 6.43 | S93: 8.84 | T93: 8.44 | U93: 7.94 | V93: 8.13 | W93: 7.66 | X93: 8.77 | Y93: 9.25 | Z93: 8.61 | AA93: 8.71 | AB93: 8.79 | AC93: 8.89 | AD93: 10.11 | AE93: 10.33 | AF93: 9.36 | AG93: 9.14 | AH93: 11.93 | AI93: 12.9 | AJ93: 10.53 | AK93: 12.5 | AL93: 14.48 | AM93: 16.92 | AN93: 18.87 | AO93: 20.74 | AP93: 24.61 | AQ93: 19.49 | AR93: 21.62 | AS93: 25.3 | AT93: 19.5 | AU93: 19.7 | AV93: 21.3 | AW93: 12.66 | AX93: 12.04 | AY93: 15.76 | AZ93: 16.8 | BA93: 13.59 | BB93: 12.35 | BC93: 19.77
A94: 2021F | B94: US | C94: HLCCV | D94: 176.7 | E94: 186.8 | F94: 200.3 | G94: 205.2 | H94: 328.5 | I94: 328.5 | J94: 377.1 | K94: 428.7 | L94: 441.6 | M94: 374.8 | N94: 437.7 | O94: 492.4 | P94: 488.9 | Q94: 624.8 | R94: 536.2 | S94: 842.2 | T94: 786.2 | U94: 807.4 | V94: 808.4 | W94: 839.5 | X94: 897.7 | Y94: 1002.3 | Z94: 921.6 | AA94: 952.3 | AB94: 944.3 | AC94: 967.4 | AD94: 1238.8 | AE94: 1243.6 | AF94: 1101.8 | AG94: 1283.2 | AH94: 1796.1 | AI94: 1843.6 | AJ94: 1485.2 | AK94: 1963.5 | AL94: 2203 | AM94: 2225.6 | AN94: 2327.4 | AO94: 2521.6 | AP94: 3892.6 | AQ94: 2709.4 | AR94: 3027.1 | AS94: 3605.3 | AT94: 2643.1 | AU94: 2986.2 | AV94: 3417.7 | AW94: 1874.6 | AX94: 1806 | AY94: 2453.7 | AZ94: 2956.4 | BA94: 2474.3 | BB94: 2483.1 | BC94: 4289.6
A95: 2021F | B95: US | C95: HLICD | D95: 1.14 | E95: 1.21 | F95: 1.23 | G95: 1.37 | H95: 2.53 | I95: 2.64 | J95: 2.84 | K95: 3.34 | L95: 3.32 | M95: 4.24 | N95: 5.4 | O95: 6.03 | P95: 6.5 | Q95: 7.04 | R95: 6.84 | S95: 6.22 | T95: 6.14 | U95: 5.63 | V95: 5.45 | W95: 4.44 | X95: 5.95 | Y95: 6.01 | Z95: 5.43 | AA95: 5.41 | AB95: 5.88 | AC95: 5.81 | AD95: 7.28 | AE95: 6.54 | AF95: 4.97 | AG95: 5.76 | AH95: 8.68 | AI95: 8.16 | AJ95: 7.04 | AK95: 9.22 | AL95: 11.37 | AM95: 13.62 | AN95: 16.26 | AO95: 18.2 | AP95: 22.6 | AQ95: 14.45 | AR95: 17.35 | AS95: 21.41 | AT95: 15.46 | AU95: 14.74 | AV95: 14.89 | AW95: 8.49 | AX95: 8.15 | AY95: 10.5 | AZ95: 12.02 | BA95: 8.65 | BB95: 7.22 | BC95: 13.27
A96: 2021F | B96: US | C96: HLICV | D96: 1045.9 | E96: 1112.7 | F96: 1311.5 | G96: 1565.7 | H96: 2881.7 | I96: 2760 | J96: 3183.9 | K96: 3747.2 | L96: 3679.2 | M96: 6711.5 | N96: 7967.5 | O96: 8789.1 | P96: 9656.2 | Q96: 10064 | R96: 10781.9 | S96: 9804.1 | T96: 9217.6 | U96: 9078.6 | V96: 9070.8 | W96: 7273.7 | X96: 8916.1 | Y96: 9828.3 | Z96: 9432.8 | AA96: 9061.8 | AB96: 11028 | AC96: 11060.9 | AD96: 14347.5 | AE96: 13235.5 | AF96: 9646.4 | AG96: 12290.2 | AH96: 18555 | AI96: 15757.1 | AJ96: 14626.7 | AK96: 17928.5 | AL96: 23384.9 | AM96: 26247.9 | AN96: 32857.6 | AO96: 36734.5 | AP96: 39332.6 | AQ96: 26801.6 | AR96: 38127.9 | AS96: 46383 | AT96: 36261.9 | AU96: 37429.2 | AV96: 35736.2 | AW96: 22132.4 | AX96: 21061.9 | AY96: 27953.1 | AZ96: 36259.9 | BA96: 27071.8 | BB96: 23416.9 | BC96: 46634.4
A97: 2021F | B97: US | C97: HLISB | D97: 915761 | E97: 922889 | F97: 1070482 | G97: 1145829 | H97: 1138450 | I97: 1044104 | J97: 1119776 | K97: 1123384 | L97: 1109154 | M97: 1584457 | N97: 1474792 | O97: 1457724 | P97: 1485954 | Q97: 1429336 | R97: 1575404 | S97: 1576081 | T97: 1501699 | U97: 1611987 | V97: 1665651 | W97: 1639448 | X97: 1499243 | Y97: 1634704 | Z97: 1737516 | AA97: 1674717 | AB97: 1877044 | AC97: 1905291 | AD97: 1970157 | AE97: 2024495 | AF97: 1941383 | AG97: 2132324 | AH97: 2138501 | AI97: 1930513 | AJ97: 2076702 | AK97: 1944695 | AL97: 2056587 | AM97: 1927003 | AN97: 2021163 | AO97: 2017864 | AP97: 1740465 | AQ97: 1854474 | AR97: 2197572 | AS97: 2166614 | AT97: 2345288 | AU97: 2539558 | AV97: 2400080 | AW97: 2606150 | AX97: 2582848 | AY97: 2663215 | AZ97: 3015380 | BA97: 3130448 | BB97: 3243811 | BC97: 3513936
A98: 2021F | B98: US | C98: HLRCD | D98: 2.05 | E98: 2.02 | F98: 2.1 | G98: 3.59 | H98: 3.68 | I98: 3.96 | J98: 4.34 | K98: 4.83 | L98: 4.68 | M98: 6.53 | N98: 7.82 | O98: 8.2 | P98: 9.08 | Q98: 9.31 | R98: 9.31 | S98: 8.98 | T98: 8.41 | U98: 8.44 | V98: 8.25 | W98: 10.32 | X98: 10.79 | Y98: 10.7 | Z98: 10.11 | AA98: 9.94 | AB98: 10.09 | AC98: 10.02 | AD98: 11.32 | AE98: 11.28 | AF98: 10.15 | AG98: 10.04 | AH98: 13.39 | AI98: 14.67 | AJ98: 12.38 | AK98: 14.65 | AL98: 16.54 | AM98: 19.13 | AN98: 21.43 | AO98: 23.31 | AP98: 27.52 | AQ98: 23.56 | AR98: 25.65 | AS98: 28.25 | AT98: 25.91 | AU98: 25.3 | AV98: 30.05 | AW98: 22.75 | AX98: 21.56 | AY98: 25.15 | AZ98: 25.93 | BA98: 22.72 | BB98: 20.59 | BC98: 26.81
A99: 2021F | B99: US | C99: HLRCV | D99: 1124.1 | E99: 1123.5 | F99: 1259.7 | G99: 2047.6 | H99: 1936.9 | I99: 2030.1 | J99: 2310.3 | K99: 2512.8 | L99: 2362.7 | M99: 2221.5 | N99: 2436.5 | O99: 2452.5 | P99: 2625.4 | Q99: 3201.6 | R99: 2608.2 | S99: 2825.1 | T99: 2593.4 | U99: 2893.9 | V99: 2818.2 | W99: 3958.1 | X99: 3804.8 | Y99: 4052.5 | Z99: 3741.1 | AA99: 3878.8 | AB99: 3874.6 | AC99: 3959.7 | AD99: 5314.2 | AE99: 5138.7 | AF99: 4308.9 | AG99: 5289.3 | AH99: 7439.7 | AI99: 7721.2 | AJ99: 6661 | AK99: 7984.3 | AL99: 8473.8 | AM99: 9822.1 | AN99: 9559.1 | AO99: 11286.9 | AP99: 15230.8 | AQ99: 12904.2 | AR99: 13589.5 | AS99: 13914.7 | AT99: 10250.7 | AU99: 11725.8 | AV99: 14707.7 | AW99: 10141.7 | AX99: 9267.8 | AY99: 10830.2 | AZ99: 13134 | BA99: 12801.6 | BB99: 10189.1 | BC99: 12981.4
A100: 2021F | B100: US | C100: HLRFB | D100: 14735 | E100: 24890 | F100: 48507 | G100: 46542 | H100: 68211 | I100: 82044 | J100: 40910 | K100: 37648 | L100: 49033 | M100: 171678 | N100: 242898 | O100: 220150 | P100: 204649 | Q100: 72854 | R100: 247943 | S100: 236432 | T100: 227810 | U100: 261028 | V100: 242961 | W100: 248284 | X100: 281375 | Y100: 323001 | Z100: 360870 | AA100: 362732 | AB100: 374188 | AC100: 363411 | AD100: 373350 | AE100: 341120 | AF100: 307717 | AG100: 379754 | AH100: 359042 | AI100: 281161 | AJ100: 236508 | AK100: 240432 | AL100: 235538 | AM100: 211335 | AN100: 149734 | AO100: 189094 | AP100: 163517 | AQ100: 137527 | AR100: 9234 | AS100: 4959 | AT100: 5842 | AU100: 5032 | AV100: 8857 | AW100: 11546 | AX100: 9591 | AY100: 10259 | AZ100: 9007 | BA100: 8362 | BB100: 7824 | BC100: 5477
A101: 2021F | B101: US | C101: HLSCB | D101: 1652286 | E101: 1675406 | F101: 1878297 | G101: 1912855 | H101: 1845381 | I101: 1729258 | J101: 1835639 | K101: 1829018 | L101: 1799111 | M101: 2041924 | N101: 1892329 | O101: 1877363 | P101: 1890170 | Q101: 1910475 | R101: 1981654 | S101: 2015562 | T101: 1930422 | U101: 2077940 | V101: 2129919 | W101: 2155191 | X101: 1977155 | Y101: 2142871 | Z101: 2233891 | AA101: 2194456 | AB101: 2402669 | AC101: 2427239 | AD101: 2577710 | AE101: 2614524 | AF101: 2501211 | AG101: 2813629 | AH101: 2856602 | AI101: 2613480 | AJ101: 2769830 | AK101: 2664837 | AL101: 2740295 | AM101: 2600314 | AN101: 2618101 | AO101: 2645690 | AP101: 2492286 | AQ101: 2569358 | AR101: 2871992 | AS101: 2806336 | AT101: 2880889 | AU101: 3160740 | AV101: 3057697 | AW101: 3209881 | AX101: 3174567 | AY101: 3261984 | AZ101: 3710507 | BA101: 3888372 | BB101: 3948435 | BC101: 4224800
A102: 2021F | B102: US | C102: HLTCD | D102: 1.45 | E102: 1.48 | F102: 1.51 | G102: 2.03 | H102: 2.85 | I102: 3.02 | J102: 3.27 | K102: 3.74 | L102: 3.7 | M102: 4.6 | N102: 5.78 | O102: 6.35 | P102: 6.86 | Q102: 7.41 | R102: 7.17 | S102: 6.82 | T102: 6.65 | U102: 6.24 | V102: 6.06 | W102: 5.69 | X102: 7 | Y102: 7.06 | Z102: 6.4 | AA102: 6.43 | AB102: 6.76 | AC102: 6.67 | AD102: 8.18 | AE102: 7.57 | AF102: 6.09 | AG102: 6.77 | AH102: 9.79 | AI102: 9.77 | AJ102: 8.3 | AK102: 10.57 | AL102: 12.56 | AM102: 14.95 | AN102: 17.32 | AO102: 19.31 | AP102: 23.92 | AQ102: 16.76 | AR102: 19.1 | AS102: 22.82 | AT102: 17.1 | AU102: 16.54 | AV102: 17.68 | AW102: 10.69 | AX102: 10.18 | AY102: 12.71 | AZ102: 14.18 | BA102: 10.95 | BB102: 9.17 | BC102: 15.18
... A166: 2021F | B166: US | C166: NUETV | D166: 43.6 | E166: 73 | F166: 103.8 | G166: 177.5 | H166: 258.8 | I166: 448.2 | J166: 520.1 | K166: 742.7 | L166: 915.1 | M166: 941.1 | N166: 1189.1 | O166: 1436.4 | P166: 1684.5 | Q166: 1859.1 | R166: 2383.7 | S166: 2878 | T166: 3061.3 | U166: 3378.4 | V166: 4056.7 | W166: 3939.5 | X166: 4103.9 | Y166: 4072.9 | Z166: 3802.3 | AA166: 3596.6 | AB166: 3777.1 | AC166: 3809.8 | AD166: 3624.4 | AE166: 3369.5 | AF166: 3554.8 | AG166: 3642.7 | AH166: 3628.4 | AI166: 3523.5 | AJ166: 3504.4 | AK166: 3362.7 | AL166: 3445.3 | AM166: 3468.8 | AN166: 3636.5 | AO166: 3871.1 | AP166: 3976.4 | AQ166: 4680.2 | AR166: 5413.7 | AS166: 5620.9 | AT166: 5965.3 | AU166: 6522.6 | AV166: 6252.1 | AW166: 5975.4 | AX166: 5857.2 | AY166: 6134.9 | AZ166: 5916.3 | BA166: 5592.1 | BB166: 5195.2 | BC166: 5593.1
A167: 2021F | B167: US | C167: OHICD | AR167: 17.32 | AS167: 21.52 | AT167: 15.74 | AU167: 14.79 | AV167: 14.44 | AW167: 8.64 | AX167: 8.27 | AY167: 10.25 | AZ167: 11.87 | BA167: 8.52 | BB167: 7.09 | BC167: 12.91
A168: 2021F | B168: US | C168: OHICV | AR168: 29228.4 | AS168: 34804.7 | AT168: 26349.5 | AU168: 26739.4 | AV168: 26677.9 | AW168: 17351.2 | AX168: 16642.8 | AY168: 22011.3 | AZ168: 29384.9 | BA168: 22841 | BB168: 19827 | BC168: 39610.3
A169: 2021F | B169: US | C169: OPICD | D169: 1.16 | E169: 1.18 | F169: 1.19 | G169: 1.35 | H169: 2.43 | I169: 2.89 | J169: 3.15 | K169: 3.45 | L169: 3.56 | M169: 4.98 | N169: 7.58 | O169: 9.33 | P169: 8.52 | Q169: 8.01 | R169: 8.06 | S169: 7.76 | T169: 4.92 | U169: 5.79 | V169: 4.84 | W169: 5.67 | X169: 6.48 | Y169: 5.73 | Z169: 5.78 | AA169: 5.18 | AB169: 5.03 | AC169: 5.44 | AD169: 6.32 | AE169: 5.8 | AF169: 4.09 | AG169: 5.49 | AH169: 8.02 | AI169: 6.75 | AJ169: 6.9 | AK169: 7.94 | AL169: 9.93 | AM169: 13.41 | AN169: 16.22 | AO169: 18.35 | AP169: 25.42 | AQ169: 15.92 | AR169: 20.52 | AS169: 27.05 | AT169: 26.76 | AU169: 26.73 | AV169: 24.99 | AW169: 13.98 | AX169: 11.92 | AY169: 14.47 | AZ169: 17.9 | BA169: 16.68 | BB169: 11.66 | BC169: 19.07
A170: 2021F | B170: US | C170: OPICV | D170: 967.6 | E170: 1043.6 | F170: 1155.8 | G170: 1413.7 | H170: 2640 | I170: 2946.3 | J170: 4176.3 | K170: 5431.7 | L170: 6142.3 | M170: 9286 | N170: 14324.2 | O170: 14924.1 | P170: 10451 | Q170: 9618.4 | R170: 9632 | S170: 8924.5 | T170: 6139.4 | U170: 7051.7 | V170: 6060.7 | W170: 6966.2 | X170: 8947 | Y170: 8029.8 | Z170: 8282.3 | AA170: 7422.9 | AB170: 7372.3 | AC170: 7516.8 | AD170: 8986.5 | AE170: 9347.7 | AF170: 6838.7 | AG170: 8820.1 | AH170: 12715.9 | AI170: 9419.4 | AJ170: 10230.1 | AK170: 12305.1 | AL170: 17127.4 | AM170: 21627.1 | AN170: 26794.2 | AO170: 28253.6 | AP170: 34845.8 | AQ170: 17624.1 | AR170: 23497.7 | AS170: 29164 | AT170: 24959.5 | AU170: 27521 | AV170: 24825.6 | AW170: 13389.9 | AX170: 11211.9 | AY170: 14586.8 | AZ170: 17698.8 | BA170: 15299.1 | BB170: 9767.9 | BC170: 15931.1
A171: 2021F | B171: US | C171: OPISB | D171: 834813 | E171: 885547 | F171: 975363 | G171: 1043542 | H171: 1084533 | I171: 1019367 | J171: 1324193 | K171: 1576596 | L171: 1727692 | M171: 1865110 | N171: 1888876 | O171: 1599058 | P171: 1227071 | Q171: 1201419 | R171: 1195164 | S171: 1150193 | T171: 1248795 | U171: 1218050 | V171: 1253240 | W171: 1228024 | X171: 1379950 | Y171: 1401983 | Z171: 1433529 | AA171: 1433997 | AB171: 1464470 | AC171: 1382515 | AD171: 1421195 | AE171: 1611378 | AF171: 1671291 | AG171: 1607960 | AH171: 1585354 | AI171: 1395908 | AJ171: 1483366 | AK171: 1549817 | AL171: 1724137 | AM171: 1613320 | AN171: 1651719 | AO171: 1539947 | AP171: 1370996 | AQ171: 1106863 | AR171: 1144979 | AS171: 1078277 | AT171: 932752 | AU171: 1029422 | AV171: 993476 | AW171: 957648 | AX171: 940252 | AY171: 1008411 | AZ171: 988601 | BA171: 916982 | BB171: 838039 | BC171: 835536
A172: 2021F | B172: US | C172: OPSCB | D172: 834813 | E172: 885547 | F172: 975363 | G172: 1043542 | H172: 1084533 | I172: 1019367 | J172: 1324193 | K172: 1576596 | L172: 1727692 | M172: 1865110 | N172: 1888876 | O172: 1599058 | P172: 1227071 | Q172: 1201419 | R172: 1195164 | S172: 1150193 | T172: 1248795 | U172: 1218050 | V172: 1253240 | W172: 1228024 | X172: 1379950 | Y172: 1401983 | Z172: 1433529 | AA172: 1433997 | AB172: 1464470 | AC172: 1382515 | AD172: 1421195 | AE172: 1611378 | AF172: 1671291 | AG172: 1607960 | AH172: 1585354 | AI172: 1395908 | AJ172: 1483366 | AK172: 1549817 | AL172: 1724137 | AM172: 1613320 | AN172: 1651719 | AO172: 1539947 | AP172: 1370996 | AQ172: 1106863 | AR172: 1144979 | AS172: 1078277 | AT172: 932752 | AU172: 1029422 | AV172: 993476 | AW172: 957648 | AX172: 940252 | AY172: 1008411 | AZ172: 988601 | BA172: 916982 | BB172: 838039 | BC172: 835536
A173: 2021F | B173: US | C173: OPTCD | D173: 1.16 | E173: 1.18 | F173: 1.19 | G173: 1.35 | H173: 2.43 | I173: 2.89 | J173: 3.15 | K173: 3.45 | L173: 3.56 | M173: 4.98 | N173: 7.58 | O173: 9.33 | P173: 8.52 | Q173: 8.01 | R173: 8.06 | S173: 7.76 | T173: 4.92 | U173: 5.79 | V173: 4.84 | W173: 5.67 | X173: 6.48 | Y173: 5.73 | Z173: 5.78 | AA173: 5.18 | AB173: 5.03 | AC173: 5.44 | AD173: 6.32 | AE173: 5.8 | AF173: 4.09 | AG173: 5.49 | AH173: 8.02 | AI173: 6.75 | AJ173: 6.9 | AK173: 7.94 | AL173: 9.93 | AM173: 13.41 | AN173: 16.22 | AO173: 18.35 | AP173: 25.42 | AQ173: 15.92 | AR173: 20.52 | AS173: 27.05 | AT173: 26.76 | AU173: 26.73 | AV173: 24.99 | AW173: 13.98 | AX173: 11.92 | AY173: 14.47 | AZ173: 17.9 | BA173: 16.68 | BB173: 11.66 | BC173: 19.07
A174: 2021F | B174: US | C174: OPTCV | D174: 967.6 | E174: 1043.6 | F174: 1155.8 | G174: 1413.7 | H174: 2640 | I174: 2946.3 | J174: 4176.3 | K174: 5431.7 | L174: 6142.3 | M174: 9286 | N174: 14324.2 | O174: 14924.1 | P174: 10451 | Q174: 9618.4 | R174: 9632 | S174: 8924.5 | T174: 6139.4 | U174: 7051.7 | V174: 6060.7 | W174: 6966.2 | X174: 8947 | Y174: 8029.8 | Z174: 8282.3 | AA174: 7422.9 | AB174: 7372.3 | AC174: 7516.8 | AD174: 8986.5 | AE174: 9347.7 | AF174: 6838.7 | AG174: 8820.1 | AH174: 12715.9 | AI174: 9419.4 | AJ174: 10230.1 | AK174: 12305.1 | AL174: 17127.4 | AM174: 21627.1 | AN174: 26794.2 | AO174: 28253.6 | AP174: 34845.8 | AQ174: 17624.1 | AR174: 23497.7 | AS174: 29164 | AT174: 24959.5 | AU174: 27521 | AV174: 24825.6 | AW174: 13389.9 | AX174: 11211.9 | AY174: 14586.8 | AZ174: 17698.8 | BA174: 15299.1 | BB174: 9767.9 | BC174: 15931.1
A175: 2021F | B175: US | C175: OPTXD | D175: 1.16 | E175: 1.18 | F175: 1.19 | G175: 1.35 | H175: 2.43 | I175: 2.89 | J175: 3.15 | K175: 3.45 | L175: 3.56 | M175: 4.98 | N175: 7.58 | O175: 9.33 | P175: 8.52 | Q175: 8.01 | R175: 8.06 | S175: 7.76 | T175: 4.92 | U175: 5.79 | V175: 4.84 | W175: 5.67 | X175: 6.48 | Y175: 5.73 | Z175: 5.78 | AA175: 5.18 | AB175: 5.03 | AC175: 5.44 | AD175: 6.32 | AE175: 5.8 | AF175: 4.09 | AG175: 5.49 | AH175: 8.02 | AI175: 6.75 | AJ175: 6.9 | AK175: 7.94 | AL175: 9.93 | AM175: 13.41 | AN175: 16.22 | AO175: 18.35 | AP175: 25.42 | AQ175: 15.92 | AR175: 20.52 | AS175: 27.05 | AT175: 26.76 | AU175: 26.73 | AV175: 24.99 | AW175: 13.98 | AX175: 11.92 | AY175: 14.47 | AZ175: 17.9 | BA175: 16.68 | BB175: 11.66 | BC175: 19.07
A176: 2021F | B176: US | C176: OPTXV | D176: 967.6 | E176: 1043.6 | F176: 1155.8 | G176: 1413.7 | H176: 2640 | I176: 2946.3 | J176: 4176.3 | K176: 5431.7 | L176: 6142.3 | M176: 9286 | N176: 14324.2 | O176: 14924.1 | P176: 10451 | Q176: 9618.4 | R176: 9632 | S176: 8924.5 | T176: 6139.4 | U176: 7051.7 | V176: 6060.7 | W176: 6966.2 | X176: 8947 | Y176: 8029.8 | Z176: 8282.3 | AA176: 7422.9 | AB176: 7372.3 | AC176: 7516.8 | AD176: 8986.5 | AE176: 9347.7 | AF176: 6838.7 | AG176: 8820.1 | AH176: 12715.9 | AI176: 9419.4 | AJ176: 10230.1 | AK176: 12305.1 | AL176: 17127.4 | AM176: 21627.1 | AN176: 26794.2 | AO176: 28253.6 | AP176: 34845.8 | AQ176: 17624.1 | AR176: 23497.7 | AS176: 29164 | AT176: 24959.5 | AU176: 27521 | AV176: 24825.6 | AW176: 13389.9 | AX176: 11211.9 | AY176: 14586.8 | AZ176: 17698.8 | BA176: 15299.1 | BB176: 9767.9 | BC176: 15931.1
A177: 2021F | B177: US | C177: P1ICD | D177: 1.13 | E177: 1.2 | F177: 1.24 | G177: 1.33 | H177: 2.31 | I177: 2.64 | J177: 2.81 | K177: 3.03 | L177: 3.19 | M177: 4.36 | N177: 6.59 | O177: 8.08 | P177: 7.17 | Q177: 7 | R177: 7.04 | S177: 6.9 | T177: 5.32 | U177: 5.31 | V177: 4.85 | W177: 5.18 | X177: 5.64 | Y177: 5.43 | Z177: 5.08 | AA177: 5.02 | AB177: 4.93 | AC177: 5.21 | AD177: 5.64 | AE177: 5.57 | AF177: 4.54 | AG177: 5.15 | AH177: 6.83 | AI177: 6.09 | AJ177: 6.34 | AK177: 7.14 | AL177: 8.1 | AM177: 10.2 | AN177: 12.49 | AO177: 13.96 | AP177: 18.26 | AQ177: 15.08 | AR177: 18.78 | AS177: 23.39 | AT177: 23.13 | AU177: 23.57 | AV177: 23.06 | AW177: 16.54 | AX177: 13.94 | AY177: 15.32 | AZ177: 18.56 | BA177: 18.26 | BB177: 15.36 | BC177: 19.61
A178: 2021F | B178: US | C178: P1ICV | D178: 2697.6 | E178: 2953.7 | F178: 3227.4 | G178: 3759.4 | H178: 6225.9 | I178: 6470 | J178: 7738 | K178: 9521.8 | L178: 10839.3 | M178: 15306.1 | N178: 21837.3 | O178: 23572 | P178: 18119.1 | Q178: 17022.3 | R178: 17880 | S178: 17396 | T178: 14117.7 | U178: 14603.9 | V178: 13530.5 | W178: 14085.2 | X178: 16798 | Y178: 15552 | Z178: 15250.4 | AA178: 14882.2 | AB178: 15043.4 | AC178: 15446.2 | AD178: 17038.5 | AE178: 18030.7 | AF178: 15760.9 | AG178: 18222.2 | AH178: 22692.3 | AI178: 19349.4 | AJ178: 20406.6 | AK178: 23112.7 | AL178: 29029.3 | AM178: 35366.1 | AN178: 43321.5 | AO178: 45611.6 | AP178: 52809.9 | AQ178: 36279.6 | AR178: 43931.1 | AS178: 51533.6 | AT178: 47685.4 | AU178: 48780.8 | AV178: 46939.1 | AW178: 34366.1 | AX178: 28471.8 | AY178: 31605.9 | AZ178: 37102.5 | BA178: 36029.2 | BB178: 28322.3 | BC178: 37478.7
A179: 2021F | B179: US | C179: P1ISB | D179: 2388985 | E179: 2459232 | F179: 2609971 | G179: 2816333 | H179: 2695244 | I179: 2452251 | J179: 2750288 | K179: 3143326 | L179: 3393541 | M179: 3513193 | N179: 3312505 | O179: 2916658 | P179: 2526485 | Q179: 2430081 | R179: 2538517 | S179: 2519528 | T179: 2652616 | U179: 2747767 | V179: 2791935 | W179: 2720684 | X179: 2979767 | Y179: 2863624 | Z179: 3003747 | AA179: 2963035 | AB179: 3052585 | AC179: 2966421 | AD179: 3018496 | AE179: 3239533 | AF179: 3470896 | AG179: 3535458 | AH179: 3323295 | AI179: 3174942 | AJ179: 3219603 | AK179: 3235901 | AL179: 3585101 | AM179: 3467186 | AN179: 3467779 | AO179: 3268224 | AP179: 2892379 | AQ179: 2405248 | AR179: 2338793 | AS179: 2203573 | AT179: 2061195 | AU179: 2069339 | AV179: 2035580 | AW179: 2077253 | AX179: 2043051 | AY179: 2062675 | AZ179: 1998598 | BA179: 1973440 | BB179: 1844134 | BC179: 1910979
A180: 2021F | B180: US | C180: P1SCB | D180: 3014799 | E180: 3065521 | F180: 3198338 | G180: 3370196 | H180: 3190796 | I180: 2889926 | J180: 3220015 | K180: 3607848 | L180: 3869034 | M180: 3995926 | N180: 3701378 | O180: 3296643 | P180: 2853699 | Q180: 2839711 | R180: 2953961 | S180: 2924588 | T180: 3045144 | U180: 3144166 | V180: 3189642 | W180: 3099731 | X180: 3306857 | Y180: 3176557 | Z180: 3326536 | AA180: 3333345 | AB180: 3415804 | AC180: 3350994 | AD180: 3408306 | AE180: 3670596 | AF180: 3949753 | AG180: 4007446 | AH180: 3761977 | AI180: 3604118 | AJ180: 3667024 | AK180: 3680196 | AL180: 4084769 | AM180: 3990650 | AN180: 3933486 | AO180: 3668045 | AP180: 3234368 | AQ180: 2722877 | AR180: 2691480 | AS180: 2539225 | AT180: 2316075 | AU180: 2367203 | AV180: 2341107 | AW180: 2384932 | AX180: 2352207 | AY180: 2332912 | AZ180: 2269395 | BA180: 2216875 | BB180: 2080018 | BC180: 2150546
... A233: 2021F | B233: US | C233: PETXV | D233: 59530.1 | E233: 63836 | F233: 68357.8 | G233: 78120.2 | H233: 110782.5 | I233: 121173.8 | J233: 136943.4 | K233: 154274.1 | L233: 165121 | M233: 215523.4 | N233: 276255 | O233: 311446.3 | P233: 299088.8 | Q233: 282890.6 | R233: 292892.5 | S233: 289110.6 | T233: 232298.1 | U233: 242941.8 | V233: 249505.3 | W233: 269718.9 | X233: 297961.3 | Y233: 287672.4 | Z233: 289939.4 | AA233: 295743 | AB233: 304025 | AC233: 308747.1 | AD233: 349187.5 | AE233: 354118.4 | AF233: 307921.2 | AG233: 340213.9 | AH233: 456133.4 | AI233: 450759.4 | AJ233: 416366.2 | AK233: 497078 | AL233: 603077 | AM233: 749943.4 | AN233: 834858.1 | AO233: 892944 | AP233: 1048305.4 | AQ233: 716093.4 | AR233: 848364.8 | AS233: 1024458.5 | AT233: 994311.8 | AU233: 1004334.1 | AV233: 1005558.3 | AW233: 740103.2 | AX233: 655316.8 | AY233: 749157.3 | AZ233: 868581.6 | BA233: 825210.3 | BB233: 616851.9 | BC233: 897794.4
A234: 2021F | B234: US | C234: PQACD | AR234: 25.8 | AS234: 29.52 | AT234: 22.57 | AU234: 23.03 | AV234: 24.56 | AW234: 14.9 | AX234: 14.53 | AY234: 19.11 | AZ234: 20.32 | BA234: 17.08 | BB234: 15.81 | BC234: 24.64
A235: 2021F | B235: US | C235: PQACV | AR235: 118 | AS235: 135.8 | AT235: 102 | AU235: 140.3 | AV235: 187.1 | AW235: 148.9 | AX235: 171.7 | AY235: 236.8 | AZ235: 256.4 | BA235: 213.3 | BB235: 136.7 | BC235: 240.6
A236: 2021F | B236: US | C236: PQCCD | AR236: 21.62 | AS236: 25.3 | AT236: 19.5 | AU236: 19.7 | AV236: 21.3 | AW236: 12.66 | AX236: 12.04 | AY236: 15.76 | AZ236: 16.8 | BA236: 13.59 | BB236: 12.35 | BC236: 19.77
A237: 2021F | B237: US | C237: PQCCV | AR237: 3027.1 | AS237: 3605.3 | AT237: 2643.1 | AU237: 2986.2 | AV237: 3417.7 | AW237: 1874.6 | AX237: 1806 | AY237: 2453.7 | AZ237: 2956.4 | BA237: 2474.3 | BB237: 2483.1 | BC237: 4289.6
A238: 2021F | B238: US | C238: PQICD | AR238: 17.44 | AS238: 21.09 | AT238: 14.78 | AU238: 14.61 | AV238: 16.39 | AW238: 8.01 | AX238: 7.76 | AY238: 11.5 | AZ238: 12.72 | BA238: 9.39 | BB238: 8.05 | BC238: 15.77
A239: 2021F | B239: US | C239: PQICV | AR239: 8899.5 | AS239: 11578.3 | AT239: 9912.4 | AU239: 10689.7 | AV239: 9058.3 | AW239: 4781.2 | AX239: 4419.1 | AY239: 5941.8 | AZ239: 6875.1 | BA239: 4230.8 | BB239: 3589.9 | BC239: 7024.1
A240: 2021F | B240: US | C240: PQISB | AR240: 510290 | AS240: 549018 | AT240: 670892 | AU240: 731718 | AV240: 552740 | AW240: 597088 | AX240: 569787 | AY240: 516473 | AZ240: 540573 | BA240: 450604 | BB240: 445824 | BC240: 445515
A241: 2021F | B241: US | C241: PQRCD | AR241: 25.65 | AS241: 28.25 | AT241: 25.91 | AU241: 25.3 | AV241: 30.05 | AW241: 22.75 | AX241: 21.56 | AY241: 25.15 | AZ241: 25.93 | BA241: 22.72 | BB241: 20.59 | BC241: 26.81
A242: 2021F | B242: US | C242: PQRCV | AR242: 13589.5 | AS242: 13914.7 | AT242: 10250.7 | AU242: 11725.8 | AV242: 14707.7 | AW242: 10141.7 | AX242: 9267.8 | AY242: 10830.2 | AZ242: 13134 | BA242: 12801.6 | BB242: 10189.1 | BC242: 12981.4
A243: 2021F | B243: US | C243: PQRFB | AR243: 9234 | AS243: 4959 | AT243: 5842 | AU243: 5032 | AV243: 8857 | AW243: 11546 | AX243: 9591 | AY243: 10259 | AZ243: 9007 | BA243: 8362 | BB243: 7824 | BC243: 5477
A244: 2021F | B244: US | C244: PQSCB | AR244: 1184710 | AS244: 1188740 | AT244: 1206493 | AU244: 1352900 | AV244: 1210357 | AW244: 1200820 | AX244: 1161507 | AY244: 1115242 | AZ244: 1235700 | BA244: 1208528 | BB244: 1150449 | BC244: 1156379
A245: 2021F | B245: US | C245: PQTCD | AR245: 21.64 | AS245: 24.59 | AT245: 18.99 | AU245: 18.88 | AV245: 22.61 | AW245: 14.11 | AX245: 13.49 | AY245: 17.45 | AZ245: 18.79 | BA245: 16.32 | BB245: 14.25 | BC245: 21.22
... A248: 2021F | B248: US | C248: PQTXV | AR248: 25634.1 | AS248: 29234.2 | AT248: 22908.2 | AU248: 25542 | AV248: 27370.9 | AW248: 16946.4 | AX248: 15664.7 | AY248: 19462.4 | AZ248: 23221.9 | BA248: 19720.1 | BB248: 16398.9 | BC248: 24535.7
A249: 2021F | B249: US | C249: RFACD | D249: 0.38 | E249: 0.52 | F249: 0.58 | G249: 0.66 | H249: 1.58 | I249: 1.72 | J249: 1.71 | K249: 1.87 | L249: 1.82 | M249: 2.47 | N249: 3.31 | O249: 4.44 | P249: 4.54 | Q249: 4.42 | R249: 4.6 | S249: 4.36 | T249: 2.11 | U249: 2.64 | V249: 2.22 | W249: 2.47 | X249: 2.98 | Y249: 2.83 | Z249: 1.98 | AA249: 1.98 | AB249: 2.06 | AC249: 2.18 | AD249: 2.33 | AE249: 2.95 | AF249: 2.18 | AG249: 2.61 | AH249: 4.54 | AI249: 4.38 | AJ249: 4.01 | AK249: 5.06 | AL249: 5.26 | AM249: 6.22 | AN249: 7.73 | AO249: 8.19 | AP249: 12.28 | AQ249: 9.89 | AR249: 11.55 | AS249: 15.12 | AT249: 16.85 | AU249: 16.01 | AV249: 14.4 | AW249: 8.85 | AX249: 6.64 | AY249: 8.76 | AZ249: 11.78 | BA249: 11.26 | BB249: 7.77 | BC249: 11.88
A250: 2021F | B250: US | C250: RFACV | D250: 291.2 | E250: 361.6 | F250: 375.3 | G250: 483.3 | H250: 1102.1 | I250: 1225.9 | J250: 1410.6 | K250: 1702.9 | L250: 1802 | M250: 3027.7 | N250: 4626.3 | O250: 5411.1 | P250: 4629.6 | Q250: 3632 | R250: 3714.4 | S250: 3422.1 | T250: 1838.1 | U250: 2373.1 | V250: 2042.1 | W250: 2398.9 | X250: 3025.2 | Y250: 2905.2 | Z250: 2121.5 | AA250: 1782.8 | AB250: 1821 | AC250: 1987.6 | AD250: 1986.6 | AE250: 2096.5 | AF250: 1468.6 | AG250: 1737.1 | AH250: 4029.5 | AI250: 2562.1 | AJ250: 2712.4 | AK250: 2887.2 | AL250: 3886.3 | AM250: 5208.3 | AN250: 7001.7 | AO250: 8134.9 | AP250: 11366.1 | AQ250: 7818.8 | AR250: 10300 | AS250: 11737.3 | AT250: 11299.3 | AU250: 9306.4 | AV250: 6428.8 | AW250: 4103.2 | AX250: 4138.5 | AY250: 5821.4 | AZ250: 7114.4 | BA250: 5955.6 | BB250: 3042.9 | BC250: 7306.8
A251: 2021F | B251: US | C251: RFCCD | D251: 0.45 | E251: 0.61 | F251: 0.65 | G251: 0.78 | H251: 1.89 | I251: 1.91 | J251: 1.87 | K251: 2.2 | L251: 2.06 | M251: 3.01 | N251: 4.12 | O251: 5.12 | P251: 4.67 | Q251: 4.51 | R251: 4.94 | S251: 4.5 | T251: 2.71 | U251: 3.1 | V251: 2.53 | W251: 2.92 | X251: 3.41 | Y251: 2.61 | Z251: 2.68 | AA251: 2.75 | AB251: 2.9 | AC251: 3.14 | AD251: 3.75 | AE251: 3.27 | AF251: 2.38 | AG251: 2.69 | AH251: 4.49 | AI251: 4.06 | AJ251: 4.08 | AK251: 5.3 | AL251: 5.26 | AM251: 7.48 | AN251: 8.69 | AO251: 9.71 | AP251: 13.18 | AQ251: 9.9 | AR251: 12.9 | AS251: 17.34 | AT251: 18.4 | AU251: 17.41 | AV251: 15.79 | AW251: 8.86 | AX251: 6.8 | AY251: 8.94 | AZ251: 11.63 | BA251: 11.4 | BB251: 8.85 | BC251: 13.11
A252: 2021F | B252: US | C252: RFCCV | D252: 323.2 | E252: 409.1 | F252: 421.9 | G252: 519.2 | H252: 1119.6 | I252: 939.1 | J252: 1062.4 | K252: 1295.7 | L252: 1097.8 | M252: 1517.6 | N252: 2325.3 | O252: 2138.3 | P252: 1861.7 | Q252: 939.3 | R252: 1311.2 | S252: 1024.6 | T252: 785.7 | U252: 813.8 | V252: 666.5 | W252: 666.2 | X252: 784.6 | Y252: 553.8 | Z252: 506.3 | AA252: 474.8 | AB252: 497.9 | AC252: 444.9 | AD252: 515 | AE252: 363.2 | AF252: 202.6 | AG252: 197.4 | AH252: 411.2 | AI252: 283.8 | AJ252: 325.6 | AK252: 588.6 | AL252: 643.9 | AM252: 866.3 | AN252: 653.7 | AO252: 731.6 | AP252: 935.6 | AQ252: 705.3 | AR252: 795.5 | AS252: 931.9 | AT252: 577.5 | AU252: 425 | AV252: 125.3 | AW252: 35.2 | AX252: 30.2 | AY252: 34.2 | AZ252: 36.1 | BA252: 26.6 | BB252: 20.7 | BC252: 41.5
A253: 2021F | B253: US | C253: RFEID | D253: 0.41 | E253: 0.57 | F253: 0.64 | G253: 0.78 | H253: 1.87 | I253: 1.99 | J253: 1.95 | K253: 2.19 | L253: 2.13 | M253: 2.98 | N253: 4.25 | O253: 5.32 | P253: 4.83 | Q253: 4.6 | R253: 4.82 | S253: 4.24 | T253: 2.42 | U253: 2.97 | V253: 2.41 | W253: 2.85 | X253: 3.3 | Y253: 2.46 | Z253: 2.48 | AA253: 2.37 | AB253: 2.4 | AC253: 2.59 | AD253: 3.02 | AE253: 2.82 | AF253: 2.09 | AG253: 2.4 | AH253: 4.09 | AI253: 3.78 | AJ253: 3.79 | AK253: 4.47 | AL253: 4.58 | AM253: 6.86 | AN253: 8.12 | AO253: 8.98 | AP253: 13.48 | AQ253: 8.98 | AR253: 12.47 | AS253: 18.93 | AT253: 20.78 | AU253: 19.56 | AV253: 17.59 | AW253: 9.37 | AX253: 8.04 | AY253: 10.26 | AZ253: 12.64 | BA253: 12.18 | BB253: 8.97 | BC253: 13.48
A254: 2021F | B254: US | C254: RFEIV | D254: 797 | E254: 1299.8 | F254: 1758.9 | G254: 2507.8 | H254: 5681.3 | I254: 5842.1 | J254: 6289 | K254: 7925.6 | L254: 7882.2 | M254: 9243.6 | N254: 10445.7 | O254: 11032.3 | P254: 7115.9 | Q254: 6619.8 | R254: 5736.9 | S254: 4231.5 | T254: 3287.7 | U254: 3439.1 | V254: 3467.7 | W254: 4367.9 | X254: 3841.5 | Y254: 2672.1 | Z254: 2163.8 | AA254: 2275.3 | AB254: 2083.5 | AC254: 1465.4 | AD254: 1898.7 | AE254: 2014 | AF254: 2183.8 | AG254: 2303.9 | AH254: 3561.7 | AI254: 3791.8 | AJ254: 2499.2 | AK254: 3883.8 | AL254: 4023.2 | AM254: 6009.7 | AN254: 2927.4 | AO254: 3562.4 | AP254: 3239.7 | AQ254: 1625.7 | AR254: 1921.4 | AS254: 1761.3 | AT254: 1594.3 | AU254: 1510.2 | AV254: 1673.3 | AW254: 879.6 | AX254: 568.5 | AY254: 674.7 | AZ254: 989.4 | BA254: 716.1 | BB254: 472.7 | BC254: 772.4
A255: 2021F | B255: US | C255: RFICD | D255: 0.46 | E255: 0.62 | F255: 0.6 | G255: 0.73 | H255: 1.82 | I255: 1.91 | J255: 1.9 | K255: 2.15 | L255: 2.12 | M255: 2.76 | N255: 3.69 | O255: 4.48 | P255: 4.46 | Q255: 4.38 | R255: 4.73 | S255: 4.24 | T255: 2.47 | U255: 2.86 | V255: 2.34 | W255: 2.75 | X255: 3.1 | Y255: 2.44 | Z255: 2.46 | AA255: 2.41 | AB255: 2.5 | AC255: 2.75 | AD255: 3.25 | AE255: 3.03 | AF255: 2.25 | AG255: 2.62 | AH255: 4.22 | AI255: 3.85 | AJ255: 3.87 | AK255: 4.83 | AL255: 4.95 | AM255: 6.98 | AN255: 8.16 | AO255: 9.26 | AP255: 12.97 | AQ255: 9.25 | AR255: 11.94 | AS255: 16.02 | AT255: 17.48 | AU255: 17.4 | AV255: 16.41 | AW255: 9.87 | AX255: 7.39 | AY255: 9.81 | AZ255: 11.17 | BA255: 11.12 | BB255: 8.23 | BC255: 12.41
A256: 2021F | B256: US | C256: RFICV | D256: 634.8 | E256: 863 | F256: 901.5 | G256: 1156.5 | H256: 2644.5 | I256: 2367.4 | J256: 2885.9 | K256: 3456.5 | L256: 2965.4 | M256: 3866.6 | N256: 4175.5 | O256: 4086.2 | P256: 4024.7 | Q256: 2907.6 | R256: 3647.2 | S256: 2814.9 | T256: 1574.1 | U256: 1436.2 | V256: 1082.3 | W256: 923.9 | X256: 1069.6 | Y256: 652.9 | Z256: 793.1 | AA256: 916.1 | AB256: 893.5 | AC256: 778.2 | AD256: 912.6 | AE256: 732.4 | AF256: 425.3 | AG256: 447.1 | AH256: 867.2 | AI256: 628.7 | AJ256: 619 | AK256: 965.6 | AL256: 1163.1 | AM256: 1867.1 | AN256: 1849.1 | AO256: 1699.9 | AP256: 2407.7 | AQ256: 1134.3 | AR256: 1365 | AS256: 2086.1 | AT256: 1163.8 | AU256: 792.7 | AV256: 634 | AW256: 309.8 | AX256: 374.9 | AY256: 474.6 | AZ256: 465.9 | BA256: 453 | BB256: 261.5 | BC256: 566.2
A257: 2021F | B257: US | C257: RFISB | D257: 1382428 | E257: 1402447 | F257: 1511266 | G257: 1580671 | H257: 1452170 | I257: 1240020 | J257: 1522173 | K257: 1609269 | L257: 1398663 | M257: 1400371 | N257: 1130731 | O257: 911521 | P257: 903270 | Q257: 663821 | R257: 770317 | S257: 663735 | T257: 637763 | U257: 501371 | V257: 462076 | W257: 335771 | X257: 344520 | Y257: 267276 | Z257: 322813 | AA257: 380147 | AB257: 358066 | AC257: 282630 | AD257: 280423 | AE257: 241500 | AF257: 188794 | AG257: 170619 | AH257: 205456 | AI257: 163449 | AJ257: 159841 | AK257: 200028 | AL257: 234888 | AM257: 267510 | AN257: 226580 | AO257: 183540 | AP257: 185609 | AQ257: 122681 | AR257: 114284 | AS257: 130237 | AT257: 66590 | AU257: 45568 | AV257: 38625 | AW257: 31386 | AX257: 50715 | AY257: 48377 | AZ257: 41722 | BA257: 40742 | BB257: 31764 | BC257: 45637
A258: 2021F | B258: US | C258: RFRFB | D258: 241515 | E258: 216040 | F258: 249921 | G258: 276905 | H258: 276119 | I258: 269128 | J258: 299783 | K258: 327339 | L258: 317185 | M258: 254850 | N258: 218454 | O258: 169680 | P258: 143293 | Q258: 127607 | R258: 118284 | S258: 83781 | T258: 98637 | U258: 80222 | V258: 83623 | W258: 73765 | X258: 66925 | Y258: 66623 | Z258: 64102 | AA258: 65762 | AB258: 60858 | AC258: 54100 | AD258: 54810 | AE258: 49139 | AF258: 41048 | AG258: 36854 | AH258: 35182 | AI258: 39803 | AJ258: 30266 | AK258: 20414 | AL258: 13819 | AM258: 13875 | AN258: 12687 | AO258: 11593 | AP258: 8739 | AQ258: 7852 | AR258: 6161 | AS258: 4772 | AT258: 3395 | AU258: 2659 | AV258: 1955 | AW258: 2471 | AX258: 1697 | AY258: 1559 | AZ258: 1616 | BA258: 157 | BB258: 207 | BC258: 201
A259: 2021F | B259: US | C259: RFSCB | D259: 4815044 | E259: 5052749 | F259: 5569622 | G259: 6199818 | H259: 5779620 | I259: 5380195 | J259: 6145322 | K259: 6719929 | L259: 6618840 | M259: 6230549 | N259: 5553175 | O259: 4621203 | P259: 3795575 | Q259: 3132856 | R259: 3032754 | S259: 2675207 | T259: 3156250 | U259: 2821254 | V259: 3086754 | W259: 3070156 | X259: 2752926 | Y259: 2590414 | Z259: 2454036 | AA259: 2412963 | AB259: 2281596 | AC259: 1900598 | AD259: 1897310 | AE259: 1779089 | AF259: 1994676 | AG259: 1868094 | AH259: 2055415 | AI259: 1821646 | AJ259: 1575164 | AK259: 1751439 | AL259: 1975910 | AM259: 2097243 | AN259: 1568047 | AO259: 1649194 | AP259: 1422968 | AQ259: 1165432 | AR259: 1222005 | AS259: 1053369 | AT259: 845227 | AU259: 728349 | AV259: 588238 | AW259: 592619 | AX259: 748958 | AY259: 782581 | AZ259: 727110 | BA259: 630976 | BB259: 478258 | BC259: 720962
A260: 2021F | B260: US | C260: RFTCD | D260: 0.42 | E260: 0.58 | F260: 0.62 | G260: 0.75 | H260: 1.82 | I260: 1.93 | J260: 1.9 | K260: 2.14 | L260: 2.08 | M260: 2.83 | N260: 3.88 | O260: 4.91 | P260: 4.65 | Q260: 4.5 | R260: 4.75 | S260: 4.3 | T260: 2.37 | U260: 2.86 | V260: 2.35 | W260: 2.72 | X260: 3.17 | Y260: 2.62 | Z260: 2.28 | AA260: 2.26 | AB260: 2.32 | AC260: 2.46 | AD260: 2.8 | AE260: 2.93 | AF260: 2.15 | AG260: 2.51 | AH260: 4.32 | AI260: 3.99 | AJ260: 3.91 | AK260: 4.75 | AL260: 4.92 | AM260: 6.65 | AN260: 7.93 | AO260: 8.57 | AP260: 12.61 | AQ260: 9.68 | AR260: 11.77 | AS260: 15.68 | AT260: 17.31 | AU260: 16.52 | AV260: 15.06 | AW260: 8.99 | AX260: 6.83 | AY260: 8.95 | AZ260: 11.84 | BA260: 11.33 | BB260: 7.94 | BC260: 12.05
... A269: 2021F | B269: US | C269: TECCV | D269: 10677.7 | E269: 12021.3 | F269: 13463.6 | G269: 15149.4 | H269: 19578.7 | I269: 22955.5 | J269: 26446.6 | K269: 30725.4 | L269: 33562.8 | M269: 38943.7 | N269: 47074.3 | O269: 55629 | P269: 61502.7 | Q269: 65027.8 | R269: 69588 | S269: 70719.3 | T269: 68633.1 | U269: 69095.6 | V269: 71965.8 | W269: 75907 | X269: 79602.2 | Y269: 82095.7 | Z269: 83004.3 | AA269: 87093.4 | AB269: 90007.4 | AC269: 92103.6 | AD269: 96411.1 | AE269: 100756.1 | AF269: 99489.7 | AG269: 99678.8 | AH269: 113420.5 | AI269: 125787.8 | AJ269: 120161.7 | AK269: 130239.6 | AL269: 138688.1 | AM269: 155156.7 | AN269: 167625.9 | AO269: 174792.6 | AP269: 191543.2 | AQ269: 174680.8 | AR269: 177662 | AS269: 180474.3 | AT269: 171694.7 | AU269: 178184.2 | AV269: 190719.7 | AW269: 185970.5 | AX269: 178884.5 | AY269: 184766.4 | AZ269: 193092 | BA269: 189355.4 | BB269: 173890.8 | BC269: 199002.2
A270: 2021F | B270: US | C270: TEGDS | AE270: 6.62 | AF270: 5.81 | AG270: 5.8 | AH270: 6.71 | AI270: 6.58 | AJ270: 6.08 | AK270: 6.59 | AL270: 7.13 | AM270: 8.02 | AN270: 8.39 | AO270: 8.52 | AP270: 9.54 | AQ270: 7.37 | AR270: 8.07 | AS270: 8.93 | AT270: 8.34 | AU270: 8.17 | AV270: 7.95 | AW270: 6.2 | AX270: 5.56 | AY270: 5.83 | AZ270: 6.19 | BA270: 5.72 | BB270: 4.79 | BC270: 5.65
A271: 2021F | B271: US | C271: TEICD | D271: 0.84 | E271: 0.93 | F271: 0.99 | G271: 1.1 | H271: 1.78 | I271: 2.21 | J271: 2.44 | K271: 2.79 | L271: 3.05 | M271: 3.64 | N271: 4.72 | O271: 5.53 | P271: 6.08 | Q271: 6.24 | R271: 6.15 | S271: 6.06 | T271: 5.39 | U271: 5.21 | V271: 5.05 | W271: 4.97 | X271: 5.3 | Y271: 5.25 | Z271: 5.18 | AA271: 5.21 | AB271: 5.19 | AC271: 5.01 | AD271: 5.44 | AE271: 5.39 | AF271: 4.94 | AG271: 5.2 | AH271: 6.5 | AI271: 6.96 | AJ271: 6.37 | AK271: 7.53 | AL271: 8.51 | AM271: 10.42 | AN271: 11.42 | AO271: 11.98 | AP271: 14.51 | AQ271: 11.37 | AR271: 12.14 | AS271: 13.67 | AT271: 12.42 | AU271: 12.52 | AV271: 12.72 | AW271: 9.88 | AX271: 9.01 | AY271: 9.95 | AZ271: 10.66 | BA271: 9.91 | BB271: 8.73 | BC271: 11.61
A272: 2021F | B272: US | C272: TEICV | D272: 16705.5 | E272: 18258.6 | F272: 20294.1 | G272: 23795.4 | H272: 36852.9 | I272: 41127.4 | J272: 47904.2 | K272: 56015.9 | L272: 61732.1 | M272: 77653.2 | N272: 94316 | O272: 108580.5 | P272: 103502.8 | Q272: 102292.6 | R272: 110343.1 | S272: 106436.3 | T272: 91870.7 | U272: 91650.3 | V272: 92876.6 | W272: 96319.9 | X272: 103350.5 | Y272: 101885.7 | Z272: 104228.1 | AA272: 105395.8 | AB272: 108319.4 | AC272: 107352.7 | AD272: 118807.2 | AE272: 119989.7 | AF272: 107989.1 | AG272: 112959.7 | AH272: 140963.3 | AI272: 141013.2 | AJ272: 130535.2 | AK272: 151516.8 | AL272: 177117.2 | AM272: 208224.7 | AN272: 227840.3 | AO272: 236209 | AP272: 274021.7 | AQ272: 188034.1 | AR272: 221657.1 | AS272: 251301.4 | AT272: 230283.7 | AU272: 236901.2 | AV272: 242647.4 | AW272: 186824.9 | AX272: 169703 | AY272: 190546.6 | AZ272: 213534.9 | BA272: 197828.3 | BB272: 167111.2 | BC272: 231772.1
A273: 2021F | B273: US | C273: TEPFB | D273: 17520251 | E273: 18134160 | F273: 19349367 | G273: 20372781 | H273: 20477976 | I273: 20392275 | J273: 21638416 | K273: 22586798 | L273: 23436080 | M273: 23775038 | N273: 23896049 | O273: 23042198 | P273: 22778717 | Q273: 23318451 | R273: 24164666 | S273: 24211142 | T273: 24246372 | U273: 25063377 | V273: 26345524 | W273: 26957255 | X273: 27317862 | Y273: 27189427 | Z273: 27398454 | AA273: 28033102 | AB273: 28510393 | AC273: 29140972 | AD273: 30225533 | AE273: 30425280 | AF273: 31007375 | AG273: 31499785 | AH273: 32173596 | AI273: 31507273 | AJ273: 31871233 | AK273: 31887051 | AL273: 32558324 | AM273: 32994280 | AN273: 32832057 | AO273: 33682162 | AP273: 33389276 | AQ273: 32265303 | AR273: 33437058 | AS273: 33279222 | AT273: 32392761 | AU273: 32904672 | AV273: 32923948 | AW273: 32237909 | AX273: 32264146 | AY273: 32093760 | AZ273: 32906010 | BA273: 32256771 | BB273: 30920333 | BC273: 31965785
A274: 2021F | B274: US | C274: TERCD | D274: 2.1 | E274: 2.23 | F274: 2.37 | G274: 2.71 | H274: 3.38 | I274: 3.8 | J274: 4.13 | K274: 4.76 | L274: 5.13 | M274: 5.99 | N274: 7.46 | O274: 8.82 | P274: 9.77 | Q274: 10.66 | R274: 10.66 | S274: 10.91 | T274: 10.75 | U274: 10.71 | V274: 10.66 | W274: 11.02 | X274: 11.87 | Y274: 12.08 | Z274: 11.97 | AA274: 12.27 | AB274: 12.6 | AC274: 12.6 | AD274: 12.69 | AE274: 13.25 | AF274: 13.44 | AG274: 13.15 | AH274: 14.21 | AI274: 15.62 | AJ274: 14.65 | AK274: 15.79 | AL274: 17.02 | AM274: 19.16 | AN274: 21.49 | AO274: 21.57 | AP274: 23.08 | AQ274: 22.04 | AR274: 22.37 | AS274: 22.81 | AT274: 23.39 | AU274: 22.59 | AV274: 23.35 | AW274: 22.93 | AX274: 22.92 | AY274: 23.77 | AZ274: 23.29 | BA274: 23.13 | BB274: 23.8 | BC274: 25.45
A275: 2021F | B275: US | C275: TERCV | D275: 20112.2 | E275: 21933.6 | F275: 24094.7 | G275: 27031.4 | H275: 32461.3 | I275: 36838 | J275: 41685.2 | K275: 47597.6 | L275: 51857.3 | M275: 58151.5 | N275: 69279.7 | O275: 78489.1 | P275: 87508.9 | Q275: 92815.8 | R275: 97660.3 | S275: 99623.2 | T275: 97176.2 | U275: 98638.4 | V275: 103911.1 | W275: 109558.2 | X275: 110909.5 | Y275: 116004.4 | Z275: 116398.5 | AA275: 125145.6 | AB275: 126961.9 | AC275: 127961.5 | AD275: 137340 | AE275: 138201.4 | AF275: 134601.7 | AG275: 136998.8 | AH275: 155299 | AI275: 167241.2 | AJ275: 160542.3 | AK275: 178657.6 | AL275: 189080.2 | AM275: 215185.6 | AN275: 225243.8 | AO275: 237944.5 | AP275: 259660.8 | AQ275: 240767.2 | AR275: 249771.8 | AS275: 249191.2 | AT275: 234183.9 | AU275: 248460.1 | AV275: 264712 | AW275: 248044.7 | AX275: 238549.9 | AY275: 246109.7 | AZ275: 267012.8 | BA275: 264333.5 | BB275: 261258.4 | BC275: 282240.9
A276: 2021F | B276: US | C276: TERFB | D276: 2713964 | E276: 2692555 | F276: 2844741 | G276: 3008066 | H276: 2981001 | I276: 2881241 | J276: 2904796 | K276: 3005590 | L276: 2935416 | M276: 3076014 | N276: 3051098 | O276: 2203184 | P276: 2087040 | Q276: 2120226 | R276: 2253723 | S276: 2045220 | T276: 2284831 | U276: 2484861 | V276: 2695441 | W276: 2709564 | X276: 2802314 | Y276: 2667929 | Z276: 2953594 | AA276: 2877351 | AB276: 2991113 | AC276: 2915038 | AD276: 3203510 | AE276: 3196813 | AF276: 3042598 | AG276: 3051324 | AH276: 2950679 | AI276: 3152316 | AJ276: 3027656 | AK276: 3141474 | AL276: 3123427 | AM276: 3130067 | AN276: 3210548 | AO276: 3180363 | AP276: 2982797 | AQ276: 2922008 | AR276: 2972150 | AS276: 3052206 | AT276: 3104515 | AU276: 3175143 | AV276: 3070105 | AW276: 3056987 | AX276: 3242251 | AY276: 3289915 | AZ276: 3293488 | BA276: 3321477 | BB276: 3194886 | BC276: 3152787
A277: 2021F | B277: US | C277: TETCD | D277: 1.65 | E277: 1.76 | F277: 1.84 | G277: 2.02 | H277: 2.87 | I277: 3.33 | J277: 3.57 | K277: 3.98 | L277: 4.23 | M277: 5.22 | N277: 6.89 | O277: 8.04 | P277: 8.47 | Q277: 8.4 | R277: 8.3 | S277: 8.38 | T277: 7.32 | U277: 7.36 | V277: 7.29 | W277: 7.59 | X277: 8.29 | Y277: 8.25 | Z277: 8.16 | AA277: 8.29 | AB277: 8.33 | AC277: 8.31 | AD277: 8.77 | AE277: 8.83 | AF277: 8.22 | AG277: 8.58 | AH277: 10.33 | AI277: 10.78 | AJ277: 10.1 | AK277: 11.44 | AL277: 12.9 | AM277: 15.57 | AN277: 17.4 | AO277: 18.34 | AP277: 21.53 | AQ277: 17.26 | AR277: 18.92 | AS277: 21.87 | AT277: 21.84 | AU277: 21.42 | AV277: 21.33 | AW277: 17.31 | AX277: 15.95 | AY277: 17.32 | AZ277: 18.61 | BA277: 17.96 | BB277: 16.25 | BC277: 19.99
A278: 2021F | B278: US | C278: TETCV | D278: 82874.8 | E278: 90037.8 | F278: 98070.2 | G278: 111894.2 | H278: 153369 | I278: 171853.7 | J278: 193915.8 | K278: 220499.1 | L278: 239280.2 | M278: 297574.6 | N278: 374350 | O278: 427901.2 | P278: 426482 | Q278: 417621.5 | R278: 435312.9 | S278: 438343.1 | T278: 384090.9 | U278: 397626.6 | V278: 411568.4 | W278: 439051.3 | X278: 474652.2 | Y278: 472439.6 | Z278: 476845 | AA278: 492274.6 | AB278: 504856.4 | AC278: 514623.5 | AD278: 560292.9 | AE278: 567961.8 | AF278: 526282.6 | AG278: 558626.7 | AH278: 687710.9 | AI278: 696242.1 | AJ278: 663964.4 | AK278: 755070.3 | AL278: 871210.2 | AM278: 1045730.4 | AN278: 1158820.6 | AO278: 1233868.7 | AP278: 1408759.3 | AQ278: 1066528.4 | AR278: 1214277.5 | AS278: 1392467.9 | AT278: 1355174.7 | AU278: 1376402.2 | AV278: 1395430.4 | AW278: 1128447.4 | AX278: 1038883.6 | AY278: 1136379.4 | AZ278: 1271930.6 | BA278: 1223984.5 | BB278: 1007785.4 | BC278: 1317098.4
A279: 2021F | B279: US | C279: TETPV | D279: 404.2 | E279: 433.6 | F279: 467.2 | G279: 528 | H279: 717.2 | I279: 795.7 | J279: 889.4 | K279: 1001.2 | L279: 1075 | M279: 1322.2 | N279: 1647.5 | O279: 1864.8 | P279: 1840.9 | Q279: 1786.3 | R279: 1845.9 | S279: 1842.4 | T279: 1599.5 | U279: 1641.1 | V279: 1683.3 | W279: 1778.8 | X279: 1901.5 | Y279: 1867.5 | Z279: 1858.9 | AA279: 1894 | AB279: 1918.7 | AC279: 1932.7 | AD279: 2079.8 | AE279: 2083.1 | AF279: 1907.8 | AG279: 2002 | AH279: 2437.3 | AI279: 2443.2 | AJ279: 2308.4 | AK279: 2602.7 | AL279: 2975.4 | AM279: 3538.7 | AN279: 3883.7 | AO279: 4096.1 | AP279: 4632.6 | AQ279: 3476.6 | AR279: 3925.5 | AS279: 4469 | AT279: 4317.5 | AU279: 4354.9 | AV279: 4382.8 | AW279: 3518.3 | AX279: 3215.6 | AY279: 3495.2 | AZ279: 3891.6 | BA279: 3727.9 | BB279: 3040 | BC279: 3966.8
A280: 2021F | B280: US | C280: TETXD | D280: 1.65 | E280: 1.76 | F280: 1.84 | G280: 2.02 | H280: 2.87 | I280: 3.33 | J280: 3.57 | K280: 3.98 | L280: 4.23 | M280: 5.22 | N280: 6.89 | O280: 8.04 | P280: 8.47 | Q280: 8.4 | R280: 8.3 | S280: 8.38 | T280: 7.32 | U280: 7.36 | V280: 7.29 | W280: 7.59 | X280: 8.29 | Y280: 8.25 | Z280: 8.16 | AA280: 8.29 | AB280: 8.33 | AC280: 8.31 | AD280: 8.77 | AE280: 8.83 | AF280: 8.22 | AG280: 8.58 | AH280: 10.33 | AI280: 10.78 | AJ280: 10.1 | AK280: 11.44 | AL280: 12.9 | AM280: 15.57 | AN280: 17.4 | AO280: 18.34 | AP280: 21.53 | AQ280: 17.26 | AR280: 18.92 | AS280: 21.87 | AT280: 21.84 | AU280: 21.42 | AV280: 21.33 | AW280: 17.31 | AX280: 15.95 | AY280: 17.32 | AZ280: 18.61 | BA280: 17.96 | BB280: 16.25 | BC280: 19.99
A281: 2021F | B281: US | C281: TETXV | D281: 82874.8 | E281: 90037.8 | F281: 98070.2 | G281: 111894.2 | H281: 153369 | I281: 171853.7 | J281: 193915.8 | K281: 220499.1 | L281: 239280.2 | M281: 297574.6 | N281: 374350 | O281: 427901.2 | P281: 426482 | Q281: 417621.5 | R281: 435312.9 | S281: 438343.1 | T281: 384090.9 | U281: 397626.6 | V281: 411568.4 | W281: 439051.3 | X281: 474652.2 | Y281: 472439.6 | Z281: 476845 | AA281: 492274.6 | AB281: 504856.4 | AC281: 514623.5 | AD281: 560292.9 | AE281: 567961.8 | AF281: 526282.6 | AG281: 558626.7 | AH281: 687710.9 | AI281: 696242.1 | AJ281: 663964.4 | AK281: 755070.3 | AL281: 871210.2 | AM281: 1045730.4 | AN281: 1158820.6 | AO281: 1233868.7 | AP281: 1408759.3 | AQ281: 1066528.4 | AR281: 1214277.5 | AS281: 1392467.9 | AT281: 1355174.7 | AU281: 1376402.2 | AV281: 1395430.4 | AW281: 1128447.4 | AX281: 1038883.6 | AY281: 1136379.4 | AZ281: 1271930.6 | BA281: 1223984.5 | BB281: 1007785.4 | BC281: 1317098.4
A282: 2021F | B282: US | C282: TNASB | D282: 15328091 | E282: 15939288 | F282: 16905762 | G282: 17845094 | H282: 17412119 | I282: 17626080 | J282: 18518058 | K282: 19253922 | L282: 20053920 | M282: 19835617 | N282: 19020336 | O282: 18830141 | P282: 18451007 | Q282: 18641437 | R282: 19078008 | S282: 19536040 | T282: 20255656 | U282: 20898829 | V282: 21650554 | W282: 21791321 | X282: 21702674 | Y282: 21460821 | Z282: 21772453 | AA282: 21995395 | AB282: 22578251 | AC282: 23057481 | AD282: 23652957 | AE282: 23915943 | AF282: 24533077 | AG282: 25216131 | AH282: 25818685 | AI282: 25557506 | AJ282: 26085085 | AK282: 26226305 | AL282: 27195887 | AM282: 27602105 | AN282: 28021124 | AO282: 28087446 | AP282: 26683115 | AQ282: 25872486 | AR282: 26243076 | AS282: 25839366 | AT282: 25325503 | AU282: 25706435 | AV282: 26097623 | AW282: 26491125 | AX282: 27032177 | AY282: 27226047 | AZ282: 27515316 | BA282: 27488325 | BB282: 23268705 | BC282: 25862052
... A310: 2021F | B310: US | C310: ZWHDP | D310: 5216 | E310: 5070 | F310: 5248 | G310: 4762 | H310: 4880 | I310: 4903 | J310: 5179 | K310: 5014 | L310: 5382 | M310: 5166 | N310: 5077 | O310: 4851 | P310: 4936 | Q310: 4906 | R310: 4775 | S310: 4888 | T310: 4519 | U310: 4532 | V310: 4840 | W310: 4894 | X310: 4180 | Y310: 4347 | Z310: 4584 | AA310: 4837 | AB310: 4609 | AC310: 4640 | AD310: 4800 | AE310: 4629 | AF310: 4051 | AG310: 4232 | AH310: 4493 | AI310: 4256 | AJ310: 4356 | AK310: 4544 | AL310: 4344 | AM310: 4348 | AN310: 4040 | AO310: 4268 | AP310: 4494 | AQ310: 4480 | AR310: 4463 | AS310: 4314 | AT310: 3773 | AU310: 4472 | AV310: 4560 | AW310: 4096 | AX310: 3889 | AY310: 3840 | AZ310: 4293 | BA310: 4320 | BB310: 3916 | BC310: 3937

Sheet SEDS Data Processed
A1: dataset: | B1: gdp | C1: gdp | D1: gdp | F1: sedsPE | G1: sedsPE | H1: sedsPE | N1: sedsQ | O1: sedsQ | P1: sedsQ | Q1: sedsQ | S1: sedsPE | T1: sedsPE | U1: sedsPE | V1: sedsPE | AT1: sedsPE | AU1: sedsPE | AV1: sedsPE | BB1: sedsQ | BC1: sedsQ | BD1: sedsQ | BE1: sedsQ
A2: 9.209 | B2: U.S. Gross Domestic Product, Nominal | C2: U.S. Gross Domestic Product, Real | D2: U.S. Gross Domestic Product Implicit Price Deflator | F2: TNSCB | G2: TETXV | H2: TETXD | N2: CLTXB | O2: NGTXB | P2: PATXB | Q2: ESTXB | S2: CLTXD | T2: NGTXD | U2: PATXD | V2: ESTXD | AT2: CLTCV | AU2: PATCV | AV2: NGTCV | BB2: CLTCB | BC2: PATCB | BD2: NGTCB | BE2: RETCB
A3: Original Description | B3: =B2 -> U.S. Gross Domestic Product, Nominal | C3: =C2 -> U.S. Gross Domestic Product, Real | D3: =D2 -> U.S. Gross Domestic Product Implicit Price Deflator | F3: =IF(ISERROR(VLOOKUP(F$2,code,2,)),"",VLOOKUP(F$2,code,2,)) -> Total net energy consumption, adjusted for process fuel, intermediate products, and fuels with no direct cost | G3: =IF(ISERROR(VLOOKUP(G$2,code,2,)),"",VLOOKUP(G$2,code,2,)) -> Total end-use energy expenditures | H3: =IF(ISERROR(VLOOKUP(H$2,code,2,)),"",VLOOKUP(H$2,code,2,)) -> Total end-use energy average price | I3: =IF(ISERROR(VLOOKUP(I$2,code,2,)),"",VLOOKUP(I$2,code,2,)) | J3: =IF(ISERROR(VLOOKUP(J$2,code,2,)),"",VLOOKUP(J$2,code,2,)) | K3: =IF(ISERROR(VLOOKUP(K$2,code,2,)),"",VLOOKUP(K$2,code,2,)) | L3: =IF(ISERROR(VLOOKUP(L$2,code,2,)),"",VLOOKUP(L$2,code,2,)) | M3: =IF(ISERROR(VLOOKUP(M$2,code,2,)),"",VLOOKUP(M$2,code,2,)) | ... BE3: =IF(ISERROR(VLOOKUP(BE$2,code,2,)),"",VLOOKUP(BE$2,code,2,)) -> Renewable energy total consumption | BG3: =IF(ISERROR(VLOOKUP(BG$2,code,2,)),"",VLOOKUP(BG$2,code,2,)) | BH3: =IF(ISERROR(VLOOKUP(BH$2,code,2,)),"",VLOOKUP(BH$2,code,2,)) | BJ3: =IF(ISERROR(VLOOKUP(BJ$2,code,2,)),"",VLOOKUP(BJ$2,code,2,)) | BK3: =IF(ISERROR(VLOOKUP(BK$2,code,2,)),"",VLOOKUP(BK$2,code,2,)) | BM3: =IF(ISERROR(VLOOKUP(BM$2,code,2,)),"",VLOOKUP(BM$2,code,2,)) | BN3: =IF(ISERROR(VLOOKUP(BN$2,code,2,)),"",VLOOKUP(BN$2,code,2,)) | BO3: =IF(ISERROR(VLOOKUP(BO$2,code,2,)),"",VLOOKUP(BO$2,code,2,)) | BP3: =IF(ISERROR(VLOOKUP(BP$2,code,2,)),"",VLOOKUP(BP$2,code,2,)) | BQ3: =IF(ISERROR(VLOOKUP(BQ$2,code,2,)),"",VLOOKUP(BQ$2,code,2,)) | BR3: =IF(ISERROR(VLOOKUP(BR$2,code,2,)),"",VLOOKUP(BR$2,code,2,)) | BS3: =IF(ISERROR(VLOOKUP(BS$2,code,2,)),"",VLOOKUP(BS$2,code,2,)) | BT3: =IF(ISERROR(VLOOKUP(BT$2,code,2,)),"",VLOOKUP(BT$2,code,2,)) | ... DA3: =IF(ISERROR(VLOOKUP(DA$2,code,2,)),"",VLOOKUP(DA$2,code,2,))
A5: outgoing ID: | B5: GDP_nominal | C5: GDP_real | D5: GDP_deflator | F5: FE_quantity_simple | K5: FE_realprice_simple | L5: FE_expshare_simple | AM5: FE_quantity_HKO | AQ5: FE_realprice_HKO | AR5: FE_expshare_HKO | BH5: FF_shareofenexp_simple | BK5: FF_realprice_simple
N7: HKO Approach | AT7: Primary Energy: Simple
B9: GDP Data | F9: Simple Approach | N9: End-Use Quantities | S9: Nominal Prices | X9: Real Prices | AC9: Prices Relative to Electricity | AH9: Adjusted Quantity | AM9: Final Calculations | AT9: Nominal Expenditure | AX9: Real Expenditure | BB9: Quantities | BG9: Totals
B10: Nominal GDP | C10: Real GDP | D10: GDP Deflator | F10: Total Final Energy Consumption | G10: Total Final Energy Expenditure | H10: Total Final Energy Price | I10: Diff | J10: Real Final Expenditure | K10: Real Final price | L10: Expenditure Share | N10: Coal | O10: Natural Gas | P10: Petroleum Products | Q10: Electricity | S10: Coal | T10: Natural Gas | U10: Petroleum Products | V10: Electricity | X10: Coal | Y10: Natural Gas | Z10: Petroleum Products | AA10: Electricity | AC10: Coal | AD10: Natural Gas | AE10: Petroleum Products | AF10: Electricity | AH10: Coal | AI10: Natural Gas | AJ10: Petroleum Products | AK10: Electricity | AM10: Total Quantity | AN10: Nominal Expenditure | AO10: Expenditure Difference | AP10: Real Expenditure | AQ10: Average Real Price | AR10: Expenditure Share | AT10: Coal | AU10: Oil | AV10: Natural Gas | AX10: Coal | AY10: Oil | AZ10: Natural Gas | BB10: Coal | BC10: Oil | BD10: Natural Gas | BE10: Renewables | BG10: Nominal Expenditure | BH10: Share of Energy Expenditure | BI10: Quantity | BJ10: Nominal Price | BK10: Real Price | BM10: Clean-Dirty Ratio | BO10: Fossil Fuel Share of GDP
A11: Units | B11: =VLOOKUP($A11,INDIRECT(B1),MATCH(B3,INDIRECT(B1&"_col"),),) -> (Billion Dollars) | C11: =VLOOKUP($A11,INDIRECT(C1),MATCH(C3,INDIRECT(C1&"_col"),),) -> (Billion chained (2012) dollars) | D11: =VLOOKUP($A11,INDIRECT(D1),MATCH(D3,INDIRECT(D1&"_col"),),) -> (2012 = 1.00000) | F11: =IF(ISERROR(VLOOKUP(F$2,code,3,)),"",VLOOKUP(F$2,code,3,)) -> Billion Btu | G11: =VLOOKUP(G$2,code,3,) -> Million dollars | H11: =VLOOKUP(H$2,code,3,) -> Dollars per million Btu | I11: (%) | J11: (Millions $2012) | K11: $2012/Million BTU | L11: % of Nominal GDP | N11: =VLOOKUP(N$2,code,3,) -> Billion Btu | O11: =VLOOKUP(O$2,code,3,) -> Billion Btu | P11: =VLOOKUP(P$2,code,3,) -> Billion Btu | Q11: =VLOOKUP(Q$2,code,3,) -> Billion Btu | S11: =VLOOKUP(S$2,code,3,) -> Dollars per million Btu | T11: =VLOOKUP(T$2,code,3,) -> Dollars per million Btu | U11: =VLOOKUP(U$2,code,3,) -> Dollars per million Btu | V11: =VLOOKUP(V$2,code,3,) -> Dollars per million Btu | X11: $2012 per million BTU | Y11: $2012 per million BTU | Z11: $2012 per million BTU | AA11: $2012 per million BTU | AC11: % | AD11: % | AE11: % | AF11: % | AH11: Billions BTUs of Electricity | AI11: Billions BTUs of Electricity | AJ11: Billions BTUs of Electricity | AK11: Billions BTUs of Electricity | AM11: Billions BTUs of Electricity | AN11: Thousands of dollars | AO11: % | AP11: $2012 Thousands | AQ11: $2012 per million BTUs of electricity | AR11: % | AT11: =VLOOKUP(AT$2,code,3,) -> Million dollars | AU11: =VLOOKUP(AU$2,code,3,) -> Million dollars | AV11: =VLOOKUP(AV$2,code,3,) -> Million dollars | AX11: $2012 Million | AY11: $2012 Million | AZ11: $2012 Million | BB11: =VLOOKUP(BB$2,code,3,) -> Billion Btu | BC11: =VLOOKUP(BC$2,code,3,) -> Billion Btu | BD11: =VLOOKUP(BD$2,code,3,) -> Billion Btu | BG11: Million dollars | BH11: % | BI11: Billion BTU | BJ11: $ per thousand BTUs | BK11: $2012 per BTU
A12: Year/Average | B12: =IF(ISERROR(AVERAGE(B13:B66)),"",AVERAGE(B13:B66)) -> 9318.9904 | C12: =IF(ISERROR(AVERAGE(C13:C66)),"",AVERAGE(C13:C66)) -> 11494.558 | D12: =IF(ISERROR(AVERAGE(D13:D66)),"",AVERAGE(D13:D66)) -> 0.70479596 | E12: =IF(ISERROR(AVERAGE(E13:E66)),"",AVERAGE(E13:E66)) | F12: =IF(ISERROR(AVERAGE(F13:F66)),"",AVERAGE(F13:F66)) -> 60043692 | G12: =IF(ISERROR(AVERAGE(G13:G66)),"",AVERAGE(G13:G66)) -> 680898.84 | H12: =IF(ISERROR(AVERAGE(H13:H66)),"",AVERAGE(H13:H66)) -> 10.903077 | I12: =IF(ISERROR(AVERAGE(I13:I66)),"",AVERAGE(I13:I66)) -> 0.00031599637 | ... AK12: =IF(ISERROR(AVERAGE(AK13:AK66)),"",AVERAGE(AK13:AK66)) -> 9934292.9 | AM12: =AVERAGE(AM13:AM66) -> 31644413 | AN12: =AVERAGE(AN13:AN66) -> 7.1866282e+08 | AO12: =AVERAGE(AO13:AO66) -> 0.055787265 | AP12: =AVERAGE(AP13:AP66) -> 9.2826827e+08 | AQ12: =AVERAGE(AQ13:AQ66) -> 28.914954 | AR12: =AVERAGE(AR13:AR66) -> 0.085822678 | AT12: =AVERAGE(AT13:AT64) -> 27952.104 | AU12: =AVERAGE(AU13:AU64) -> 378415.56 | AV12: =AVERAGE(AV13:AV64) -> 98454.798 | AX12: =AVERAGE(AX13:AX64) -> 40481.387 | AY12: =AVERAGE(AY13:AY64) -> 486184.21 | AZ12: =AVERAGE(AZ13:AZ64) -> 128059.93 | BB12: =AVERAGE(BB13:BB64) -> 17433425 | BC12: =AVERAGE(BC13:BC64) -> 35332071 | BD12: =AVERAGE(BD13:BD64) -> 22904890 | BE12: =AVERAGE(BE13:BE64) -> 6827001 | BG12: =AVERAGE(BG13:BG64) -> 504822.46 | BH12: =AVERAGE(BH13:BH64) -> 0.74030841 | BI12: =AVERAGE(BI13:BI64) -> 75670386 | BJ12: =AVERAGE(BJ13:BJ64) -> 0.0064339292 | BK12: =AVERAGE(BK13:BK64) -> 8.5603981 | BM12: =AVERAGE(BM13:BM64) -> 0.29455207 | BO12: =AVERAGE(BO13:BO64) -> 0.060918568
A13: 1970 | B13: =IF(ISERROR(VLOOKUP($A13,INDIRECT(B$1),MATCH(B$2,INDIRECT(B$1&"_col"),),)),"",VLOOKUP($A13,INDIRECT(B$1),MATCH(B$2,INDIRECT(B$1&"_col"),),)) -> 1073.3 | C13: =IF(ISERROR(VLOOKUP($A13,INDIRECT(C$1),MATCH(C$2,INDIRECT(C$1&"_col"),),)),"",VLOOKUP($A13,INDIRECT(C$1),MATCH(C$2,INDIRECT(C$1&"_col"),),)) -> 4954.4 | D13: =IF(ISERROR(VLOOKUP($A13,INDIRECT(D$1),MATCH(D$2,INDIRECT(D$1&"_col"),),)),"",VLOOKUP($A13,INDIRECT(D$1),MATCH(D$2,INDIRECT(D$1&"_col"),),)) -> 0.21663 | F13: =IF(ISERROR(VLOOKUP(F$2,INDIRECT(F$1),MATCH($A13,INDIRECT(F$1&"_col"),),)),"",VLOOKUP(F$2,INDIRECT(F$1),MATCH($A13,INDIRECT(F$1&"_col"),),)) -> 50199863 | G13: =IF(ISERROR(VLOOKUP(G$2,INDIRECT(G$1),MATCH($A13,INDIRECT(G$1&"_col"),),)),"",VLOOKUP(G$2,INDIRECT(G$1),MATCH($A13,INDIRECT(G$1&"_col"),),)) -> 82874.8 | H13: =IF(ISERROR(VLOOKUP(H$2,INDIRECT(H$1),MATCH($A13,INDIRECT(H$1&"_col"),),)),"",VLOOKUP(H$2,INDIRECT(H$1),MATCH($A13,INDIRECT(H$1&"_col"),),)) -> 1.65 | I13: =ABS(F13*H13/1000 - G13)/G13 -> 0.00054330207 | J13: =G13/D13 -> 382563.82 | K13: =H13/D13 -> 7.6166736 | L13: =G13/1000/B13 -> 0.077214945 | N13: =IF(ISERROR(VLOOKUP(N$2,INDIRECT(N$1),MATCH($A13,INDIRECT(N$1&"_col"),),)),"",VLOOKUP(N$2,INDIRECT(N$1),MATCH($A13,INDIRECT(N$1&"_col"),),)) -> 5040889 | O13: =IF(ISERROR(VLOOKUP(O$2,INDIRECT(O$1),MATCH($A13,INDIRECT(O$1&"_col"),),)),"",VLOOKUP(O$2,INDIRECT(O$1),MATCH($A13,INDIRECT(O$1&"_col"),),)) -> 17645102 | P13: =IF(ISERROR(VLOOKUP(P$2,INDIRECT(P$1),MATCH($A13,INDIRECT(P$1&"_col"),),)),"",VLOOKUP(P$2,INDIRECT(P$1),MATCH($A13,INDIRECT(P$1&"_col"),),)) -> 27382775 | Q13: =IF(ISERROR(VLOOKUP(Q$2,INDIRECT(Q$1),MATCH($A13,INDIRECT(Q$1&"_col"),),)),"",VLOOKUP(Q$2,INDIRECT(Q$1),MATCH($A13,INDIRECT(Q$1&"_col"),),)) -> 4750527 | S13: =IF(ISERROR(VLOOKUP(S$2,INDIRECT(S$1),MATCH($A13,INDIRECT(S$1&"_col"),),)),"",VLOOKUP(S$2,INDIRECT(S$1),MATCH($A13,INDIRECT(S$1&"_col"),),)) -> 0.48 | T13: =IF(ISERROR(VLOOKUP(T$2,INDIRECT(T$1),MATCH($A13,INDIRECT(T$1&"_col"),),)),"",VLOOKUP(T$2,INDIRECT(T$1),MATCH($A13,INDIRECT(T$1&"_col"),),)) -> 0.68 | U13: =IF(ISERROR(VLOOKUP(U$2,INDIRECT(U$1),MATCH($A13,INDIRECT(U$1&"_col"),),)),"",VLOOKUP(U$2,INDIRECT(U$1),MATCH($A13,INDIRECT(U$1&"_col"),),)) -> 1.82 | V13: =IF(ISERROR(VLOOKUP(V$2,INDIRECT(V$1),MATCH($A13,INDIRECT(V$1&"_col"),),)),"",VLOOKUP(V$2,INDIRECT(V$1),MATCH($A13,INDIRECT(V$1&"_col"),),)) -> 4.98 | X13: =IF(ISERROR(S13/$D13),"",S13/$D13) -> 2.2157596 | Y13: =IF(ISERROR(T13/$D13),"",T13/$D13) -> 3.1389928 | Z13: =IF(ISERROR(U13/$D13),"",U13/$D13) -> 8.4014218 | AA13: =IF(ISERROR(V13/$D13),"",V13/$D13) -> 22.988506 | AC13: =IF(ISERROR(X13/$AA13),"",X13/$AA13) -> 0.096385542 | AD13: =IF(ISERROR(Y13/$AA13),"",Y13/$AA13) -> 0.13654618 | AE13: =IF(ISERROR(Z13/$AA13),"",Z13/$AA13) -> 0.36546185 | AF13: =IF(ISERROR(AA13/$AA13),"",AA13/$AA13) -> 1 | AH13: =IF(ISERROR(N13*AC$12),"",N13*AC$12) -> 547564.64 | AI13: =IF(ISERROR(O13*AD$12),"",O13*AD$12) -> 4343187.7 | AJ13: =IF(ISERROR(P13*AE$12),"",P13*AE$12) -> 13828304 | AK13: =IF(ISERROR(Q13*AF$12),"",Q13*AF$12) -> 4750527 | AM13: =SUM(AH13:AK13) -> 23469583 | AN13: =SUMPRODUCT(S13:V13,N13:Q13) -> 87912571 | AO13: =ABS(AN13/1000-G13)/G13 -> 0.060787731 | AP13: =SUMPRODUCT(N13:Q13,X13:AA13) -> 4.05819e+08 | AQ13: =AP13/AM13 -> 17.291274 | AR13: =AN13/B13/1000000 -> 0.081908666 | AT13: =IF(ISERROR(VLOOKUP(AT$2,INDIRECT(AT$1),MATCH($A13,INDIRECT(AT$1&"_col"),),)),"",VLOOKUP(AT$2,INDIRECT(AT$1),MATCH($A13,INDIRECT(AT$1&"_col"),),)) -> 4630.3 | AU13: =IF(ISERROR(VLOOKUP(AU$2,INDIRECT(AU$1),MATCH($A13,INDIRECT(AU$1&"_col"),),)),"",VLOOKUP(AU$2,INDIRECT(AU$1),MATCH($A13,INDIRECT(AU$1&"_col"),),)) -> 47903.8 | AV13: =IF(ISERROR(VLOOKUP(AV$2,INDIRECT(AV$1),MATCH($A13,INDIRECT(AV$1&"_col"),),)),"",VLOOKUP(AV$2,INDIRECT(AV$1),MATCH($A13,INDIRECT(AV$1&"_col"),),)) -> 10891.4 | AX13: =AT13/$D13 -> 21374.233 | AY13: =AU13/$D13 -> 221131.88 | AZ13: =AV13/$D13 -> 50276.508 | BB13: =IF(ISERROR(VLOOKUP(BB$2,INDIRECT(BB$1),MATCH($A13,INDIRECT(BB$1&"_col"),),)),"",VLOOKUP(BB$2,INDIRECT(BB$1),MATCH($A13,INDIRECT(BB$1&"_col"),),)) -> 12268895 | BC13: =IF(ISERROR(VLOOKUP(BC$2,INDIRECT(BC$1),MATCH($A13,INDIRECT(BC$1&"_col"),),)),"",VLOOKUP(BC$2,INDIRECT(BC$1),MATCH($A13,INDIRECT(BC$1&"_col"),),)) -> 29500112 | BD13: =IF(ISERROR(VLOOKUP(BD$2,INDIRECT(BD$1),MATCH($A13,INDIRECT(BD$1&"_col"),),)),"",VLOOKUP(BD$2,INDIRECT(BD$1),MATCH($A13,INDIRECT(BD$1&"_col"),),)) -> 21692710 | BE13: =IF(ISERROR(VLOOKUP(BE$2,INDIRECT(BE$1),MATCH($A13,INDIRECT(BE$1&"_col"),),)),"",VLOOKUP(BE$2,INDIRECT(BE$1),MATCH($A13,INDIRECT(BE$1&"_col"),),)) -> 4070021 | BG13: =SUM(AT13:AV13) -> 63425.5 | BH13: =BG13/G13 -> 0.76531708 | BI13: =SUM(BB13:BD13) -> 63461717 | BJ13: =BG13/BI13 -> 0.00099942931 | BK13: =BJ13/$D13*1000 -> 4.6135314 | BM13: =BE13/BD13 -> 0.1876216 | BO13: =BG13/B13/1000 -> 0.059093916
